Workbook

Sheet Gastos
A1: Media 2013 | B1: Media 2014 | C1: Media 2015 | D1: Media 2016 | E1: Gastos Fijos 2015 | F1: TOTAL Anual | G1: Total Comerc. | H1: Total Tiendas | I1: Total M.Free | J1: C.Enero | K1: T.Enero | L1: M.Enero | M1: Total Enero | N1: C.Febrero | O1: T.Febrero | P1: M.Febrero | Q1: Total Febrero | R1: C.Marzo | S1: T.Marzo | T1: M.Marzo | U1: Total Marzo | V1: C.Abril | W1: T.Abril | X1: M.Abril | Y1: Total Abril | Z1: C.Mayo | AA1: T.Mayo | AB1: M.Mayo | AC1: Total Mayo | AD1: C.Junio | AE1: T.Junio | AF1: M.Junio | AG1: Total Junio | AH1: C.Julio | AI1: T.Julio | AJ1: M.Julio | AK1: Total Julio | AL1: C.Agosto | AM1: T.Agosto | AN1: M.Agosto | AO1: Total Agosto | AP1: C.Septiem. | AQ1: T.Septiem. | AR1: M.Septiem. | AS1: Total Septiem. | AT1: C.Octubre | AU1: T.Octubre | AV1: M.Octubre | AW1: Total Octubre | AX1: C.Noviem. | AY1: T.Noviem. | AZ1: M.Noviem. | BA1: Total Noviem. | BB1: C.Diciem. | BC1: T.Diciem. | BD1: M.Diciem. | BE1: Total Diciem.
A2: 30502.2 | B2: 30428.2 | C2: 30416.98 | D2: =F2/12 -> 30763.153 | E2: Sueldos | F2: =M2+Q2+U2+Y2+AC2+AG2+AK2+AO2+AS2+AW2+BA2+BE2 -> 369157.84 | G2: =J2+N2+R2+V2+Z2+AD2+AH2+AL2+AP2+AT2+AX2+BB2 -> 152592.93 | H2: =K2+O2+S2+W2+AA2+AE2+AI2+AM2+AQ2+AU2+AY2+BC2 -> 197536.09 | I2: =L2+P2+T2+X2+AB2+AF2+AJ2+AN2+AR2+AV2+AZ2+BD2 -> 19028.82 | J2: 9500.61 | K2: 14095.83 | L2: 1355.27 | M2: =J2+K2+L2 -> 24951.71 | N2: 9500.61 | O2: 13859.62 | P2: 1355.27 | Q2: =N2+O2+P2 -> 24715.5 | R2: 9500.61 | S2: 14139.46 | T2: 1355.27 | U2: =R2+S2+T2 -> 24995.34 | V2: 11679.22 | W2: 14143.96 | X2: 1347.83 | Y2: =V2+W2+X2 -> 27171.01 | Z2: 10872.77 | AA2: 14735.03 | AB2: 1347.83 | AC2: =Z2+AA2+AB2 -> 26955.63 | AD2: 11190.01 | AE2: 13768.93 | AF2: 1398.44 | AG2: =AD2+AE2+AF2 -> 26357.38 | AH2: 20581.33 | AI2: 26313.48 | AJ2: 2705.52 | AK2: =AH2+AI2+AJ2 -> 49600.33 | AL2: 12234.82 | AM2: 15830.22 | AN2: 1371.16 | AO2: =AL2+AM2+AN2 -> 29436.2 | AP2: 11705.18 | AQ2: 15647.33 | AR2: 1371.16 | AS2: =AP2+AQ2+AR2 -> 28723.67 | AT2: 12079.18 | AU2: 14218.68 | AV2: 1371.16 | AW2: =AT2+AU2+AV2 -> 27669.02 | AX2: 12983.3 | AY2: 15133.08 | AZ2: 1371.16 | BA2: =AX2+AY2+AZ2 -> 29487.54 | BB2: 20765.29 | BC2: 25650.47 | BD2: 2678.75 | BE2: =BB2+BC2+BD2 -> 49094.51
A3: 8379.53 | B3: 8988.94 | C3: 8590.61 | D3: =F3/12 -> 9028.5742 | E3: Seguridad Social Empresa | F3: =M3+Q3+U3+Y3+AC3+AG3+AK3+AO3+AS3+AW3+BA3+BE3 -> 108342.89 | G3: =J3+N3+R3+V3+Z3+AD3+AH3+AL3+AP3+AT3+AX3+BB3 -> 47913.59 | H3: =K3+O3+S3+W3+AA3+AE3+AI3+AM3+AQ3+AU3+AY3+BC3 -> 59942.75 | I3: =L3+P3+T3+X3+AB3+AF3+AJ3+AN3+AR3+AV3+AZ3+BD3 -> 486.55 | J3: 3430.85 | K3: 4995.31 | L3: 34.26 | M3: =J3+K3+L3 -> 8460.42 | N3: 3430.85 | O3: 4863.6 | P3: 34.26 | Q3: =N3+O3+P3 -> 8328.71 | R3: 3430.85 | S3: 5008.95 | T3: 34.26 | U3: =R3+S3+T3 -> 8474.06 | V3: 3793.47 | W3: 5004.96 | X3: 32.63 | Y3: =V3+W3+X3 -> 8831.06 | Z3: 3635.76 | AA3: 5004.96 | AB3: 32.63 | AC3: =Z3+AA3+AB3 -> 8673.35 | AD3: 4032.28 | AE3: 4955 | AF3: 50.18 | AG3: =AD3+AE3+AF3 -> 9037.46 | AH3: 4032.28 | AI3: 4973 | AJ3: 50.18 | AK3: =AH3+AI3+AJ3 -> 9055.46 | AL3: 4382.61 | AM3: 5621.42 | AN3: 43.63 | AO3: =AL3+AM3+AN3 -> 10047.66 | AP3: 4382.61 | AQ3: 5203.03 | AR3: 43.63 | AS3: =AP3+AQ3+AR3 -> 9629.27 | AT3: 4312.61 | AU3: 4756.84 | AV3: 43.63 | AW3: =AT3+AU3+AV3 -> 9113.08 | AX3: 4501.21 | AY3: 4756.84 | AZ3: 43.63 | BA3: =AX3+AY3+AZ3 -> 9301.68 | BB3: 4548.21 | BC3: 4798.84 | BD3: 43.63 | BE3: =BB3+BC3+BD3 -> 9390.68
A4: 7078.55 | B4: 5971.87 | C4: 5292.21 | D4: =F4/12 -> 5349.9117 | E4: Arrendamientos | F4: =M4+Q4+U4+Y4+AC4+AG4+AK4+AO4+AS4+AW4+BA4+BE4 -> 64198.94 | G4: =J4+N4+R4+V4+Z4+AD4+AH4+AL4+AP4+AT4+AX4+BB4 -> 10485.6 | H4: =K4+O4+S4+W4+AA4+AE4+AI4+AM4+AQ4+AU4+AY4+BC4 -> 42913.34 | I4: =L4+P4+T4+X4+AB4+AF4+AJ4+AN4+AR4+AV4+AZ4+BD4 -> 10800 | J4: 873.8 | K4: 3540.9 | L4: 900 | M4: =J4+K4+L4 -> 5314.7 | N4: 873.8 | O4: 3540.9 | P4: 900 | Q4: =N4+O4+P4 -> 5314.7 | R4: 873.8 | S4: 3540.9 | T4: 900 | U4: =R4+S4+T4 -> 5314.7 | V4: 873.8 | W4: 3540.9 | X4: 900 | Y4: =V4+W4+X4 -> 5314.7 | Z4: 873.8 | AA4: 3540.9 | AB4: 900 | AC4: =Z4+AA4+AB4 -> 5314.7 | AD4: 873.8 | AE4: 3540.9 | AF4: 900 | AG4: =AD4+AE4+AF4 -> 5314.7 | AH4: 873.8 | AI4: 3540.9 | AJ4: 900 | AK4: =AH4+AI4+AJ4 -> 5314.7 | AL4: 873.8 | AM4: 3623.8 | AN4: 900 | AO4: =AL4+AM4+AN4 -> 5397.6 | AP4: 873.8 | AQ4: 3623.8 | AR4: 900 | AS4: =AP4+AQ4+AR4 -> 5397.6 | AT4: 873.8 | AU4: 3623.8 | AV4: 900 | AW4: =AT4+AU4+AV4 -> 5397.6 | AX4: 873.8 | AY4: 3627.82 | AZ4: 900 | BA4: =AX4+AY4+AZ4 -> 5401.62 | BB4: 873.8 | BC4: 3627.82 | BD4: 900 | BE4: =BB4+BC4+BD4 -> 5401.62
A5: 849.29 | B5: 579.41 | C5: 655.73 | D5: =F5/12 -> 660.05667 | E5: Luz | F5: =M5+Q5+U5+Y5+AC5+AG5+AK5+AO5+AS5+AW5+BA5+BE5 -> 7920.68 | G5: =J5+N5+R5+V5+Z5+AD5+AH5+AL5+AP5+AT5+AX5+BB5 -> 1207.22 | H5: =K5+O5+S5+W5+AA5+AE5+AI5+AM5+AQ5+AU5+AY5+BC5 -> 5856.34 | I5: =L5+P5+T5+X5+AB5+AF5+AJ5+AN5+AR5+AV5+AZ5+BD5 -> 857.12 | J5: 120.25 | K5: 484.99 | L5: 0 | M5: =J5+K5+L5 -> 605.24 | N5: 128.86 | O5: 493.96 | P5: 114.09 | Q5: =N5+O5+P5 -> 736.91 | R5: 86.9 | S5: 687.96 | T5: 74.87 | U5: =R5+S5+T5 -> 849.73 | V5: 131.62 | W5: 397.35 | X5: 77.82 | Y5: =V5+W5+X5 -> 606.79 | Z5: 80.42 | AA5: 520.66 | AB5: 74.58 | AC5: =Z5+AA5+AB5 -> 675.66 | AD5: 76.34 | AE5: 299.51 | AF5: 79.43 | AG5: =AD5+AE5+AF5 -> 455.28 | AH5: 88.12 | AI5: 617.71 | AJ5: 84.01 | AK5: =AH5+AI5+AJ5 -> 789.84 | AL5: 109.9 | AM5: 377.54 | AN5: 73.61 | AO5: =AL5+AM5+AN5 -> 561.05 | AP5: 109.69 | AQ5: 640.21 | AR5: 147.56 | AS5: =AP5+AQ5+AR5 -> 897.46 | AT5: 84.28 | AU5: 383.8 | AV5: 0 | AW5: =AT5+AU5+AV5 -> 468.08 | AX5: 79.21 | AY5: 754.75 | AZ5: 115.89 | BA5: =AX5+AY5+AZ5 -> 949.85 | BB5: 111.63 | BC5: 197.9 | BD5: 15.26 | BE5: =BB5+BC5+BD5 -> 324.79
A6: 837.9 | B6: 796.42 | C6: 667.77 | D6: =F6/12 -> 693.71083 | E6: Gasoil Solred | F6: =M6+Q6+U6+Y6+AC6+AG6+AK6+AO6+AS6+AW6+BA6+BE6 -> 8324.53 | G6: =J6+N6+R6+V6+Z6+AD6+AH6+AL6+AP6+AT6+AX6+BB6 -> 7547.64 | H6: =K6+O6+S6+W6+AA6+AE6+AI6+AM6+AQ6+AU6+AY6+BC6 -> 776.89 | I6: =L6+P6+T6+X6+AB6+AF6+AJ6+AN6+AR6+AV6+AZ6+BD6 -> 0 | J6: 541.94 | K6: 0 | L6: 0 | M6: =J6+K6+L6 -> 541.94 | N6: 660.64 | O6: 0 | P6: 0 | Q6: =N6+O6+P6 -> 660.64 | R6: 658.5 | S6: 0 | T6: 0 | U6: =R6+S6+T6 -> 658.5 | V6: 498.73 | W6: 0 | X6: 0 | Y6: =V6+W6+X6 -> 498.73 | Z6: 882.27 | AA6: 0 | AB6: 0 | AC6: =Z6+AA6+AB6 -> 882.27 | AD6: 990.69 | AE6: 0 | AF6: 0 | AG6: =AD6+AE6+AF6 -> 990.69 | AH6: 628.46 | AI6: 0 | AJ6: 0 | AK6: =AH6+AI6+AJ6 -> 628.46 | AL6: 706.77 | AM6: 0 | AN6: 0 | AO6: =AL6+AM6+AN6 -> 706.77 | AP6: 0 | AQ6: 776.89 | AR6: 0 | AS6: =AP6+AQ6+AR6 -> 776.89 | AT6: 763.29 | AU6: 0 | AV6: 0 | AW6: =AT6+AU6+AV6 -> 763.29 | AX6: 775.09 | AY6: 0 | AZ6: 0 | BA6: =AX6+AY6+AZ6 -> 775.09 | BB6: 441.26 | BC6: 0 | BD6: 0 | BE6: =BB6+BC6+BD6 -> 441.26
A7: 471.21 | B7: 394.88 | C7: 427.96 | D7: =F7/12 -> 433.07583 | E7: Teléfono Fijo | F7: =M7+Q7+U7+Y7+AC7+AG7+AK7+AO7+AS7+AW7+BA7+BE7 -> 5196.91 | G7: =J7+N7+R7+V7+Z7+AD7+AH7+AL7+AP7+AT7+AX7+BB7 -> 1636.4 | H7: =K7+O7+S7+W7+AA7+AE7+AI7+AM7+AQ7+AU7+AY7+BC7 -> 3176.98 | I7: =L7+P7+T7+X7+AB7+AF7+AJ7+AN7+AR7+AV7+AZ7+BD7 -> 383.53 | J7: 145.1 | K7: 301.02 | L7: 31.03 | M7: =J7+K7+L7 -> 477.15 | N7: 139.92 | O7: 213.19 | P7: 32.52 | Q7: =N7+O7+P7 -> 385.63 | R7: 148.92 | S7: 278.59 | T7: 34.4 | U7: =R7+S7+T7 -> 461.91 | V7: 124.31 | W7: 282.15 | X7: 37.13 | Y7: =V7+W7+X7 -> 443.59 | Z7: 145.92 | AA7: 214.09 | AB7: 23.94 | AC7: =Z7+AA7+AB7 -> 383.95 | AD7: 122.07 | AE7: 244.32 | AF7: 29.86 | AG7: =AD7+AE7+AF7 -> 396.25 | AH7: 119.45 | AI7: 241.92 | AJ7: 28.68 | AK7: =AH7+AI7+AJ7 -> 390.05 | AL7: 126.85 | AM7: 269.27 | AN7: 28.68 | AO7: =AL7+AM7+AN7 -> 424.8 | AP7: 151.89 | AQ7: 273.75 | AR7: 29.69 | AS7: =AP7+AQ7+AR7 -> 455.33 | AT7: 151.99 | AU7: 324.77 | AV7: 35.87 | AW7: =AT7+AU7+AV7 -> 512.63 | AX7: 128.81 | AY7: 265.94 | AZ7: 35.87 | BA7: =AX7+AY7+AZ7 -> 430.62 | BB7: 131.17 | BC7: 267.97 | BD7: 35.86 | BE7: =BB7+BC7+BD7 -> 435
A8: 445.93 | B8: 306.98 | C8: 330.28 | D8: =F8/12 -> 323.85833 | E8: Teléfono Móvil | F8: =M8+Q8+U8+Y8+AC8+AG8+AK8+AO8+AS8+AW8+BA8+BE8 -> 3886.3 | G8: =J8+N8+R8+V8+Z8+AD8+AH8+AL8+AP8+AT8+AX8+BB8 -> 2178.12 | H8: =K8+O8+S8+W8+AA8+AE8+AI8+AM8+AQ8+AU8+AY8+BC8 -> 1415.18 | I8: =L8+P8+T8+X8+AB8+AF8+AJ8+AN8+AR8+AV8+AZ8+BD8 -> 293 | J8: 167.65 | K8: 104.64 | L8: 22.65 | M8: =J8+K8+L8 -> 294.94 | N8: 172.65 | O8: 109.64 | P8: 22.65 | Q8: =N8+O8+P8 -> 304.94 | R8: 173.15 | S8: 113.44 | T8: 22.65 | U8: =R8+S8+T8 -> 309.24 | V8: 183.15 | W8: 123.44 | X8: 24.65 | Y8: =V8+W8+X8 -> 331.24 | Z8: 186.15 | AA8: 126.94 | AB8: 24.65 | AC8: =Z8+AA8+AB8 -> 337.74 | AD8: 186.15 | AE8: 126.04 | AF8: 24.25 | AG8: =AD8+AE8+AF8 -> 336.44 | AH8: 219.08 | AI8: 126.04 | AJ8: 24.25 | AK8: =AH8+AI8+AJ8 -> 369.37 | AL8: 193.15 | AM8: 132.04 | AN8: 24.25 | AO8: =AL8+AM8+AN8 -> 349.44 | AP8: 168.15 | AQ8: 107.04 | AR8: 24.25 | AS8: =AP8+AQ8+AR8 -> 299.44 | AT8: 175.15 | AU8: 114.04 | AV8: 26.25 | AW8: =AT8+AU8+AV8 -> 315.44 | AX8: 180.17 | AY8: 119.24 | AZ8: 26.25 | BA8: =AX8+AY8+AZ8 -> 325.66 | BB8: 173.52 | BC8: 112.64 | BD8: 26.25 | BE8: =BB8+BC8+BD8 -> 312.41
A9: 382.5 | B9: 390.84 | C9: 390.83 | D9: =F9/12 -> 378.33333 | E9: Asesoria Laboral | F9: =M9+Q9+U9+Y9+AC9+AG9+AK9+AO9+AS9+AW9+BA9+BE9 -> 4540 | G9: =J9+N9+R9+V9+Z9+AD9+AH9+AL9+AP9+AT9+AX9+BB9 -> 1587.1 | H9: =K9+O9+S9+W9+AA9+AE9+AI9+AM9+AQ9+AU9+AY9+BC9 -> 2697.53 | I9: =L9+P9+T9+X9+AB9+AF9+AJ9+AN9+AR9+AV9+AZ9+BD9 -> 255.37 | J9: 129.5 | K9: 222 | L9: 18.5 | M9: =J9+K9+L9 -> 370 | N9: 129.5 | O9: 222 | P9: 18.5 | Q9: =N9+O9+P9 -> 370 | R9: 129.5 | S9: 222 | T9: 18.5 | U9: =R9+S9+T9 -> 370 | V9: 129.5 | W9: 222 | X9: 18.5 | Y9: =V9+W9+X9 -> 370 | Z9: 129.5 | AA9: 222 | AB9: 18.5 | AC9: =Z9+AA9+AB9 -> 370 | AD9: 162.6 | AE9: 255.53 | AF9: 51.87 | AG9: =AD9+AE9+AF9 -> 470 | AH9: 129.5 | AI9: 222 | AJ9: 18.5 | AK9: =AH9+AI9+AJ9 -> 370 | AL9: 129.5 | AM9: 222 | AN9: 18.5 | AO9: =AL9+AM9+AN9 -> 370 | AP9: 129.5 | AQ9: 222 | AR9: 18.5 | AS9: =AP9+AQ9+AR9 -> 370 | AT9: 129.5 | AU9: 222 | AV9: 18.5 | AW9: =AT9+AU9+AV9 -> 370 | AX9: 129.5 | AY9: 222 | AZ9: 18.5 | BA9: =AX9+AY9+AZ9 -> 370 | BB9: 129.5 | BC9: 222 | BD9: 18.5 | BE9: =BB9+BC9+BD9 -> 370
A10: 175 | B10: 175 | C10: 170 | D10: =F10/12 -> 170 | E10: Abogado | F10: =M10+Q10+U10+Y10+AC10+AG10+AK10+AO10+AS10+AW10+BA10+BE10 -> 2040 | G10: =J10+N10+R10+V10+Z10+AD10+AH10+AL10+AP10+AT10+AX10+BB10 -> 714 | H10: =K10+O10+S10+W10+AA10+AE10+AI10+AM10+AQ10+AU10+AY10+BC10 -> 1224 | I10: =L10+P10+T10+X10+AB10+AF10+AJ10+AN10+AR10+AV10+AZ10+BD10 -> 102 | J10: 59.5 | K10: 102 | L10: 8.5 | M10: =J10+K10+L10 -> 170 | N10: 59.5 | O10: 102 | P10: 8.5 | Q10: =N10+O10+P10 -> 170 | R10: 59.5 | S10: 102 | T10: 8.5 | U10: =R10+S10+T10 -> 170 | V10: 59.5 | W10: 102 | X10: 8.5 | Y10: =V10+W10+X10 -> 170 | Z10: 59.5 | AA10: 102 | AB10: 8.5 | AC10: =Z10+AA10+AB10 -> 170 | AD10: 59.5 | AE10: 102 | AF10: 8.5 | AG10: =AD10+AE10+AF10 -> 170 | AH10: 59.5 | AI10: 102 | AJ10: 8.5 | AK10: =AH10+AI10+AJ10 -> 170 | AL10: 59.5 | AM10: 102 | AN10: 8.5 | AO10: =AL10+AM10+AN10 -> 170 | AP10: 59.5 | AQ10: 102 | AR10: 8.5 | AS10: =AP10+AQ10+AR10 -> 170 | AT10: 59.5 | AU10: 102 | AV10: 8.5 | AW10: =AT10+AU10+AV10 -> 170 | AX10: 59.5 | AY10: 102 | AZ10: 8.5 | BA10: =AX10+AY10+AZ10 -> 170 | BB10: 59.5 | BC10: 102 | BD10: 8.5 | BE10: =BB10+BC10+BD10 -> 170
A11: 115.38 | B11: 161.16 | C11: 277.69 | D11: =F11/12 -> 216.29417 | E11: Dietas JV y Coordinador | F11: =M11+Q11+U11+Y11+AC11+AG11+AK11+AO11+AS11+AW11+BA11+BE11 -> 2595.53 | G11: =J11+N11+R11+V11+Z11+AD11+AH11+AL11+AP11+AT11+AX11+BB11 -> 1030.24 | H11: =K11+O11+S11+W11+AA11+AE11+AI11+AM11+AQ11+AU11+AY11+BC11 -> 1565.29 | I11: =L11+P11+T11+X11+AB11+AF11+AJ11+AN11+AR11+AV11+AZ11+BD11 -> 0 | J11: 0 | K11: 200.5 | L11: 0 | M11: =J11+K11+L11 -> 200.5 | N11: 0 | O11: 140.3 | P11: 0 | Q11: =N11+O11+P11 -> 140.3 | R11: 0 | S11: 121.3 | T11: 0 | U11: =R11+S11+T11 -> 121.3 | V11: 87.75 | W11: 84.4 | X11: 0 | Y11: =V11+W11+X11 -> 172.15 | Z11: 96.55 | AA11: 122.8 | AB11: 0 | AC11: =Z11+AA11+AB11 -> 219.35 | AD11: 105.15 | AE11: 111.5 | AF11: 0 | AG11: =AD11+AE11+AF11 -> 216.65 | AH11: 30 | AI11: 203.4 | AJ11: 0 | AK11: =AH11+AI11+AJ11 -> 233.4 | AL11: 20 | AM11: 0 | AN11: 0 | AO11: =AL11+AM11+AN11 -> 20 | AP11: 255 | AQ11: 0 | AR11: 0 | AS11: =AP11+AQ11+AR11 -> 255 | AT11: 254.85 | AU11: 210.03 | AV11: 0 | AW11: =AT11+AU11+AV11 -> 464.88 | AX11: 88.94 | AY11: 150.23 | AZ11: 0 | BA11: =AX11+AY11+AZ11 -> 239.17 | BB11: 92 | BC11: 220.83 | BD11: 0 | BE11: =BB11+BC11+BD11 -> 312.83
A12: 80.42 | B12: 83.03 | C12: 62 | D12: =F12/12 -> 62 | E12: Limpieza de Cristales | F12: =M12+Q12+U12+Y12+AC12+AG12+AK12+AO12+AS12+AW12+BA12+BE12 -> 744 | G12: =J12+N12+R12+V12+Z12+AD12+AH12+AL12+AP12+AT12+AX12+BB12 -> 0 | H12: =K12+O12+S12+W12+AA12+AE12+AI12+AM12+AQ12+AU12+AY12+BC12 -> 562.56 | I12: =L12+P12+T12+X12+AB12+AF12+AJ12+AN12+AR12+AV12+AZ12+BD12 -> 181.44 | J12: 0 | K12: 46.88 | L12: 15.12 | M12: =J12+K12+L12 -> 62 | N12: 0 | O12: 46.88 | P12: 15.12 | Q12: =N12+O12+P12 -> 62 | R12: 0 | S12: 46.88 | T12: 15.12 | U12: =R12+S12+T12 -> 62 | V12: 0 | W12: 46.88 | X12: 15.12 | Y12: =V12+W12+X12 -> 62 | Z12: 0 | AA12: 46.88 | AB12: 15.12 | AC12: =Z12+AA12+AB12 -> 62 | AD12: 0 | AE12: 46.88 | AF12: 15.12 | AG12: =AD12+AE12+AF12 -> 62 | AH12: 0 | AI12: 46.88 | AJ12: 15.12 | AK12: =AH12+AI12+AJ12 -> 62 | AL12: 0 | AM12: 46.88 | AN12: 15.12 | AO12: =AL12+AM12+AN12 -> 62 | AP12: 0 | AQ12: 46.88 | AR12: 15.12 | AS12: =AP12+AQ12+AR12 -> 62 | AT12: 0 | AU12: 46.88 | AV12: 15.12 | AW12: =AT12+AU12+AV12 -> 62 | AX12: 0 | AY12: 46.88 | AZ12: 15.12 | BA12: =AX12+AY12+AZ12 -> 62 | BB12: 0 | BC12: 46.88 | BD12: 15.12 | BE12: =BB12+BC12+BD12 -> 62
A13: 79.25 | B13: 314.34 | C13: 301.01 | D13: =F13/12 -> 334.7175 | E13: Transportes | F13: =M13+Q13+U13+Y13+AC13+AG13+AK13+AO13+AS13+AW13+BA13+BE13 -> 4016.61 | G13: =J13+N13+R13+V13+Z13+AD13+AH13+AL13+AP13+AT13+AX13+BB13 -> 0 | H13: =K13+O13+S13+W13+AA13+AE13+AI13+AM13+AQ13+AU13+AY13+BC13 -> 3931.41 | I13: =L13+P13+T13+X13+AB13+AF13+AJ13+AN13+AR13+AV13+AZ13+BD13 -> 85.2 | J13: 0 | K13: 261.97 | L13: 5.8 | M13: =J13+K13+L13 -> 267.77 | N13: 0 | O13: 292.16 | P13: 5.8 | Q13: =N13+O13+P13 -> 297.96 | R13: 0 | S13: 239.1 | T13: 0 | U13: =R13+S13+T13 -> 239.1 | V13: 0 | W13: 524.2 | X13: 11.6 | Y13: =V13+W13+X13 -> 535.8 | Z13: 0 | AA13: 208.15 | AB13: 17.4 | AC13: =Z13+AA13+AB13 -> 225.55 | AD13: 0 | AE13: 291.33 | AF13: 0 | AG13: =AD13+AE13+AF13 -> 291.33 | AH13: 0 | AI13: 324.56 | AJ13: 0 | AK13: =AH13+AI13+AJ13 -> 324.56 | AL13: 0 | AM13: 320.37 | AN13: 11.6 | AO13: =AL13+AM13+AN13 -> 331.97 | AP13: 0 | AQ13: 277.43 | AR13: 0 | AS13: =AP13+AQ13+AR13 -> 277.43 | AT13: 0 | AU13: 515.07 | AV13: 11.6 | AW13: =AT13+AU13+AV13 -> 526.67 | AX13: 0 | AY13: 386.15 | AZ13: 11.6 | BA13: =AX13+AY13+AZ13 -> 397.75 | BB13: 0 | BC13: 290.92 | BD13: 9.8 | BE13: =BB13+BC13+BD13 -> 300.72
... A15: 40 | B15: 29.92 | C15: 21 | D15: =F15/12 -> 21 | E15: Comunidades | F15: =M15+Q15+U15+Y15+AC15+AG15+AK15+AO15+AS15+AW15+BA15+BE15 -> 252 | G15: =J15+N15+R15+V15+Z15+AD15+AH15+AL15+AP15+AT15+AX15+BB15 -> 0 | H15: =K15+O15+S15+W15+AA15+AE15+AI15+AM15+AQ15+AU15+AY15+BC15 -> 0 | I15: =L15+P15+T15+X15+AB15+AF15+AJ15+AN15+AR15+AV15+AZ15+BD15 -> 252 | J15: 0 | K15: 0 | L15: 21 | M15: =J15+K15+L15 -> 21 | N15: 0 | O15: 0 | P15: 21 | Q15: =N15+O15+P15 -> 21 | R15: 0 | S15: 0 | T15: 21 | U15: =R15+S15+T15 -> 21 | V15: 0 | W15: 0 | X15: 21 | Y15: =V15+W15+X15 -> 21 | Z15: 0 | AA15: 0 | AB15: 21 | AC15: =Z15+AA15+AB15 -> 21 | AD15: 0 | AE15: 0 | AF15: 21 | AG15: =AD15+AE15+AF15 -> 21 | AH15: 0 | AI15: 0 | AJ15: 21 | AK15: =AH15+AI15+AJ15 -> 21 | AL15: 0 | AM15: 0 | AN15: 21 | AO15: =AL15+AM15+AN15 -> 21 | AP15: 0 | AQ15: 0 | AR15: 21 | AS15: =AP15+AQ15+AR15 -> 21 | AT15: 0 | AU15: 0 | AV15: 21 | AW15: =AT15+AU15+AV15 -> 21 | AX15: 0 | AY15: 0 | AZ15: 21 | BA15: =AX15+AY15+AZ15 -> 21 | BB15: 0 | BC15: 0 | BD15: 21 | BE15: =BB15+BC15+BD15 -> 21
A16: 1082.71 | B16: 1082.72 | C16: 1029.01 | D16: =F16/12 -> 956.09667 | E16: Interes+Amort. Prestamo Piso | F16: =M16+Q16+U16+Y16+AC16+AG16+AK16+AO16+AS16+AW16+BA16+BE16 -> 11473.16 | G16: =J16+N16+R16+V16+Z16+AD16+AH16+AL16+AP16+AT16+AX16+BB16 -> 0 | H16: =K16+O16+S16+W16+AA16+AE16+AI16+AM16+AQ16+AU16+AY16+BC16 -> 0 | I16: =L16+P16+T16+X16+AB16+AF16+AJ16+AN16+AR16+AV16+AZ16+BD16 -> 0 | J16: 0 | K16: 0 | L16: 0 | M16: 975.99 | N16: 0 | O16: 0 | P16: 0 | Q16: 975.99 | R16: 0 | S16: 0 | T16: 0 | U16: 975.99 | V16: 0 | W16: 0 | X16: 0 | Y16: 975.99 | Z16: 0 | AA16: 0 | AB16: 0 | AC16: 975.99 | AD16: 0 | AE16: 0 | AF16: 0 | AG16: 975.99 | AH16: 0 | AI16: 0 | AJ16: 0 | AK16: 975.99 | AL16: 0 | AM16: 0 | AN16: 0 | AO16: 928.68 | AP16: 0 | AQ16: 0 | AR16: 0 | AS16: 928.68 | AT16: 0 | AU16: 0 | AV16: 0 | AW16: 928.68 | AX16: 0 | AY16: 0 | AZ16: 0 | BA16: 928.68 | BB16: 0 | BC16: 0 | BD16: 0 | BE16: 926.51
A17: 339.06 | B17: 186.85 | C17: 206.82 | D17: =F17/12 -> 250.48333 | E17: Adeslas (Angel Luis) | F17: =M17+Q17+U17+Y17+AC17+AG17+AK17+AO17+AS17+AW17+BA17+BE17 -> 3005.8 | G17: =J17+N17+R17+V17+Z17+AD17+AH17+AL17+AP17+AT17+AX17+BB17 -> 0 | H17: =K17+O17+S17+W17+AA17+AE17+AI17+AM17+AQ17+AU17+AY17+BC17 -> 0 | I17: =L17+P17+T17+X17+AB17+AF17+AJ17+AN17+AR17+AV17+AZ17+BD17 -> 0 | J17: 0 | K17: 0 | L17: 0 | M17: 254.15 | N17: 0 | O17: 0 | P17: 0 | Q17: 250.15 | R17: 0 | S17: 0 | T17: 0 | U17: 250.15 | V17: 0 | W17: 0 | X17: 0 | Y17: 250.15 | Z17: 0 | AA17: 0 | AB17: 0 | AC17: 250.15 | AD17: 0 | AE17: 0 | AF17: 0 | AG17: 250.15 | AH17: 0 | AI17: 0 | AJ17: 0 | AK17: 250.15 | AL17: 0 | AM17: 0 | AN17: 0 | AO17: 250.15 | AP17: 0 | AQ17: 0 | AR17: 0 | AS17: 250.15 | AT17: 0 | AU17: 0 | AV17: 0 | AW17: 250.15 | AX17: 0 | AY17: 0 | AZ17: 0 | BA17: 250.15 | BB17: 0 | BC17: 0 | BD17: 0 | BE17: 250.15
A18: 50920.35 | B18: 49918.69 | C18: =SUM(C2:C17) -> 48863.59 | D18: =SUM(D2:D17) -> 49664.819 | E18: Total gastos Fijos 2015 | F18: =M18+Q18+U18+Y18+AC18+AG18+AK18+AO18+AS18+AW18+BA18+BE18 -> 595977.83 | G18: =SUM(G2:G17) -> 226899.2 | H18: =SUM(H2:H17) -> 321874.64 | I18: =SUM(I2:I17) -> 32725.03 | J18: =SUM(J2:J17) -> 14975.56 | K18: =SUM(K2:K17) -> 24385.66 | L18: =SUM(L2:L17) -> 2412.13 | M18: =SUM(M2:M17) -> 43003.49 | N18: =SUM(N2:N17) -> 15096.33 | ... BE18: =SUM(BE2:BE17) -> 67817.36
A19: Variables | B19: Variables | C19: Variables | D19: Variables | E19: Gastos Variables | F19: TOTAL Anual | G19: Total Comerc. | H19: Total Tiendas | I19: Total M.Free | J19: C.Enero | K19: T.Enero | L19: M.Enero | M19: Total Enero | N19: C.Febrero | O19: T.Febrero | P19: M.Febrero | Q19: Total Febrero | R19: C.Marzo | S19: T.Marzo | T19: M.Marzo | U19: Total Marzo | V19: C.Abril | W19: T.Abril | X19: M.Abril | Y19: Total Abril | Z19: C.Mayo | AA19: T.Mayo | AB19: M.Mayo | AC19: Total Mayo | AD19: C.Junio | AE19: T.Junio | AF19: M.Junio | AG19: Total Junio | AH19: C.Julio | AI19: T.Julio | AJ19: M.Julio | AK19: Total Julio | AL19: C.Agosto | AM19: T.Agosto | AN19: M.Agosto | AO19: Total Agosto | AP19: C.Septiem. | AQ19: T.Septiem. | AR19: T.Septiem. | AS19: Total Septiem. | AT19: C.Octubre | AU19: T.Octubre | AV19: M.Octubre | AW19: Total Octubre | AX19: C.Noviem. | AY19: T.Noviem. | AZ19: M.Noviem. | BA19: Total Noviem. | BB19: C.Diciem. | BC19: T.Diciem. | BD19: M.Diciem. | BE19: Total Diciem.
A20: 2163.3 | B20: 872.54 | C20: 749.41 | D20: =F20/12 -> 409.04833 | E20: Arreglo Tiendas | F20: =M20+Q20+U20+Y20+AC20+AG20+AK20+AO20+AS20+AW20+BA20+BE20 -> 4908.58 | G20: =J20+N20+R20+V20+Z20+AD20+AH20+AL20+AP20+AT20+AX20+BB20 -> 228.36 | H20: =K20+O20+S20+W20+AA20+AE20+AI20+AM20+AQ20+AU20+AY20+BC20 -> 4437.22 | I20: =L20+P20+T20+X20+AB20+AF20+AJ20+AN20+AR20+AV20+AZ20+BD20 -> 243 | J20: 0 | K20: 0 | L20: 0 | M20: =J20+K20+L20 -> 0 | N20: 0 | O20: 173.67 | P20: 0 | Q20: =N20+O20+P20 -> 173.67 | R20: 0 | S20: 127.17 | T20: 0 | U20: =R20+S20+T20 -> 127.17 | V20: 0 | W20: 0 | X20: 0 | Y20: =V20+W20+X20 -> 0 | Z20: 0 | AA20: 830.58 | AB20: 0 | AC20: =Z20+AA20+AB20 -> 830.58 | AD20: 0 | AE20: 1380.15 | AF20: 0 | AG20: =AD20+AE20+AF20 -> 1380.15 | AH20: 0 | AI20: 235.53 | AJ20: 0 | AK20: =AH20+AI20+AJ20 -> 235.53 | AL20: 0 | AM20: 0 | AN20: 0 | AO20: =AL20+AM20+AN20 -> 0 | AP20: 15 | AQ20: 513.6 | AR20: 0 | AS20: =AP20+AQ20+AR20 -> 528.6 | AT20: 0 | AU20: 0 | AV20: 0 | AW20: =AT20+AU20+AV20 -> 0 | AX20: 213.36 | AY20: 346.71 | AZ20: 243 | BA20: =AX20+AY20+AZ20 -> 803.07 | BB20: 0 | BC20: 829.81 | BD20: 0 | BE20: =BB20+BC20+BD20 -> 829.81
A21: 1952.36 | B21: 141.08 | C21: 396.18 | D21: =F21/12 -> 269.75 | E21: Sueldos Fuera Nómi. (Idemni) | F21: =M21+Q21+U21+Y21+AC21+AG21+AK21+AO21+AS21+AW21+BA21+BE21 -> 3237 | G21: =J21+N21+R21+V21+Z21+AD21+AH21+AL21+AP21+AT21+AX21+BB21 -> 641.25 | H21: =K21+O21+S21+W21+AA21+AE21+AI21+AM21+AQ21+AU21+AY21+BC21 -> 2465.75 | I21: =L21+P21+T21+X21+AB21+AF21+AJ21+AN21+AR21+AV21+AZ21+BD21 -> 130 | J21: 54 | K21: 544 | L21: 40 | M21: =J21+K21+L21 -> 638 | N21: 60.75 | O21: 60.75 | P21: 0 | Q21: =N21+O21+P21 -> 121.5 | R21: 60.75 | S21: 190.75 | T21: 0 | U21: =R21+S21+T21 -> 251.5 | V21: 0 | W21: 94.5 | X21: 90 | Y21: =V21+W21+X21 -> 184.5 | Z21: 60.75 | AA21: 60.75 | AB21: 0 | AC21: =Z21+AA21+AB21 -> 121.5 | AD21: 60.75 | AE21: 60.75 | AF21: 0 | AG21: =AD21+AE21+AF21 -> 121.5 | AH21: 60.75 | AI21: 60.75 | AJ21: 0 | AK21: =AH21+AI21+AJ21 -> 121.5 | AL21: 60.75 | AM21: 60.75 | AN21: 0 | AO21: =AL21+AM21+AN21 -> 121.5 | AP21: 40.5 | AQ21: 40.5 | AR21: 0 | AS21: =AP21+AQ21+AR21 -> 81 | AT21: 60.75 | AU21: 940.75 | AV21: 0 | AW21: =AT21+AU21+AV21 -> 1001.5 | AX21: 60.75 | AY21: 60.75 | AZ21: 0 | BA21: =AX21+AY21+AZ21 -> 121.5 | BB21: 60.75 | BC21: 290.75 | BD21: 0 | BE21: =BB21+BC21+BD21 -> 351.5
A22: 549.63 | B22: 370.29 | C22: 838.5 | D22: =F22/12 -> 3197.2358 | E22: Impuestos (Basur, IBI, Circ.) | F22: =M22+Q22+U22+Y22+AC22+AG22+AK22+AO22+AS22+AW22+BA22+BE22 -> 38366.83 | G22: =J22+N22+R22+V22+Z22+AD22+AH22+AL22+AP22+AT22+AX22+BB22 -> 10638.08 | H22: =K22+O22+S22+W22+AA22+AE22+AI22+AM22+AQ22+AU22+AY22+BC22 -> 26377.49 | I22: =L22+P22+T22+X22+AB22+AF22+AJ22+AN22+AR22+AV22+AZ22+BD22 -> 1351.26 | J22: 0 | K22: 47.65 | L22: 0 | M22: =J22+K22+L22 -> 47.65 | N22: 0 | O22: 0 | P22: 0 | Q22: =N22+O22+P22 -> 0 | R22: 71.81 | S22: 105.01 | T22: 2.18 | U22: =R22+S22+T22 -> 179 | V22: 0 | W22: 47.65 | X22: 113.1 | Y22: =V22+W22+X22 -> 160.75 | Z22: 769.54 | AA22: 269.81 | AB22: 18.03 | AC22: =Z22+AA22+AB22 -> 1057.38 | AD22: 0 | AE22: 0 | AF22: 0 | AG22: =AD22+AE22+AF22 -> 0 | AH22: 2457.84 | AI22: 3425.28 | AJ22: 307.23 | AK22: =AH22+AI22+AJ22 -> 6190.35 | AL22: 0 | AM22: 7866.73 | AN22: 0 | AO22: =AL22+AM22+AN22 -> 7866.73 | AP22: 478.17 | AQ22: 742.24 | AR22: 53.13 | AS22: =AP22+AQ22+AR22 -> 1273.54 | AT22: 0 | AU22: 269.63 | AV22: 0 | AW22: =AT22+AU22+AV22 -> 269.63 | AX22: 6860.72 | AY22: 11148.67 | AZ22: 857.59 | BA22: =AX22+AY22+AZ22 -> 18866.98 | BB22: 0 | BC22: 2454.82 | BD22: 0 | BE22: =BB22+BC22+BD22 -> 2454.82
A23: 521.05 | B23: 553.22 | C23: 396.93 | D23: =F23/12 -> 183.06917 | E23: Publicidad | F23: =M23+Q23+U23+Y23+AC23+AG23+AK23+AO23+AS23+AW23+BA23+BE23 -> 2196.83 | G23: =J23+N23+R23+V23+Z23+AD23+AH23+AL23+AP23+AT23+AX23+BB23 -> 720.17 | H23: =K23+O23+S23+W23+AA23+AE23+AI23+AM23+AQ23+AU23+AY23+BC23 -> 1062.91 | I23: =L23+P23+T23+X23+AB23+AF23+AJ23+AN23+AR23+AV23+AZ23+BD23 -> 413.75 | J23: 0 | K23: 86.86 | L23: 0 | M23: =J23+K23+L23 -> 86.86 | N23: 0 | O23: 22.72 | P23: 119.59 | Q23: =N23+O23+P23 -> 142.31 | R23: 0 | S23: 0 | T23: 0 | U23: =R23+S23+T23 -> 0 | V23: 9.51 | W23: 0 | X23: 0 | Y23: =V23+W23+X23 -> 9.51 | Z23: 49.5 | AA23: 61.5 | AB23: 117 | AC23: =Z23+AA23+AB23 -> 228 | AD23: 0 | AE23: 0 | AF23: 0 | AG23: =AD23+AE23+AF23 -> 0 | AH23: 17.64 | AI23: 0 | AJ23: 0 | AK23: =AH23+AI23+AJ23 -> 17.64 | AL23: 0 | AM23: 0 | AN23: 0 | AO23: =AL23+AM23+AN23 -> 0 | AP23: 0 | AQ23: 0 | AR23: 25 | AS23: =AP23+AQ23+AR23 -> 25 | AT23: 0 | AU23: 20.16 | AV23: 78.51 | AW23: =AT23+AU23+AV23 -> 98.67 | AX23: 0 | AY23: 85.95 | AZ23: 0 | BA23: =AX23+AY23+AZ23 -> 85.95 | BB23: 643.52 | BC23: 785.72 | BD23: 73.65 | BE23: =BB23+BC23+BD23 -> 1502.89
A24: 470.6 | B24: 204.26 | C24: 560.93 | D24: =F24/12 -> 397.27083 | E24: Mantenimiento Vehiculos | F24: =M24+Q24+U24+Y24+AC24+AG24+AK24+AO24+AS24+AW24+BA24+BE24 -> 4767.25 | G24: =J24+N24+R24+V24+Z24+AD24+AH24+AL24+AP24+AT24+AX24+BB24 -> 3807.79 | H24: =K24+O24+S24+W24+AA24+AE24+AI24+AM24+AQ24+AU24+AY24+BC24 -> 885.66 | I24: =L24+P24+T24+X24+AB24+AF24+AJ24+AN24+AR24+AV24+AZ24+BD24 -> 73.8 | J24: 58.95 | K24: 0 | L24: 0 | M24: =J24+K24+L24 -> 58.95 | N24: 210.44 | O24: 0 | P24: 0 | Q24: =N24+O24+P24 -> 210.44 | R24: 0 | S24: 0 | T24: 0 | U24: =R24+S24+T24 -> 0 | V24: 1485.81 | W24: 885.66 | X24: 73.8 | Y24: =V24+W24+X24 -> 2445.27 | Z24: 0 | AA24: 0 | AB24: 0 | AC24: =Z24+AA24+AB24 -> 0 | AD24: 60.75 | AE24: 0 | AF24: 0 | AG24: =AD24+AE24+AF24 -> 60.75 | AH24: 143.91 | AI24: 0 | AJ24: 0 | AK24: =AH24+AI24+AJ24 -> 143.91 | AL24: 379.71 | AM24: 0 | AN24: 0 | AO24: =AL24+AM24+AN24 -> 379.71 | AP24: 796.94 | AQ24: 0 | AR24: 0 | AS24: =AP24+AQ24+AR24 -> 796.94 | AT24: 46.5 | AU24: 0 | AV24: 0 | AW24: =AT24+AU24+AV24 -> 46.5 | AX24: 564.78 | AY24: 0 | AZ24: 0 | BA24: =AX24+AY24+AZ24 -> 564.78 | BB24: 60 | BC24: 0 | BD24: 0 | BE24: =BB24+BC24+BD24 -> 60
A25: 379.48 | B25: 155.08 | C25: 128.02 | D25: =F25/12 -> 97.434167 | E25: Arsys Internet + Golden Soft | F25: =M25+Q25+U25+Y25+AC25+AG25+AK25+AO25+AS25+AW25+BA25+BE25 -> 1169.21 | G25: =J25+N25+R25+V25+Z25+AD25+AH25+AL25+AP25+AT25+AX25+BB25 -> 903.68 | H25: =K25+O25+S25+W25+AA25+AE25+AI25+AM25+AQ25+AU25+AY25+BC25 -> 259.88 | I25: =L25+P25+T25+X25+AB25+AF25+AJ25+AN25+AR25+AV25+AZ25+BD25 -> 5.65 | J25: 71.54 | K25: 16 | L25: 0 | M25: =J25+K25+L25 -> 87.54 | N25: 71.54 | O25: 16 | P25: 0 | Q25: =N25+O25+P25 -> 87.54 | R25: 71.54 | S25: 16 | T25: 0 | U25: =R25+S25+T25 -> 87.54 | V25: 116.74 | W25: 83.88 | X25: 5.65 | Y25: =V25+W25+X25 -> 206.27 | Z25: 71.54 | AA25: 16 | AB25: 0 | AC25: =Z25+AA25+AB25 -> 87.54 | AD25: 71.54 | AE25: 16 | AF25: 0 | AG25: =AD25+AE25+AF25 -> 87.54 | AH25: 71.54 | AI25: 16 | AJ25: 0 | AK25: =AH25+AI25+AJ25 -> 87.54 | AL25: 71.54 | AM25: 16 | AN25: 0 | AO25: =AL25+AM25+AN25 -> 87.54 | AP25: 71.54 | AQ25: 16 | AR25: 0 | AS25: =AP25+AQ25+AR25 -> 87.54 | AT25: 71.54 | AU25: 16 | AV25: 0 | AW25: =AT25+AU25+AV25 -> 87.54 | AX25: 71.54 | AY25: 16 | AZ25: 0 | BA25: =AX25+AY25+AZ25 -> 87.54 | BB25: 71.54 | BC25: 16 | BD25: 0 | BE25: =BB25+BC25+BD25 -> 87.54
A26: 288.25 | B26: 252.9 | C26: 453.73 | D26: =F26/12 -> 82.5325 | E26: Comisiones Tarjetas, etc | F26: =M26+Q26+U26+Y26+AC26+AG26+AK26+AO26+AS26+AW26+BA26+BE26 -> 990.39 | G26: =J26+N26+R26+V26+Z26+AD26+AH26+AL26+AP26+AT26+AX26+BB26 -> 0 | H26: =K26+O26+S26+W26+AA26+AE26+AI26+AM26+AQ26+AU26+AY26+BC26 -> 832.91 | I26: =L26+P26+T26+X26+AB26+AF26+AJ26+AN26+AR26+AV26+AZ26+BD26 -> 157.48 | J26: 0 | K26: 45.15 | L26: 6.87 | M26: =J26+K26+L26 -> 52.02 | N26: 0 | O26: 59.12 | P26: 20.05 | Q26: =N26+O26+P26 -> 79.17 | R26: 0 | S26: 48.08 | T26: 11.52 | U26: =R26+S26+T26 -> 59.6 | V26: 0 | W26: 45.46 | X26: 9.49 | Y26: =V26+W26+X26 -> 54.95 | Z26: 0 | AA26: 41.47 | AB26: 8.97 | AC26: =Z26+AA26+AB26 -> 50.44 | AD26: 0 | AE26: 95.5 | AF26: 9.27 | AG26: =AD26+AE26+AF26 -> 104.77 | AH26: 0 | AI26: 66.64 | AJ26: 20.41 | AK26: =AH26+AI26+AJ26 -> 87.05 | AL26: 0 | AM26: 207.2 | AN26: 20.25 | AO26: =AL26+AM26+AN26 -> 227.45 | AP26: 0 | AQ26: 69.79 | AR26: 11.84 | AS26: =AP26+AQ26+AR26 -> 81.63 | AT26: 0 | AU26: 67.05 | AV26: 14.61 | AW26: =AT26+AU26+AV26 -> 81.66 | AX26: 0 | AY26: 34.53 | AZ26: 9.35 | BA26: =AX26+AY26+AZ26 -> 43.88 | BB26: 0 | BC26: 52.92 | BD26: 14.85 | BE26: =BB26+BC26+BD26 -> 67.77
D27: =F27/12 -> 403.83408 | E27: Comisiones Bancarias | F27: =M27+Q27+U27+Y27+AC27+AG27+AK27+AO27+AS27+AW27+BA27+BE27 -> 4846.009 | G27: =J27+N27+R27+V27+Z27+AD27+AH27+AL27+AP27+AT27+AX27+BB27 -> 1784.73 | H27: =K27+O27+S27+W27+AA27+AE27+AI27+AM27+AQ27+AU27+AY27+BC27 -> 2824.709 | I27: =L27+P27+T27+X27+AB27+AF27+AJ27+AN27+AR27+AV27+AZ27+BD27 -> 236.57 | J27: 83.99 | K27: 131.94 | L27: 11.99 | M27: =J27+K27+L27 -> 227.92 | N27: 110.42 | O27: 173.41 | P27: 15.79 | Q27: =N27+O27+P27 -> 299.62 | R27: 494.98 | S27: 848.6 | T27: 70.71 | U27: =R27+S27+T27 -> 1414.29 | V27: 129.04 | W27: 193.56 | X27: 16.13 | Y27: =V27+W27+X27 -> 338.73 | Z27: 140.17 | AA27: 209.68 | AB27: 17.64 | AC27: =Z27+AA27+AB27 -> 367.49 | AD27: 128.62 | AE27: 192.849 | AF27: 16.12 | AG27: =AD27+AE27+AF27 -> 337.589 | AH27: 258.3 | AI27: 406.01 | AJ27: 36.91 | AK27: =AH27+AI27+AJ27 -> 701.22 | AL27: 89.68 | AM27: 129.48 | AN27: 9.96 | AO27: =AL27+AM27+AN27 -> 229.12 | AP27: 89.49 | AQ27: 129.23 | AR27: 9.94 | AS27: =AP27+AQ27+AR27 -> 228.66 | AT27: 89.01 | AU27: 132.01 | AV27: 10.01 | AW27: =AT27+AU27+AV27 -> 231.03 | AX27: 84.64 | AY27: 137.55 | AZ27: 10.58 | BA27: =AX27+AY27+AZ27 -> 232.77 | BB27: 86.39 | BC27: 140.39 | BD27: 10.79 | BE27: =BB27+BC27+BD27 -> 237.57
A28: 671.89 | B28: 671.89 | C28: 671.89 | D28: =F28/12 -> 0 | E28: Comisiones Zeleris | G28: =J28+N28+R28+V28+Z28+AD28+AH28+AL28+AP28+AT28+AX28+BB28 -> 0 | H28: =K28+O28+S28+W28+AA28+AE28+AI28+AM28+AQ28+AU28+AY28+BC28 -> 1720.18 | I28: =L28+P28+T28+X28+AB28+AF28+AJ28+AN28+AR28+AV28+AZ28+BD28 -> 0 | J28: 0 | K28: 573.33 | L28: 0 | M28: =J28+K28+L28 -> 573.33 | N28: 0 | O28: 496.54 | P28: 0 | Q28: =N28+O28+P28 -> 496.54 | R28: 0 | S28: 398.11 | T28: 0 | U28: =R28+S28+T28 -> 398.11 | V28: 0 | W28: 252.2 | X28: 0 | Y28: =V28+W28+X28 -> 252.2 | Z28: 0 | AA28: 0 | AB28: 0 | AC28: =Z28+AA28+AB28 -> 0 | AD28: 0 | AE28: 0 | AF28: 0 | AG28: =AD28+AE28+AF28 -> 0 | AH28: 0 | AI28: 0 | AJ28: 0 | AK28: =AH28+AI28+AJ28 -> 0 | AL28: 0 | AM28: 0 | AN28: 0 | AO28: =AL28+AM28+AN28 -> 0 | AP28: 0 | AQ28: 0 | AR28: 0 | AS28: =AP28+AQ28+AR28 -> 0 | AT28: 0 | AU28: 0 | AV28: 0 | AW28: =AT28+AU28+AV28 -> 0 | AX28: 0 | AY28: 0 | AZ28: 0 | BA28: =AX28+AY28+AZ28 -> 0 | BB28: 0 | BC28: 0 | BD28: 0 | BE28: =BB28+BC28+BD28 -> 0
A29: 235.54 | B29: 322.46 | C29: 190.84 | D29: =F29/12 -> 222.26833 | E29: Material de Oficina | F29: =M29+Q29+U29+Y29+AC29+AG29+AK29+AO29+AS29+AW29+BA29+BE29 -> 2667.22 | G29: =J29+N29+R29+V29+Z29+AD29+AH29+AL29+AP29+AT29+AX29+BB29 -> 611.41 | H29: =K29+O29+S29+W29+AA29+AE29+AI29+AM29+AQ29+AU29+AY29+BC29 -> 2033.13 | I29: =L29+P29+T29+X29+AB29+AF29+AJ29+AN29+AR29+AV29+AZ29+BD29 -> 22.68 | J29: 41.17 | K29: 142.23 | L29: 0 | M29: =J29+K29+L29 -> 183.4 | N29: 0 | O29: 111.59 | P29: 0 | Q29: =N29+O29+P29 -> 111.59 | R29: 0 | S29: 64.86 | T29: 4.31 | U29: =R29+S29+T29 -> 69.17 | V29: 0 | W29: 245.77 | X29: 0 | Y29: =V29+W29+X29 -> 245.77 | Z29: 0 | AA29: 180.17 | AB29: 0 | AC29: =Z29+AA29+AB29 -> 180.17 | AD29: 36.64 | AE29: 169.11 | AF29: 0 | AG29: =AD29+AE29+AF29 -> 205.75 | AH29: 0 | AI29: 187.34 | AJ29: 0 | AK29: =AH29+AI29+AJ29 -> 187.34 | AL29: 0 | AM29: 171.6 | AN29: 0 | AO29: =AL29+AM29+AN29 -> 171.6 | AP29: 291.62 | AQ29: 491.18 | AR29: 0 | AS29: =AP29+AQ29+AR29 -> 782.8 | AT29: 192.18 | AU29: 192.18 | AV29: 18.37 | AW29: =AT29+AU29+AV29 -> 402.73 | AX29: 0 | AY29: 27.3 | AZ29: 0 | BA29: =AX29+AY29+AZ29 -> 27.3 | BB29: 49.8 | BC29: 49.8 | BD29: 0 | BE29: =BB29+BC29+BD29 -> 99.6
A30: 218.56 | B30: 353.34 | C30: 492.05 | D30: =F30/12 -> 440.41083 | E30: Seguros Tiendas | F30: =M30+Q30+U30+Y30+AC30+AG30+AK30+AO30+AS30+AW30+BA30+BE30 -> 5284.93 | G30: =J30+N30+R30+V30+Z30+AD30+AH30+AL30+AP30+AT30+AX30+BB30 -> 319.25 | H30: =K30+O30+S30+W30+AA30+AE30+AI30+AM30+AQ30+AU30+AY30+BC30 -> 4313.71 | I30: =L30+P30+T30+X30+AB30+AF30+AJ30+AN30+AR30+AV30+AZ30+BD30 -> 651.97 | J30: 0 | K30: 0 | L30: 0 | M30: =J30+K30+L30 -> 0 | N30: 0 | O30: 0 | P30: 0 | Q30: =N30+O30+P30 -> 0 | R30: 0 | S30: 1871.27 | T30: 0 | U30: =R30+S30+T30 -> 1871.27 | V30: 133.76 | W30: 996.33 | X30: 16.72 | Y30: =V30+W30+X30 -> 1146.81 | Z30: 0 | AA30: 579.92 | AB30: 0 | AC30: =Z30+AA30+AB30 -> 579.92 | AD30: 0 | AE30: 587.99 | AF30: 0 | AG30: =AD30+AE30+AF30 -> 587.99 | AH30: 0 | AI30: 0 | AJ30: 0 | AK30: =AH30+AI30+AJ30 -> 0 | AL30: 128.61 | AM30: 185.77 | AN30: 14.29 | AO30: =AL30+AM30+AN30 -> 328.67 | AP30: 0 | AQ30: 0 | AR30: 0 | AS30: =AP30+AQ30+AR30 -> 0 | AT30: 0 | AU30: 0 | AV30: 0 | AW30: =AT30+AU30+AV30 -> 0 | AX30: 56.88 | AY30: 92.43 | AZ30: 7.11 | BA30: =AX30+AY30+AZ30 -> 156.42 | BB30: 0 | BC30: 0 | BD30: 613.85 | BE30: =BB30+BC30+BD30 -> 613.85
A31: 286.49 | B31: 465.25 | C31: 20.83 | D31: =F31/12 -> 245.94167 | E31: Varios (Multas,etc) | F31: =M31+Q31+U31+Y31+AC31+AG31+AK31+AO31+AS31+AW31+BA31+BE31 -> 2951.3 | G31: =J31+N31+R31+V31+Z31+AD31+AH31+AL31+AP31+AT31+AX31+BB31 -> 1113.73 | H31: =K31+O31+S31+W31+AA31+AE31+AI31+AM31+AQ31+AU31+AY31+BC31 -> 1709.72 | I31: =L31+P31+T31+X31+AB31+AF31+AJ31+AN31+AR31+AV31+AZ31+BD31 -> 127.85 | J31: 0 | K31: 0 | L31: 0 | M31: =J31+K31+L31 -> 0 | N31: 0 | O31: 0 | P31: 0 | Q31: =N31+O31+P31 -> 0 | R31: 0 | S31: 0 | T31: 0 | U31: =R31+S31+T31 -> 0 | V31: 17.15 | W31: 25.71 | X31: 2.14 | Y31: =V31+W31+X31 -> 45 | Z31: 0 | AA31: 0 | AB31: 0 | AC31: =Z31+AA31+AB31 -> 0 | AD31: 0 | AE31: 0 | AF31: 0 | AG31: =AD31+AE31+AF31 -> 0 | AH31: 0 | AI31: 50 | AJ31: 0 | AK31: =AH31+AI31+AJ31 -> 50 | AL31: 591.57 | AM31: 854.49 | AN31: 65.73 | AO31: =AL31+AM31+AN31 -> 1511.79 | AP31: 19.9 | AQ31: 28.6 | AR31: 2.2 | AS31: =AP31+AQ31+AR31 -> 50.7 | AT31: 206.93 | AU31: 298.89 | AV31: 22.99 | AW31: =AT31+AU31+AV31 -> 528.81 | AX31: 278.18 | AY31: 452.03 | AZ31: 34.79 | BA31: =AX31+AY31+AZ31 -> 765 | BB31: 0 | BC31: 0 | BD31: 0 | BE31: =BB31+BC31+BD31 -> 0
A32: 187.01 | B32: 151.64 | C32: 170.14 | D32: =F32/12 -> 201.70417 | E32: Seguros Automovil | F32: =M32+Q32+U32+Y32+AC32+AG32+AK32+AO32+AS32+AW32+BA32+BE32 -> 2420.45 | G32: =J32+N32+R32+V32+Z32+AD32+AH32+AL32+AP32+AT32+AX32+BB32 -> 2420.45 | H32: =K32+O32+S32+W32+AA32+AE32+AI32+AM32+AQ32+AU32+AY32+BC32 -> 0 | I32: =L32+P32+T32+X32+AB32+AF32+AJ32+AN32+AR32+AV32+AZ32+BD32 -> 0 | J32: 0 | K32: 0 | L32: 0 | M32: =J32+K32+L32 -> 0 | N32: 0 | O32: 0 | P32: 0 | Q32: =N32+O32+P32 -> 0 | R32: 0 | S32: 0 | T32: 0 | U32: =R32+S32+T32 -> 0 | V32: 970.66 | W32: 0 | X32: 0 | Y32: =V32+W32+X32 -> 970.66 | Z32: 236.6 | AA32: 0 | AB32: 0 | AC32: =Z32+AA32+AB32 -> 236.6 | AD32: 321.4 | AE32: 0 | AF32: 0 | AG32: =AD32+AE32+AF32 -> 321.4 | AH32: 311.46 | AI32: 0 | AJ32: 0 | AK32: =AH32+AI32+AJ32 -> 311.46 | AL32: 0 | AM32: 0 | AN32: 0 | AO32: =AL32+AM32+AN32 -> 0 | AP32: 0 | AQ32: 0 | AR32: 0 | AS32: =AP32+AQ32+AR32 -> 0 | AT32: 580.33 | AU32: 0 | AV32: 0 | AW32: =AT32+AU32+AV32 -> 580.33 | AX32: 0 | AY32: 0 | AZ32: 0 | BA32: =AX32+AY32+AZ32 -> 0 | BB32: 0 | BC32: 0 | BD32: 0 | BE32: =BB32+BC32+BD32 -> 0
A33: 86.35 | B33: 67.53 | C33: 100.68 | D33: =F33/12 -> 104.92 | E33: Mutua | F33: =M33+Q33+U33+Y33+AC33+AG33+AK33+AO33+AS33+AW33+BA33+BE33 -> 1259.04 | G33: =J33+N33+R33+V33+Z33+AD33+AH33+AL33+AP33+AT33+AX33+BB33 -> 473.1 | H33: =K33+O33+S33+W33+AA33+AE33+AI33+AM33+AQ33+AU33+AY33+BC33 -> 725.04 | I33: =L33+P33+T33+X33+AB33+AF33+AJ33+AN33+AR33+AV33+AZ33+BD33 -> 60.9 | J33: 51.24 | K33: 80.63 | L33: 7.33 | M33: =J33+K33+L33 -> 139.2 | N33: 0 | O33: 0 | P33: 0 | Q33: =N33+O33+P33 -> 0 | R33: 32.13 | S33: 55.08 | T33: 4.59 | U33: =R33+S33+T33 -> 91.8 | V33: 180.88 | W33: 271.32 | X33: 22.61 | Y33: =V33+W33+X33 -> 474.81 | Z33: 0 | AA33: 0 | AB33: 0 | AC33: =Z33+AA33+AB33 -> 0 | AD33: 0 | AE33: 0 | AF33: 0 | AG33: =AD33+AE33+AF33 -> 0 | AH33: 85.05 | AI33: 133.15 | AJ33: 12.15 | AK33: =AH33+AI33+AJ33 -> 230.35 | AL33: 0 | AM33: 0 | AN33: 0 | AO33: =AL33+AM33+AN33 -> 0 | AP33: 0 | AQ33: 0 | AR33: 0 | AS33: =AP33+AQ33+AR33 -> 0 | AT33: 90.36 | AU33: 130.52 | AV33: 10.04 | AW33: =AT33+AU33+AV33 -> 230.92 | AX33: 0 | AY33: 0 | AZ33: 0 | BA33: =AX33+AY33+AZ33 -> 0 | BB33: 33.44 | BC33: 54.34 | BD33: 4.18 | BE33: =BB33+BC33+BD33 -> 91.96
A34: 0 | B34: 0 | C34: 0 | D34: =F34/12 -> 319.04167 | E34: Penalizaciones Teléfonica | F34: =M34+Q34+U34+Y34+AC34+AG34+AK34+AO34+AS34+AW34+BA34+BE34 -> 3828.5 | G34: =J34+N34+R34+V34+Z34+AD34+AH34+AL34+AP34+AT34+AX34+BB34 -> 980 | H34: =K34+O34+S34+W34+AA34+AE34+AI34+AM34+AQ34+AU34+AY34+BC34 -> 2848.5 | I34: =L34+P34+T34+X34+AB34+AF34+AJ34+AN34+AR34+AV34+AZ34+BD34 -> 0 | J34: 250 | K34: 966.5 | L34: 0 | M34: =J34+K34+L34 -> 1216.5 | N34: 200 | O34: 420 | P34: 0 | Q34: =N34+O34+P34 -> 620 | R34: 0 | S34: 512 | T34: 0 | U34: =R34+S34+T34 -> 512 | V34: 80 | W34: 50 | X34: 0 | Y34: =V34+W34+X34 -> 130 | Z34: 0 | AA34: 100 | AB34: 0 | AC34: =Z34+AA34+AB34 -> 100 | AD34: 50 | AE34: 250 | AF34: 0 | AG34: =AD34+AE34+AF34 -> 300 | AH34: 400 | AI34: 550 | AJ34: 0 | AK34: =AH34+AI34+AJ34 -> 950 | AL34: 0 | AM34: 0 | AN34: 0 | AO34: =AL34+AM34+AN34 -> 0 | AP34: 0 | AQ34: 0 | AR34: 0 | AS34: =AP34+AQ34+AR34 -> 0 | AT34: 0 | AU34: 0 | AV34: 0 | AW34: =AT34+AU34+AV34 -> 0 | BA34: =AX34+AY34+AZ34 -> 0 | BE34: =BB34+BC34+BD34 -> 0
A35: 5683.96 | B35: 5142.09 | C35: 6800.17 | D35: =F35/12 -> 6126.2917 | E35: Salidas ALuis (Comisiones) | F35: =M35+Q35+U35+Y35+AC35+AG35+AK35+AO35+AS35+AW35+BA35+BE35 -> 73515.5 | G35: =J35+N35+R35+V35+Z35+AD35+AH35+AL35+AP35+AT35+AX35+BB35 -> 0 | H35: =K35+O35+S35+W35+AA35+AE35+AI35+AM35+AQ35+AU35+AY35+BC35 -> 0 | I35: =L35+P35+T35+X35+AB35+AF35+AJ35+AN35+AR35+AV35+AZ35+BD35 -> 0 | J35: 0 | K35: 0 | L35: 0 | M35: 6018 | N35: 0 | O35: 0 | P35: 0 | Q35: 6362 | R35: 0 | S35: 0 | T35: 0 | U35: 8270 | V35: 0 | W35: 0 | X35: 0 | Y35: 4810 | Z35: 0 | AA35: 0 | AB35: 0 | AC35: 8033 | AD35: 0 | AE35: 0 | AF35: 0 | AG35: 7563.5 | AH35: 0 | AI35: 0 | AJ35: 0 | AK35: 3346 | AL35: 0 | AM35: 0 | AN35: 0 | AO35: 3140 | AP35: 0 | AQ35: 0 | AR35: 0 | AS35: 4020 | AT35: 0 | AU35: 0 | AV35: 0 | AW35: 8110 | AX35: 0 | AY35: 0 | AZ35: 0 | BA35: 4060 | BB35: 0 | BC35: 0 | BD35: 0 | BE35: 9783
A36: 13028.99 | B36: 9051.68 | C36: =sum(C20:C35) -> 11970.3 | D36: =sum(D20:D35) -> 12700.753 | E36: Total Gastos Variables | F36: =M36+Q36+U36+Y36+AC36+AG36+AK36+AO36+AS36+AW36+BA36+BE36 -> 154129.22 | G36: =SUM(G20:G35) -> 24642 | H36: =SUM(H20:H35) -> 52496.809 | I36: =SUM(I20:I35) -> 3474.91 | J36: =SUM(J20:J35) -> 610.89 | K36: =SUM(K20:K35) -> 2634.29 | L36: =SUM(L20:L35) -> 66.19 | M36: =SUM(M20:M35) -> 9329.37 | N36: =SUM(N20:N35) -> 653.15 | ... BE36: =SUM(BE20:BE35) -> 16180.31
A37: =A18+A36 -> 63949.34 | B37: =B18+B36 -> 58970.37 | C37: 60080.65 | D37: =D18+D36 -> 62365.572 | E37: Total gastos Fijos + Variables | F37: =M37+Q37+U37+Y37+AC37+AG37+AK37+AO37+AS37+AW37+BA37+BE37 -> 750107.05 | G37: =G18+G36 -> 251541.2 | H37: =H18+H36 -> 374371.45 | I37: =I18+I36 -> 36199.94 | J37: =J18+J36 -> 15586.45 | K37: =K18+K36 -> 27019.95 | L37: =L18+L36 -> 2478.32 | M37: =M18+M36 -> 52332.86 | N37: =N18+N36 -> 15749.48 | ... BE37: =BE18+BE36 -> 83997.67
A38: =A37*12 -> 767392.08 | B38: =B37*12 -> 707644.44 | C38: =C37*12 -> 720967.8 | D38: =D37*12 -> 748386.87 | E38: Compras Mercaderias | F38: =M38+Q38+U38+Y38+AC38+AG38+AK38+AO38+AS38+AW38+BA38+BE38 -> 780016.79 | M38: 75482.45 | Q38: 60528.23 | U38: 52370.99 | Y38: 77015.97 | AC38: 64085.51 | AG38: 50353.64 | AK38: 45214.13 | AO38: 62094.97 | AS38: 103251.53 | AW38: 54591.03 | BA38: 58847.21 | BE38: 76181.13
E39: Total gastos General | F39: =M39+Q39+U39+Y39+AC39+AG39+AK39+AO39+AS39+AW39+BA39+BE39 -> 1530123.8 | M39: =M37+M38 -> 127815.31 | Q39: =Q37+Q38 -> 111997.74 | U39: =U37+U38 -> 108975.46 | Y39: =Y37+Y38 -> 134279.55 | AC39: =AC37+AC38 -> 121519.46 | AE39: 0 | AG39: =AG37+AG38 -> 106769.9 | AK39: =AK37+AK38 -> 126467.07 | AO39: =AO37+AO38 -> 125265.67 | AS39: =AS37+AS38 -> 159725.74 | AW39: =AW37+AW38 -> 113324.27 | BA39: =BA37+BA38 -> 133804.87 | BE39: =BE37+BE38 -> 160178.8
E40: Ventas Mercaderias | M40: 138266.74 | Q40: 116626 | U40: 108935 | Y40: 122705 | AC40: 122287.4 | AG40: 126875.09 | AK40: 111192.5 | AO40: 119492.23 | AS40: 115456.52 | AW40: 123579.94 | BA40: 124000 | BE40: 124873.66
E41: Beneficio o Perdida | F41: =M41+Q41+U41+Y41+AC41+AG41+AK41+AO41+AS41+AW41+BA41+BE41 -> -75833.759 | M41: =M40-M39 -> 10451.43 | Q41: =Q40-Q39 -> 4628.26 | U41: =U40-U39 -> -40.46 | Y41: =Y40-Y39 -> -11574.55 | AC41: =AC40-AC39 -> 767.94 | AG41: =AG40-AG39 -> 20105.191 | AK41: =AK40-AK39 -> -15274.57 | AO41: =AO40-AO39 -> -5773.44 | AS41: =AS40-AS39 -> -44269.22 | AW41: =AW40-AW39 -> 10255.67 | BA41: =BA40-BA39 -> -9804.87 | BE41: =BE40-BE39 -> -35305.14

Sheet Luz
A1: iberdrola.es | D1: 2106 | P1: 2017
A2: Usuario: CRCHAMSA | B2: Potencia | C2: Diciembre | D2: Enero | E2: Febrero | F2: Marzo | G2: Abril | H2: Mayo | I2: Junio | J2: Julio | K2: Agosto | L2: Septiembre | M2: Octubre | N2: Noviembre | O2: Diciembre | P2: Enero | Q2: Promedio MES | R2: Media Diaria | S2: Luz Asignada
A3: Contraseña: xa253625
A4: Estación KW | B4: 13.856 | C4: 1213 | D4: 1200 | E4: 1352 | F4: 911 | G4: 1324 | H4: 740 | I4: 683 | J4: 848 | K4: 1153 | L4: 1100 | M4: 794 | N4: 597 | O4: 952 | Q4: =SUM(C4:N4)/12 -> 992.91667 | R4: =Q4/25 -> 39.716667 | S4: 34
A5: Estación Importe | B5: =(B4*0.128398)*30 -> 53.372481 | C5: 310.04 | D5: 291.01 | E5: 311.83 | F5: 210.31 | G5: 318.52 | H5: 194.6 | I5: 184.75 | J5: 213.26 | K5: 265.95 | L5: 265.44 | M5: 203.95 | N5: 191.7 | O5: 223.26 | Q5: 246.78 | R5: 8.23
A7: Vitigudino KW | B7: 3.45 | D7: 974 | F7: 2468 | H7: 1800 | J7: 1993 | L7: 1369 | M7: 779 | N7: 1493 | O7: 188 | Q7: =SUM(C7:N7)/12 -> 906.33333 | R7: =Q7/25 -> 36.253333 | S7: 14
A8: Vitigudino Importe | B8: =(B7*0.114873)*30 -> 11.889356 | D8: 223.21 | F8: 445.27 | H8: 339.57 | J8: 395.53 | L8: 262.52 | M8: 152.96 | N8: 257.76 | O8: 26.81 | Q8: 182.35 | R8: 6.08
A10: Santa Marta KW | B10: 6.9 | C10: 750 | D10: 763 | E10: 654 | F10: 549 | G10: 569 | H10: 519 | I10: 438 | J10: 506 | K10: 675 | L10: 653 | M10: 546 | N10: 869 | O10: 81 | Q10: =SUM(C10:N10)/12 -> 624.25 | R10: =Q10/25 -> 24.97 | S10: 9
A11: Santa Marta Importe | B11: =(B10*0.114873)*30 -> 23.778711 | C11: 230.29 | D11: 218.13 | E11: 188.97 | F11: 159.32 | G11: 169.68 | H11: 163.37 | I11: 140.14 | J11: 156.51 | K11: 192.6 | L11: 179.59 | M11: 174.52 | N11: 298.82 | O11: 34.92 | Q11: 180.67 | R11: 6.02
A13: MovilFree KW | B13: 4.6 | C13: 396 | E13: 661 | F13: 457 | G13: 459 | H13: 427 | I13: 432 | J13: 482 | K13: 433 | L13: 431 | M13: 416 | N13: 676 | Q13: =SUM(C13:N13)/12 -> 439.16667 | R13: =Q13/25 -> 17.566667 | S13: 11
A14: MovilFree Importe | B14: =(B13*0.114873)*30 -> 15.852474 | C14: 83.9 | E14: 138.05 | F14: 90.59 | G14: 94.16 | H14: 90.24 | I14: 96.15 | J14: 101.65 | K14: 89.07 | L14: 90.42 | M14: 88.12 | N14: 131.23 | Q14: 82.52 | R14: 2.75
A16: Correhuela KW | B16: 3.45 | C16: 323 | E16: 675 | F16: 346 | G16: 445 | H16: 282 | I16: 228 | J16: 214 | K16: 92 | L16: 219 | M16: 187 | N16: 192 | O16: 253 | Q16: =SUM(C16:N16)/12 -> 266.91667 | R16: =Q16/25 -> 10.676667 | S16: 11
A17: Correhuela Importe | B17: =(B16*0.114873)*30 -> 11.889356 | C17: 90.01 | E17: 177.36 | F17: 83.01 | G17: 111.56 | H17: 83.64 | I17: 83.95 | J17: 75.95 | K17: 88.23 | L17: 75.67 | M17: 67.98 | N17: 78.59 | O17: 63.36 | Q17: 78.41 | R17: 2.61
A19: Peñaranda KW | B19: 3.45 | C19: 202 | E19: 364 | F19: 196 | G19: 165 | H19: 79 | I19: 49 | J19: 115 | K19: 174 | L19: 217 | M19: 105 | N19: 237 | O19: 155 | Q19: =SUM(C19:N19)/12 -> 158.58333 | R19: =Q19/25 -> 6.3433333 | S19: 8
A20: Peñaranda Importe | B20: =(B19*0.114873)*30 -> 11.889356 | C20: 46.22 | E20: 75.44 | F20: 39.69 | G20: 40.33 | H20: 29.74 | I20: 34.92 | J20: 36.57 | K20: 43.02 | L20: 56.17 | M20: 34.94 | N20: 52.67 | O20: 28.09 | Q20: 39.78 | R20: 1.33
A22: Total Kw Consumidos | C22: =C4+C7+C10+C13+C16+C19 -> 2884 | D22: =D4+D7+D10+D13+D16+D19 -> 2937 | E22: =E4+E7+E10+E13+E16+E19 -> 3706 | F22: =F4+F7+F10+F13+F16+F19 -> 4927 | G22: =G4+G7+G10+G13+G16+G19 -> 2962 | H22: =H4+H7+H10+H13+H16+H19 -> 3847 | I22: =I4+I7+I10+I13+I16+I19 -> 1830 | J22: =J4+J7+J10+J13+J16+J19 -> 4158 | ... N22: =N4+N7+N10+N13+N16+N19 -> 4064 | Q22: =Q4+Q7+Q10+Q13+Q16+Q19 -> 3388.1667 | R22: =R4+R7+R10+R13+R16+R19 -> 135.52667 | S22: =S4+S7+S10+S13+S16+S19 -> 87
A23: Total Factura | B23: =B5+B8+B11+B14+B17+B20 -> 128.67173 | C23: =C5+C8+C11+C14+C17+C20 -> 760.46 | D23: =D5+D8+D11+D14+D17+D20 -> 732.35 | E23: =E5+E8+E11+E14+E17+E20 -> 891.65 | F23: =F5+F8+F11+F14+F17+F20 -> 1028.19 | G23: =G5+G8+G11+G14+G17+G20 -> 734.25 | H23: =H5+H8+H11+H14+H17+H20 -> 901.16 | I23: =I5+I8+I11+I14+I17+I20 -> 539.91 | ... N23: =N5+N8+N11+N14+N17+N20 -> 1010.77 | Q23: =Q5+Q8+Q11+Q14+Q17+Q20 -> 810.51 | R23: =R5+R8+R11+R14+R17+R20 -> 27.02
D24: Estación: TRIFÁSICO | G24: Santa Marta: TRIFÁSICO | J24: Vitigudino: | M24: Correhuela : | P24: MovilFree : | S24: Peñaranda :
C25: domingo | D25: 42694 | E25: 8.33 | G25: 42694 | H25: 19.77 | J25: 42694 | K25: 13.2 | M25: 42694 | N25: 3.2 | P25: 42694 | Q25: 4.58 | S25: 42694 | T25: 2.25
C26: Lunes | D26: 42695 | E26: 40.1 | F26: 44.52 | G26: 42695 | H26: 13.09 | I26: 11.32 | J26: 42695 | K26: 18.1 | L26: 18.75 | M26: 42695 | N26: 13.5 | O26: 1.41 | P26: 42695 | Q26: 13.51 | R26: 13.15 | S26: 42695 | T26: 9.32 | U26: 11.65
C27: martes | D27: 42696 | E27: 49.59 | F27: 40.11 | G27: 42696 | H27: 13.26 | I27: 10.54 | J27: 42696 | K27: 3.06 | L27: 20.22 | M27: 42696 | N27: 12.94 | O27: 25 | P27: 42696 | Q27: 13.26 | R27: 13.69 | S27: 42696 | T27: 1.24 | U27: 10.99
C28: miércoles | D28: 42697 | E28: 43.5 | F28: 38.86 | G28: 42697 | H28: 17.58 | I28: 10.41 | J28: 42697 | K28: 13.47 | L28: 16.55 | M28: 42697 | N28: 13.2 | O28: 12.71 | P28: 42697 | Q28: 13.02 | R28: 12.75 | S28: 42697 | T28: 11.66 | U28: 9.65
C29: jueves | D29: 42698 | E29: 44.81 | F29: 38.74 | G29: 42698 | H29: 19.72 | I29: 10.36 | J29: 42698 | K29: 16.99 | L29: 15.05 | M29: 42698 | N29: 13.16 | O29: 13.1 | P29: 42698 | Q29: 13.47 | R29: 12.4 | S29: 42698 | T29: 11.81 | U29: 9.18
C30: viernes | D30: 42699 | E30: 44.29 | F30: 35.4 | G30: 42699 | H30: 20.86 | I30: 8.57 | J30: 42699 | K30: 18.61 | L30: 16.87 | M30: 42699 | N30: 13.3 | O30: 12.69 | P30: 42699 | Q30: 13.34 | R30: 12.8 | S30: 42699 | T30: 11.94 | U30: 8.6
C31: sábado | D31: 42700 | E31: 21.28 | F31: 20.92 | G31: 42700 | H31: 10.4 | I31: 7.2 | J31: 42700 | K31: 9.24 | L31: 9.94 | M31: 42700 | N31: 8.31 | O31: 8.08 | P31: 42700 | Q31: 8.55 | R31: 8.92 | S31: 42700 | T31: 6.11 | U31: 4.62
C32: domingo | D32: 42701 | E32: 5.48 | F32: 5.47 | G32: 42701 | H32: 2.8 | I32: 2.96 | J32: 42701 | K32: 1.26 | L32: 1.26 | M32: 42701 | N32: 2.61 | O32: 2.5 | P32: 42701 | Q32: 3.97 | R32: 3.66 | S32: 42701 | T32: 0.71 | U32: 0.71
C33: Total | E33: =SUM(E26:E32) -> 249.05 | F33: =SUM(F26:F32) -> 224.02 | H33: =SUM(H26:H32) -> 97.71 | I33: =SUM(I26:I32) -> 61.36 | K33: =SUM(K26:K32) -> 80.73 | L33: =SUM(L26:L32) -> 98.64 | N33: =SUM(N26:N32) -> 77.02 | O33: =SUM(O26:O32) -> 75.49 | Q33: =SUM(Q26:Q32) -> 79.12 | R33: =SUM(R26:R32) -> 77.37 | T33: =SUM(T26:T32) -> 52.79 | U33: =SUM(U26:U32) -> 55.4
F34: =F33/7*30 -> 960.08571 | I34: =I33/7*30 -> 262.97143 | L34: =L33/7*30 -> 422.74286 | O34: =O33/7*30 -> 323.52857 | R34: =R33/7*30 -> 331.58571 | U34: =U33/7*30 -> 237.42857
M36: =(F33+I33+L33+O33+R33+U33)/7*30 -> 2538.3429 | N36: 0.11799 | O36: =M36*N36 -> 299.49907
M37: 4064 | N37: 0.127261 | O37: =M37*N37 -> 517.1887

Sheet Teléfono
A1: https://www.movistar.es/mi-movistar/ | E1: Usuario: B37290293 Contraseña: 1111AAAA | F1: Factura del 11 de Noviembre 2016 | G1: Factura del 11 de Diciembre 2016 | H1: Factura del 11 de Enero 2017
A2: Tienda | B2: Contratos | C2: Fijo | D2: Móvil | E2: Tipo Contrato Fijo ó Móvil
A3: Correhuela | B3: RTB y ADSL | C3: 923264998 | E3: RTB+FIBRA 50MB / 5MB + Llamadas a Fijos | F3: 44.67
A4: MovilFree | C4: 923214407 | E4: RTB+FIBRA 50MB / 5MB + Llamadas a Fijos | F4: 43.4
A5: Vitigudino | C5: 923500500 | E5: RTB+ADSL 10MB + Llamadas a Fijos (Hasta el 15 de Febrero de 2017 50%) | F5: 34.7
A6: Peñaranda | C6: 923543095 | E6: RTB+ADSL 10MB + Llamadas a Fijos | F6: 42.82
A7: Santa Marta | C7: 923332290 | E7: RTB+FIBRA 50MB / 5MB + Llamadas a Fijos | F7: 43.54
A8: Estación | C8: 923230939 | E8: RTB+FIBRA 300MB + Llamadas a Fijos + Móviles (Fibra NO Tiene Descuentos) | F8: 57.75
A9: Estación RDSI* | C9: 923125347 | E9: RDSI+ADSL 10MB + BONO + Bono llamadas a Fijos (RDSI NO Tiene Descuentos) | F9: 92.67
A10: Estación DDI Voz | C10: 923226212 | E10: Número Virtual (DDi NO Tiene Descuentos) | F10: 0
A11: Principe de Vergara/ Diego | B11: Fusión TV+ 4 | C11: 923185610 | D11: 639843010 | E11: FUSION+4 Línea Principal (ilimitadas Ext y 1000 int + 3Gb Datos) | F11: 161
A12: Angel Luis | D12: 619110112 | E12: FUSION+4 Línea Adicional (ilimitadas Ext y 1000 int + 3Gb Datos)
A13: Salva | D13: 636991853 | E13: FUSION+4 Línea Adicional (ilimitadas Ext y 1000 int + 3Gb Datos)
A14: Angelete | D14: 638168461 | E14: FUSION+4 Línea Adicional (ilimitadas Ext y 1000 int + 3Gb Datos)
A15: Juan Carlos | B15: FUSION EMPRESAS 2014 | D15: 616481284 | E15: TARIFA 20 CON ADSL/FIBRA (ilimitadas Ext y 1000 int + 2Gb Datos) | F15: 387.1
A16: Gabriel | D16: 608082959 | E16: TARIFA 20 CON ADSL/FIBRA (ilimitadas Ext y 1000 int + 2Gb Datos)
A17: Juan António | D17: 646571799 | E17: TARIFA 20 CON ADSL/FIBRA (ilimitadas Ext y 1000 int + 2Gb Datos)
A18: Javier | D18: 636991850 | E18: TARIFA 20 CON ADSL/FIBRA (ilimitadas Ext y 1000 int + 2Gb Datos)
A19: Marcos | D19: 628176776 | E19: TARIFA 20 CON ADSL/FIBRA (ilimitadas Ext y 1000 int + 2Gb Datos)
A20: Vicente | D20: 626460568 | E20: TARIFA 20 CON ADSL/FIBRA (ilimitadas Ext y 1000 int + 2Gb Datos)
A21: Andrés | D21: 616481282 | E21: TARIFA 20 CON ADSL/FIBRA (ilimitadas Ext y 1000 int + 2Gb Datos)
A22: MovilFree | D22: 626056199 | E22: TARIFA 20 CON ADSL/FIBRA (ilimitadas Ext y 1000 int + 2Gb Datos)
A23: Vitigudino | D23: 609030055 | E23: TARIFA 20 CON ADSL/FIBRA (ilimitadas Ext y 1000 int + 2Gb Datos)
A24: Peñaranda | D24: 628686492 | E24: TARIFA 20 CON ADSL/FIBRA (ilimitadas Ext y 1000 int + 2Gb Datos)
A25: Estación | D25: 636991851 | E25: TARIFA 30 CON ADSL/FIBRA (ilimitadas Ext y 1000 int + 4Gb Datos + MultiSim)
A26: Correhuela | D26: 616481281 | E26: TARIFA 10 CON ADSL/FIBRA (100 min Ext y 1000 int + 100Mb Datos)
A27: Santa Marta | D27: 650380024 | E27: TARIFA 10 CON ADSL/FIBRA (100 min Ext y 1000 int + 100Mb Datos)
... A31: Padre | D31: 605614460 | E31: TARIFA 5 CON ADSL/FIBRA (10 cts/min + establecimiento, SMS 15 cts)
A32: Total | F32: =SUM(F3:F31)/1.21 -> 750.12397 | G32: =SUM(G3:G31)/1.21 -> 0 | H32: =SUM(H3:H31)/1.21 -> 0

Sheet Ingresos
A1: INGRESOS 2016 | C1: Total | D1: Nacional + Contractual | H1: Nacional | AD1: Territorial | AO1: Otras comisiones / Caja | AY1: MovilFree
D2: Alta ADSL / F300 | E2: Contrato / Migra AV | F2: Contrato MV | G2: Contrato / Migra BV | H2: Migra F300 | I2: Migra F300 / MFE | J2: TV AV | K2: TV MV | L2: TV BV | M2: MFE XDSL | N2: MFE FTTH | O2: Servicios TI | P2: Repos AV | Q2: Canje AV | R2: Canje MV | S2: Canje BV | T2: Extra / Transc AV | U2: Extra / Transc MV | V2: Extra / Transc BV | W2: TMA AV | X2: TMA MV | Y2: TMA BV | Z2: Seguro | AA2: Financia | AB2: Prepago | AC2: MultiSIM | AD2: Alta ADSL / F300 | AE2: Alta F300 / Migra F300 | AF2: Contr. AV / Migras | AG2: Alta / Porta | AH2: Repos. Tarifas | AI2: Alta BAF / MFE | AJ2: Migra F300 / MFE | AK2: Alta / Migra BAF / MFE | AL2: Alta MFE / Migra MFE | AM2: TMA | AN2: Servicio TI | AO2: Aportación Terminal | AP2: Caja Terminal | AQ2: Banco Financia | AR2: Recicla | AS2: Caja Tarjeta SIM | AT2: Caja Accesorio | AU2: Caja Recarga | AV2: PRV PDV | AW2: PRV FFVV | AX2: Pre-Liq PRV FFVV | AY2: Ingresos
A3: ENE | B3: Estación | C3: =SUM(D3:AY3) -> 28734.17 | D3: 646 | E3: 714 | F3: - | G3: 300 | H3: 108 | I3: - | J3: 0 | K3: 400 | L3: 434 | M3: - | N3: - | O3: - | P3: - | Q3: 375 | R3: 450 | S3: 0 | T3: 75 | U3: 120 | V3: 0 | W3: - | X3: - | Y3: - | Z3: 70 | AA3: 231 | AB3: 635 | AC3: 63 | AD3: 285 | AE3: 252 | AF3: 615 | AG3: - | AH3: - | AI3: - | AJ3: - | AK3: - | AL3: - | AM3: - | AN3: - | AO3: 2955.59 | AP3: 6992.64 | AQ3: 8241.43 | AR3: 186.24 | AS3: 242.98 | AT3: 506.77 | AU3: 297.52 | AV3: 3538 | AW3: - | AX3: - | AY3: -
B4: Correhuela | C4: =SUM(D4:AY4) -> 32814.5 | D4: 462 | E4: 568 | F4: - | G4: 240 | H4: 96 | I4: - | J4: 0 | K4: 180 | L4: 416 | M4: - | N4: - | O4: - | P4: - | Q4: 775 | R4: 390 | S4: 10 | T4: 75 | U4: 36 | V4: 0 | W4: - | X4: - | Y4: - | Z4: 7 | AA4: 231 | AB4: 665 | AC4: 35 | AD4: 255 | AE4: 168 | AF4: 360 | AG4: - | AH4: - | AI4: - | AJ4: - | AK4: - | AL4: - | AM4: - | AN4: - | AO4: 3671.37 | AP4: 7624.45 | AQ4: 12466.41 | AR4: 6.24 | AS4: 257.85 | AT4: 559.9 | AU4: 446.28 | AV4: 2813 | AW4: - | AX4: - | AY4: -
B5: Santa Marta | C5: =SUM(D5:AY5) -> 17896.4 | D5: 524 | E5: 680 | F5: - | G5: 130 | H5: 84 | I5: - | J5: 50 | K5: 68 | L5: 260 | M5: - | N5: - | O5: - | P5: - | Q5: 200 | R5: 315 | S5: 10 | T5: 50 | U5: 15 | V5: 0 | W5: - | X5: - | Y5: - | Z5: 126 | AA5: 126 | AB5: 488.75 | AC5: 0 | AD5: 240 | AE5: 196 | AF5: 540 | AG5: - | AH5: - | AI5: - | AJ5: - | AK5: - | AL5: - | AM5: - | AN5: - | AO5: 1567.06 | AP5: 2279.75 | AQ5: 6718.18 | AR5: 6.24 | AS5: 102.48 | AT5: 472.6 | AU5: 338.84 | AV5: 2308.5 | AW5: - | AX5: - | AY5: -
B6: Peñaranda | C6: =SUM(D6:AY6) -> 17654.37 | D6: 296 | E6: 252 | F6: - | G6: 252 | H6: 12 | I6: - | J6: 50 | K6: 80 | L6: 164 | M6: - | N6: - | O6: - | P6: - | Q6: 225 | R6: 240 | S6: 10 | T6: 0 | U6: 30 | V6: 0 | W6: - | X6: - | Y6: - | Z6: 42 | AA6: 112 | AB6: 395 | AC6: 7 | AD6: 165 | AE6: 14 | AF6: 285 | AG6: - | AH6: - | AI6: - | AJ6: - | AK6: - | AL6: - | AM6: - | AN6: - | AO6: 2031.45 | AP6: 4910.82 | AQ6: 4351.9 | AR6: 6.24 | AS6: 196.96 | AT6: 475 | AU6: 719 | AV6: 2332 | AW6: - | AX6: - | AY6: -
B7: Vitigudino | C7: =SUM(D7:AY7) -> 19223.91 | D7: 544 | E7: 480 | F7: - | G7: 260 | H7: 0 | I7: - | J7: 200 | K7: 60 | L7: 324 | M7: - | N7: - | O7: - | P7: - | Q7: 200 | R7: 405 | S7: 0 | T7: 0 | U7: 30 | V7: 0 | W7: - | X7: - | Y7: - | Z7: 14 | AA7: 119 | AB7: 775.5 | AC7: 7 | AD7: 285 | AE7: 0 | AF7: 390 | AG7: - | AH7: - | AI7: - | AJ7: - | AK7: - | AL7: - | AM7: - | AN7: - | AO7: 2731.62 | AP7: 5085.03 | AQ7: 3680 | AR7: 6.24 | AS7: 89.25 | AT7: 427.18 | AU7: 628.09 | AV7: 2483 | AW7: - | AX7: - | AY7: -
B8: Básico GVT | C8: =SUM(D8:AY8) -> 7536.88 | D8: 230 | E8: 92 | F8: 665 | G8: 10 | H8: - | I8: 20 | J8: - | K8: - | L8: - | M8: 55 | N8: 0 | O8: 62 | P8: 60 | Q8: - | R8: - | S8: - | T8: - | U8: - | V8: - | W8: 75 | X8: 0 | Y8: 0 | Z8: - | AA8: - | AB8: - | AC8: - | AD8: - | AE8: - | AF8: - | AG8: 1136 | AH8: 20 | AI8: 262.5 | AJ8: 60 | AK8: - | AL8: 100 | AM8: - | AN8: 159 | AO8: 866.94 | AP8: 156.83 | AQ8: - | AR8: - | AS8: 6.61 | AT8: 0 | AU8: - | AV8: - | AW8: 3150 | AX8: 350 | AY8: -
B9: Básico XCU | C9: =SUM(D9:AY9) -> 0 | D9: N/D | E9: N/D | F9: N/D | G9: N/D | H9: - | I9: N/D | J9: - | K9: - | L9: - | M9: N/D | N9: N/D | O9: N/D | P9: N/D | Q9: - | R9: - | S9: - | T9: - | U9: - | V9: - | W9: N/D | X9: N/D | Y9: N/D | Z9: - | AA9: - | AB9: - | AC9: - | AD9: - | AE9: - | AF9: - | AG9: N/D | AH9: N/D | AI9: N/D | AJ9: N/D | AK9: - | AL9: N/D | AM9: - | AN9: N/D | AQ9: - | AR9: - | AU9: - | AV9: - | AW9: N/D | AX9: N/D | AY9: -
B10: Plus NFG | C10: =SUM(D10:AY10) -> 5652.2 | D10: 10 | E10: 0 | F10: 130 | G10: 10 | H10: - | I10: 40 | J10: - | K10: - | L10: - | M10: 0 | N10: 90 | O10: 60 | P10: 5 | Q10: - | R10: - | S10: - | T10: - | U10: - | V10: - | W10: 200 | X10: 0 | Y10: 0 | Z10: - | AA10: - | AB10: - | AC10: - | AD10: - | AE10: - | AF10: - | AG10: 135 | AH10: 40 | AI10: 84 | AJ10: 120 | AK10: - | AL10: 100 | AM10: - | AN10: 180 | AQ10: - | AR10: - | AU10: - | AV10: - | AW10: 3048.2 | AX10: 1400 | AY10: -
B11: Plus N7D | C11: =SUM(D11:AY11) -> 6406.2 | D11: 130 | E11: 40 | F11: 100 | G11: 0 | H11: - | I11: 10 | J11: - | K11: - | L11: - | M11: 0 | N11: 90 | O11: 60 | P11: 100 | Q11: - | R11: - | S11: - | T11: - | U11: - | V11: - | W11: 0 | X11: 54 | Y11: 10 | Z11: - | AA11: - | AB11: - | AC11: - | AD11: - | AE11: - | AF11: - | AG11: 804 | AH11: 120 | AI11: 150 | AJ11: 10 | AK11: - | AL11: 100 | AM11: - | AN11: 180 | AQ11: - | AR11: - | AU11: - | AV11: - | AW11: 3048.2 | AX11: 1400 | AY11: -
B12: Plus K2Z | C12: =SUM(D12:AY12) -> 4922.2 | D12: 0 | E12: 0 | F12: 0 | G12: 0 | H12: - | I12: 20 | J12: - | K12: - | L12: - | M12: 0 | N12: 0 | O12: 80 | P12: 40 | Q12: - | R12: - | S12: - | T12: - | U12: - | V12: - | W12: 75 | X12: 0 | Y12: 0 | Z12: - | AA12: - | AB12: - | AC12: - | AD12: - | AE12: - | AF12: - | AG12: 0 | AH12: 40 | AI12: 0 | AJ12: 30 | AK12: - | AL12: 0 | AM12: - | AN12: 189 | AQ12: - | AR12: - | AU12: - | AV12: - | AW12: 3048.2 | AX12: 1400 | AY12: -
B13: Total | C13: =SUM(C3:C12)+AY13 -> 143930.83 | D13: =SUM(D3:D12) -> 2842 | E13: =SUM(E3:E12) -> 2826 | F13: =SUM(F3:F12) -> 895 | G13: =SUM(G3:G12) -> 1202 | H13: =SUM(H3:H12) -> 300 | I13: =SUM(I3:I12) -> 90 | J13: =SUM(J3:J12) -> 300 | K13: =SUM(K3:K12) -> 788 | ... AL13: =SUM(AL3:AL12) -> 300 | AM13: 0 | AN13: =SUM(AN3:AN12) -> 708 | AO13: =SUM(AO3:AO12) -> 13824.03 | AP13: =SUM(AP3:AP12) -> 27049.52 | AQ13: =SUM(AQ3:AQ12) -> 35457.92 | AR13: =SUM(AR3:AR12) -> 211.2 | AS13: =SUM(AS3:AS12) -> 896.13 | AT13: =SUM(AT3:AT12) -> 2441.45 | AU13: =SUM(AU3:AU12) -> 2429.73 | ... AX13: =SUM(AX3:AX12) -> 4550 | AY13: 3090
A14: FEB | B14: Estación | C14: =SUM(D14:AY14) -> 23601.83 | D14: 526 | E14: 578 | F14: - | G14: 450 | H14: 84 | I14: - | J14: 50 | K14: 13 | L14: 105 | M14: - | N14: - | O14: - | P14: - | Q14: 425 | R14: 405 | S14: 5 | T14: 25 | U14: 45 | V14: 22 | W14: - | X14: - | Y14: - | Z14: 140 | AA14: 220 | AB14: 267 | AC14: 53 | AD14: 225 | AE14: 210 | AF14: 375 | AG14: - | AH14: - | AI14: - | AJ14: - | AK14: - | AL14: - | AM14: - | AN14: - | AO14: 3472.5 | AP14: 4747.97 | AQ14: 6310.08 | AR14: 0 | AS14: 106.61 | AT14: 782.19 | AU14: 421.48 | AV14: 3538 | AW14: - | AX14: - | AY14: -
B15: Correhuela | C15: =SUM(D15:AY15) -> 18088.94 | D15: 441 | E15: 447 | F15: - | G15: 239 | H15: 72 | I15: - | J15: 0 | K15: 16 | L15: 0 | M15: - | N15: - | O15: - | P15: - | Q15: 400 | R15: 285 | S15: 0 | T15: 0 | U15: 45 | V15: 15 | W15: - | X15: - | Y15: - | Z15: 21 | AA15: 98 | AB15: 199.75 | AC15: 60 | AD15: 255 | AE15: 140 | AF15: 270 | AG15: - | AH15: - | AI15: - | AJ15: - | AK15: - | AL15: - | AM15: - | AN15: - | AO15: 3156.32 | AP15: 5056.19 | AQ15: 3227.68 | AR15: 0 | AS15: 125.62 | AT15: 375.81 | AU15: 330.57 | AV15: 2813 | AW15: - | AX15: - | AY15: -
B16: Santa Marta | C16: =SUM(D16:AY16) -> 14823.5 | D16: 308 | E16: 532 | F16: - | G16: 335 | H16: 72 | I16: - | J16: 200 | K16: 40 | L16: 90 | M16: - | N16: - | O16: - | P16: - | Q16: 150 | R16: 300 | S16: 15 | T16: 0 | U16: 60 | V16: 45 | W16: - | X16: - | Y16: - | Z16: 112 | AA16: 112 | AB16: 226.5 | AC16: 50 | AD16: 180 | AE16: 126 | AF16: 360 | AG16: - | AH16: - | AI16: - | AJ16: - | AK16: - | AL16: - | AM16: - | AN16: - | AO16: 2059.29 | AP16: 2126.28 | AQ16: 4069.58 | AR16: 0 | AS16: 85.95 | AT16: 306.38 | AU16: 297.52 | AV16: 2565 | AW16: - | AX16: - | AY16: -
B17: Peñaranda | C17: =SUM(D17:AY17) -> 9368.1 | D17: 498 | E17: 267 | F17: - | G17: 248 | H17: 0 | I17: - | J17: 150 | K17: 60 | L17: 192 | M17: - | N17: - | O17: - | P17: - | Q17: 50 | R17: 135 | S17: 10 | T17: 25 | U17: 15 | V17: 5 | W17: - | X17: - | Y17: - | Z17: 42 | AA17: 28 | AB17: 132.25 | AC17: 20 | AD17: 270 | AE17: 0 | AF17: 0 | AG17: - | AH17: - | AI17: - | AJ17: - | AK17: - | AL17: - | AM17: - | AN17: - | AO17: 982.36 | AP17: 2302.47 | AQ17: 585.12 | AR17: 0 | AS17: 119 | AT17: 180.9 | AU17: 719 | AV17: 2332 | AW17: - | AX17: - | AY17: -
B18: Vitigudino | C18: =SUM(D18:AY18) -> 15767.35 | D18: 510 | E18: 418 | F18: - | G18: 360 | H18: 24 | I18: - | J18: 100 | K18: 100 | L18: 98 | M18: - | N18: - | O18: - | P18: - | Q18: 100 | R18: 585 | S18: 10 | T18: 25 | U18: 45 | V18: 0 | W18: - | X18: - | Y18: - | Z18: 63 | AA18: 56 | AB18: 205.25 | AC18: 20 | AD18: 255 | AE18: 28 | AF18: 0 | AG18: - | AH18: - | AI18: - | AJ18: - | AK18: - | AL18: - | AM18: - | AN18: - | AO18: 3487.37 | AP18: 4543.71 | AQ18: 1112.39 | AR18: 0 | AS18: 99.17 | AT18: 349.38 | AU18: 690.08 | AV18: 2483 | AW18: - | AX18: - | AY18: -
B19: Básico GVT | C19: =SUM(D19:AY19) -> 8038.52 | D19: 140 | E19: 250 | F19: 750 | G19: 240 | H19: - | I19: 70 | J19: - | K19: - | L19: - | M19: 55 | N19: 90 | O19: 90 | P19: 80 | Q19: - | R19: - | S19: - | T19: - | U19: - | V19: - | W19: 175 | X19: 36 | Y19: 20 | Z19: - | AA19: - | AB19: - | AC19: - | AD19: - | AE19: - | AF19: - | AG19: 1467 | AH19: 40 | AI19: - | AJ19: - | AK19: 765 | AL19: 330 | AM19: - | AN19: 243 | AO19: 197.52 | AP19: 0 | AQ19: - | AR19: - | AS19: 0 | AT19: 0 | AU19: - | AV19: - | AW19: 2650 | AX19: 350 | AY19: -
B20: Básico XCU | C20: =SUM(D20:AY20) -> 0 | D20: N/D | E20: N/D | F20: N/D | G20: N/D | H20: - | I20: N/D | J20: - | K20: - | L20: - | M20: N/D | N20: N/D | O20: N/D | P20: N/D | Q20: - | R20: - | S20: - | T20: - | U20: - | V20: - | W20: N/D | X20: N/D | Y20: N/D | Z20: - | AA20: - | AB20: - | AC20: - | AD20: - | AE20: - | AF20: - | AG20: N/D | AH20: N/D | AI20: - | AJ20: - | AK20: N/D | AL20: N/D | AM20: - | AN20: N/D | AQ20: - | AR20: - | AU20: - | AV20: - | AW20: N/D | AX20: N/D | AY20: -
B21: Plus NFG | C21: =SUM(D21:AY21) -> 7874 | D21: 150 | E21: 400 | F21: 110 | G21: 80 | H21: - | I21: 30 | J21: - | K21: - | L21: - | M21: 55 | N21: 180 | O21: 70 | P21: 80 | Q21: - | R21: - | S21: - | T21: - | U21: - | V21: - | W21: 50 | X21: 0 | Y21: 0 | Z21: - | AA21: - | AB21: - | AC21: - | AD21: - | AE21: - | AF21: - | AG21: 616 | AH21: 80 | AI21: - | AJ21: - | AK21: 903 | AL21: 660 | AM21: - | AN21: 210 | AQ21: - | AR21: - | AU21: - | AV21: - | AW21: 2800 | AX21: 1400 | AY21: -
B22: Plus N7D | C22: =SUM(D22:AY22) -> 6847 | D22: 110 | E22: 280 | F22: 580 | G22: 270 | H22: - | I22: 10 | J22: - | K22: - | L22: - | M22: 55 | N22: 0 | O22: 90 | P22: 60 | Q22: - | R22: - | S22: - | T22: - | U22: - | V22: - | W22: 25 | X22: 0 | Y22: 60 | Z22: - | AA22: - | AB22: - | AC22: - | AD22: - | AE22: - | AF22: - | AG22: 400 | AH22: 60 | AI22: - | AJ22: - | AK22: 477 | AL22: 0 | AM22: - | AN22: 270 | AQ22: - | AR22: - | AU22: - | AV22: - | AW22: 2700 | AX22: 1400 | AY22: -
B23: Plus K2Z | C23: =SUM(D23:AY23) -> 5968 | D23: 0 | E23: 120 | F23: 85 | G23: 70 | H23: - | I23: 40 | J23: - | K23: - | L23: - | M23: 55 | N23: 0 | O23: 100 | P23: 100 | Q23: - | R23: - | S23: - | T23: - | U23: - | V23: - | W23: 0 | X23: 18 | Y23: 0 | Z23: - | AA23: - | AB23: - | AC23: - | AD23: - | AE23: - | AF23: - | AG23: 380 | AH23: 80 | AI23: - | AJ23: - | AK23: 420 | AL23: 0 | AM23: - | AN23: 300 | AQ23: - | AR23: - | AU23: - | AV23: - | AW23: 2800 | AX23: 1400 | AY23: -
B24: Total | C24: =SUM(C14:C23) -> 110377.24 | D24: =SUM(D14:D23) -> 2683 | E24: =SUM(E14:E23) -> 3292 | F24: =SUM(F14:F23) -> 1525 | G24: =SUM(G14:G23) -> 2292 | H24: =SUM(H14:H23) -> 252 | I24: =SUM(I14:I23) -> 150 | J24: =SUM(J14:J23) -> 500 | ... AH24: =SUM(AH14:AH23) -> 260 | AI24: 0 | AJ24: 0 | AK24: =SUM(AK14:AK23) -> 2565 | AL24: =SUM(AL14:AL23) -> 990 | AM24: 0 | AN24: =SUM(AN14:AN23) -> 1023 | AO24: =SUM(AO14:AO23) -> 13355.36 | AP24: =SUM(AP14:AP23) -> 18776.62 | AQ24: =SUM(AQ14:AQ23) -> 15304.85 | AR24: =SUM(AR14:AR23) -> 0 | AS24: =SUM(AS14:AS23) -> 536.35 | AT24: =SUM(AT14:AT23) -> 1994.66 | AU24: =SUM(AU14:AU23) -> 2458.65 | ... AX24: =SUM(AX14:AX23) -> 4550 | AY24: 2987.8
A25: MAR | B25: Estación | C25: =SUM(D25:AY25) -> 20283.32 | D25: 723 | E25: 848 | F25: - | G25: 90 | H25: 110 | I25: - | J25: 15 | K25: 195 | L25: 346 | M25: - | N25: - | O25: - | P25: - | Q25: 350 | R25: 210 | S25: 0 | T25: 75 | U25: 57 | V25: 0 | W25: - | X25: - | Y25: - | Z25: 80 | AA25: 240 | AB25: 231.5 | AC25: 80 | AD25: 0 | AE25: 238 | AF25: 360 | AG25: - | AH25: - | AI25: - | AJ25: - | AK25: - | AL25: - | AM25: - | AN25: - | AO25: 2557.96 | AP25: 2350.41 | AQ25: 6550 | AR25: 0 | AS25: 215.7 | AT25: 397.14 | AU25: 425.61 | AV25: 3538 | AW25: - | AX25: - | AY25: -
B26: Correhuela | C26: =SUM(D26:AY26) -> 16492.66 | D26: 771 | E26: 580 | F26: - | G26: 170 | H26: 110 | I26: - | J26: 200 | K26: 78 | L26: 520 | M26: - | N26: - | O26: - | P26: - | Q26: 175 | R26: 285 | S26: 5 | T26: 25 | U26: 15 | V26: 5 | W26: - | X26: - | Y26: - | Z26: 30 | AA26: 140 | AB26: 212.25 | AC26: 20 | AD26: 0 | AE26: 210 | AF26: 255 | AG26: - | AH26: - | AI26: - | AJ26: - | AK26: - | AL26: - | AM26: - | AN26: - | AO26: 1545.02 | AP26: 3374.62 | AQ26: 3774.38 | AR26: 0 | AS26: 158.67 | AT26: 479.4 | AU26: 541.32 | AV26: 2813 | AW26: - | AX26: - | AY26: -
B27: Santa Marta | C27: =SUM(D27:AY27) -> 20880.06 | D27: 655 | E27: 809 | F27: - | G27: 100 | H27: 60 | I27: - | J27: 5 | K27: 117 | L27: 277 | M27: - | N27: - | O27: - | P27: - | Q27: 425 | R27: 165 | S27: 5 | T27: 25 | U27: 45 | V27: 17 | W27: - | X27: - | Y27: - | Z27: 130 | AA27: 230 | AB27: 198.75 | AC27: 20 | AD27: 225 | AE27: 196 | AF27: 330 | AG27: - | AH27: - | AI27: - | AJ27: - | AK27: - | AL27: - | AM27: - | AN27: - | AO27: 1780.14 | AP27: 1564.58 | AQ27: 10527.15 | AR27: 0 | AS27: 46.28 | AT27: 167.95 | AU27: 194.21 | AV27: 2565 | AW27: - | AX27: - | AY27: -
B28: Peñaranda | C28: =SUM(D28:AY28) -> 10745.3 | D28: 357 | E28: 380 | F28: - | G28: 90 | H28: 0 | I28: - | J28: 0 | K28: 0 | L28: 0 | M28: - | N28: - | O28: - | P28: - | Q28: 75 | R28: 180 | S28: 0 | T28: 0 | U28: 0 | V28: 10 | W28: - | X28: - | Y28: - | Z28: 30 | AA28: 70 | AB28: 104.5 | AC28: 0 | AD28: 180 | AE28: 0 | AF28: 195 | AG28: - | AH28: - | AI28: - | AJ28: - | AK28: - | AL28: - | AM28: - | AN28: - | AO28: 1220.18 | AP28: 2298.76 | AQ28: 2118.18 | AR28: 0 | AS28: 137.19 | AT28: 250.28 | AU28: 950.41 | AV28: 2098.8 | AW28: - | AX28: - | AY28: -
B29: Vitigudino | C29: =SUM(D29:AY29) -> 19029.69 | D29: 624 | E29: 760 | F29: - | G29: 130 | H29: 0 | I29: - | J29: 80 | K29: 117 | L29: 79 | M29: - | N29: - | O29: - | P29: - | Q29: 200 | R29: 465 | S29: 5 | T29: 25 | U29: 90 | V29: 0 | W29: - | X29: - | Y29: - | Z29: 20 | AA29: 160 | AB29: 159 | AC29: 20 | AD29: 255 | AE29: 0 | AF29: 300 | AG29: - | AH29: - | AI29: - | AJ29: - | AK29: - | AL29: - | AM29: - | AN29: - | AO29: 3781.45 | AP29: 4092.56 | AQ29: 3910.24 | AR29: 0 | AS29: 79.33 | AT29: 351.14 | AU29: 842.97 | AV29: 2483 | AW29: - | AX29: - | AY29: -
B30: Básico GVT | C30: =SUM(D30:AY30) -> 5892.82 | D30: 180 | E30: 580 | F30: 310 | G30: 30 | H30: - | I30: 50 | J30: - | K30: - | L30: - | M30: 110 | N30: 180 | O30: 100 | P30: 60 | Q30: - | R30: - | S30: - | T30: - | U30: - | V30: - | W30: 100 | X30: 56 | Y30: 20 | Z30: - | AA30: - | AB30: - | AC30: - | AD30: - | AE30: - | AF30: - | AG30: 1309.5 | AH30: 40 | AI30: - | AJ30: - | AK30: 849 | AL30: 800 | AM30: - | AN30: 228 | AO30: 540.32 | AP30: 0 | AQ30: - | AR30: - | AS30: 0 | AT30: 0 | AU30: - | AV30: - | AW30: 0 | AX30: 350 | AY30: -
B31: Básico XCU | C31: =SUM(D31:AY31) -> 0 | D31: N/D | E31: N/D | F31: N/D | G31: N/D | H31: - | I31: N/D | J31: - | K31: - | L31: - | M31: N/D | N31: N/D | O31: N/D | P31: N/D | Q31: - | R31: - | S31: - | T31: - | U31: - | V31: - | W31: N/D | X31: N/D | Y31: N/D | Z31: - | AA31: - | AB31: - | AC31: - | AD31: - | AE31: - | AF31: - | AG31: N/D | AH31: N/D | AI31: - | AJ31: - | AK31: N/D | AL31: N/D | AM31: - | AN31: N/D | AQ31: - | AR31: - | AU31: - | AV31: - | AW31: N/D | AX31: N/D | AY31: -
B32: Plus NFG | C32: =SUM(D32:AY32) -> 6950 | D32: 60 | E32: 70 | F32: 30 | G32: 0 | H32: - | I32: 10 | J32: - | K32: - | L32: - | M32: 55 | N32: 180 | O32: 50 | P32: 80 | Q32: - | R32: - | S32: - | T32: - | U32: - | V32: - | W32: 350 | X32: 20 | Y32: 10 | Z32: - | AA32: - | AB32: - | AC32: - | AD32: - | AE32: - | AF32: - | AG32: 520 | AH32: 40 | AI32: - | AJ32: - | AK32: 525 | AL32: 600 | AM32: - | AN32: 150 | AQ32: - | AR32: - | AU32: - | AV32: - | AW32: 2800 | AX32: 1400 | AY32: -
B33: Plus N7D | C33: =SUM(D33:AY33) -> 7512 | D33: 50 | E33: 190 | F33: 150 | G33: 0 | H33: - | I33: 120 | J33: - | K33: - | L33: - | M33: 55 | N33: 0 | O33: 90 | P33: 80 | Q33: - | R33: - | S33: - | T33: - | U33: - | V33: - | W33: 225 | X33: 0 | Y33: 20 | Z33: - | AA33: - | AB33: - | AC33: - | AD33: - | AE33: - | AF33: - | AG33: 770 | AH33: 80 | AI33: - | AJ33: - | AK33: 612 | AL33: 600 | AM33: - | AN33: 270 | AQ33: - | AR33: - | AU33: - | AV33: - | AW33: 2800 | AX33: 1400 | AY33: -
B34: Plus K2Z | C34: =SUM(D34:AY34) -> 5435 | D34: 60 | E34: 80 | F34: 10 | G34: 0 | H34: - | I34: 20 | J34: - | K34: - | L34: - | M34: 0 | N34: 0 | O34: 80 | P34: 120 | Q34: - | R34: - | S34: - | T34: - | U34: - | V34: - | W34: 50 | X34: 20 | Y34: 10 | Z34: - | AA34: - | AB34: - | AC34: - | AD34: - | AE34: - | AF34: - | AG34: 280 | AH34: 100 | AI34: - | AJ34: - | AK34: 165 | AL34: 0 | AM34: - | AN34: 240 | AQ34: - | AR34: - | AU34: - | AV34: - | AW34: 2800 | AX34: 1400 | AY34: -
B35: Total | C35: =SUM(C25:C34) -> 113220.85 | D35: =SUM(D25:D34) -> 3480 | E35: =SUM(E25:E34) -> 4297 | F35: =SUM(F25:F34) -> 500 | G35: =SUM(G25:G34) -> 610 | H35: =SUM(H25:H34) -> 280 | I35: =SUM(I25:I34) -> 200 | J35: =SUM(J25:J34) -> 300 | ... AH35: =SUM(AH25:AH34) -> 260 | AI35: 0 | AJ35: 0 | AK35: =SUM(AK25:AK34) -> 2151 | AL35: =SUM(AL25:AL34) -> 2000 | AM35: 0 | AN35: =SUM(AN25:AN34) -> 888 | AO35: =SUM(AO25:AO34) -> 11425.07 | AP35: =SUM(AP25:AP34) -> 13680.93 | AQ35: =SUM(AQ25:AQ34) -> 26879.95 | AR35: =SUM(AR25:AR34) -> 0 | AS35: =SUM(AS25:AS34) -> 637.17 | AT35: =SUM(AT25:AT34) -> 1645.91 | AU35: =SUM(AU25:AU34) -> 2954.52 | ... AX35: =SUM(AX25:AX34) -> 4550 | AY35: 3040
A36: ABR | B36: Estación | C36: =SUM(D36:AY36) -> 25700.98 | D36: 743 | E36: 536 | F36: - | G36: 360 | H36: 120 | I36: - | J36: 80 | K36: 117 | L36: 434 | M36: - | N36: - | O36: - | P36: - | Q36: 425 | R36: 435 | S36: 5 | T36: 25 | U36: 75 | V36: 0 | W36: - | X36: - | Y36: - | Z36: 110 | AA36: 300 | AB36: 741 | AC36: 10 | AD36: 255 | AE36: 266 | AF36: 0 | AG36: - | AH36: - | AI36: - | AJ36: - | AK36: - | AL36: - | AM36: - | AN36: - | AO36: 3168.6 | AP36: 3405 | AQ36: 9465.84 | AR36: 5.5 | AS36: 181.81 | AT36: 535.6 | AU36: 363.63 | AV36: 3538 | AW36: - | AX36: - | AY36: -
B37: Correhuela | C37: =SUM(D37:AY37) -> 17348.42 | D37: 684 | E37: 390 | F37: - | G37: 200 | H37: 60 | I37: - | J37: 0 | K37: 0 | L37: 188 | M37: - | N37: - | O37: - | P37: - | Q37: 125 | R37: 375 | S37: 5 | T37: 0 | U37: 45 | V37: 5 | W37: - | X37: - | Y37: - | Z37: 10 | AA37: 80 | AB37: 760.75 | AC37: 40 | AD37: 0 | AE37: 168 | AF37: 0 | AG37: - | AH37: - | AI37: - | AJ37: - | AK37: - | AL37: - | AM37: - | AN37: - | AO37: 1868.13 | AP37: 5480.05 | AQ37: 2430.57 | AR37: 0 | AS37: 148.76 | AT37: 352.33 | AU37: 1119.83 | AV37: 2813 | AW37: - | AX37: - | AY37: -
B38: Santa Marta | C38: =SUM(D38:AY38) -> 14972.24 | D38: 537 | E38: 565 | F38: - | G38: 271 | H38: 90 | I38: - | J38: 150 | K38: 0 | L38: 109 | M38: - | N38: - | O38: - | P38: - | Q38: 150 | R38: 255 | S38: 10 | T38: 50 | U38: 30 | V38: 0 | W38: - | X38: - | Y38: - | Z38: 70 | AA38: 160 | AB38: 253 | AC38: 20 | AD38: 195 | AE38: 168 | AF38: 0 | AG38: - | AH38: - | AI38: - | AJ38: - | AK38: - | AL38: - | AM38: - | AN38: - | AO38: 1449.99 | AP38: 3117.59 | AQ38: 3892.56 | AR38: 0 | AS38: 104.13 | AT38: 462.45 | AU38: 297.52 | AV38: 2565 | AW38: - | AX38: - | AY38: -
B39: Peñaranda | C39: =SUM(D39:AY39) -> 13027.21 | D39: 429 | E39: 312 | F39: - | G39: 200 | H39: 0 | I39: - | J39: 0 | K39: 39 | L39: 315 | M39: - | N39: - | O39: - | P39: - | Q39: 125 | R39: 285 | S39: 10 | T39: 0 | U39: 60 | V39: 0 | W39: - | X39: - | Y39: - | Z39: 40 | AA39: 110 | AB39: 273 | AC39: 10 | AD39: 165 | AE39: 0 | AF39: 135 | AG39: - | AH39: - | AI39: - | AJ39: - | AK39: - | AL39: - | AM39: - | AN39: - | AO39: 1445.07 | AP39: 2764.8 | AQ39: 2622.31 | AR39: 0 | AS39: 66.11 | AT39: 243.47 | AU39: 1045.45 | AV39: 2332 | AW39: - | AX39: - | AY39: -
B40: Vitigudino | C40: =SUM(D40:AY40) -> 18296.49 | D40: 585 | E40: 312 | F40: - | G40: 290 | H40: 0 | I40: - | J40: 80 | K40: 78 | L40: 227 | M40: - | N40: - | O40: - | P40: - | Q40: 50 | R40: 705 | S40: 0 | T40: 25 | U40: 60 | V40: 0 | W40: - | X40: - | Y40: - | Z40: 40 | AA40: 150 | AB40: 304.75 | AC40: 0 | AD40: 240 | AE40: 0 | AF40: 120 | AG40: - | AH40: - | AI40: - | AJ40: - | AK40: - | AL40: - | AM40: - | AN40: - | AO40: 3669.2 | AP40: 3806.9 | AQ40: 3841.32 | AR40: 0 | AS40: 72.72 | AT40: 363.22 | AU40: 793.38 | AV40: 2483 | AW40: - | AX40: - | AY40: -
B41: Básico GVT | C41: =SUM(D41:AY41) -> 9800.38 | D41: 55 | E41: 770 | F41: 275 | G41: 220 | H41: - | I41: 10 | J41: - | K41: - | L41: - | M41: 0 | N41: 200 | O41: 60 | P41: 60 | Q41: - | R41: - | S41: - | T41: - | U41: - | V41: - | W41: 50 | X41: 72 | Y41: 0 | Z41: - | AA41: - | AB41: - | AC41: - | AD41: - | AE41: - | AF41: - | AG41: 1092 | AH41: 60 | AI41: - | AJ41: - | AK41: 0 | AL41: 0 | AM41: 0 | AN41: 180 | AO41: 46.38 | AP41: 0 | AQ41: - | AR41: - | AS41: 0 | AT41: 0 | AU41: - | AV41: - | AW41: 6300 | AX41: 350 | AY41: -
B42: Básico XCU | C42: =SUM(D42:AY42) -> 4463 | D42: 85 | E42: 280 | F42: 65 | G42: 60 | H42: - | I42: 10 | J42: - | K42: - | L42: - | M42: 0 | N42: 0 | O42: 50 | P42: 40 | Q42: - | R42: - | S42: - | T42: - | U42: - | V42: - | W42: 0 | X42: 0 | Y42: 0 | Z42: - | AA42: - | AB42: - | AC42: - | AD42: - | AE42: - | AF42: - | AG42: 553 | AH42: 60 | AI42: - | AJ42: - | AK42: 0 | AL42: 0 | AM42: 0 | AN42: 210 | AQ42: - | AR42: - | AU42: - | AV42: - | AW42: 2700 | AX42: 350 | AY42: -
B43: Plus NFG | C43: =SUM(D43:AY43) -> 6541 | D43: 140 | E43: 0 | F43: 605 | G43: 150 | H43: - | I43: 20 | J43: - | K43: - | L43: - | M43: 0 | N43: 100 | O43: 20 | P43: 60 | Q43: - | R43: - | S43: - | T43: - | U43: - | V43: - | W43: 325 | X43: 54 | Y43: 0 | Z43: - | AA43: - | AB43: - | AC43: - | AD43: - | AE43: - | AF43: - | AG43: 525 | AH43: 60 | AI43: - | AJ43: - | AK43: 0 | AL43: 0 | AM43: 222 | AN43: 60 | AQ43: - | AR43: - | AU43: - | AV43: - | AW43: 2800 | AX43: 1400 | AY43: -
B44: Plus N7D | C44: =SUM(D44:AY44) -> 4977 | D44: 60 | E44: 0 | F44: 0 | G44: 0 | H44: - | I44: 30 | J44: - | K44: - | L44: - | M44: 100 | N44: 0 | O44: 60 | P44: 60 | Q44: - | R44: - | S44: - | T44: - | U44: - | V44: - | W44: 125 | X44: 18 | Y44: 0 | Z44: - | AA44: - | AB44: - | AC44: - | AD44: - | AE44: - | AF44: - | AG44: 0 | AH44: 60 | AI44: - | AJ44: - | AK44: 0 | AL44: 0 | AM44: 84 | AN44: 180 | AQ44: - | AR44: - | AU44: - | AV44: - | AW44: 2800 | AX44: 1400 | AY44: -
B45: Plus K2Z | C45: =SUM(D45:AY45) -> 6694 | D45: 0 | E45: 40 | F45: 380 | G45: 210 | H45: - | I45: 40 | J45: - | K45: - | L45: - | M45: 0 | N45: 0 | O45: 80 | P45: 120 | Q45: - | R45: - | S45: - | T45: - | U45: - | V45: - | W45: 0 | X45: 36 | Y45: 0 | Z45: - | AA45: - | AB45: - | AC45: - | AD45: - | AE45: - | AF45: - | AG45: 1210 | AH45: 120 | AI45: - | AJ45: - | AK45: 0 | AL45: 0 | AM45: 18 | AN45: 240 | AQ45: - | AR45: - | AU45: - | AV45: - | AW45: 2800 | AX45: 1400 | AY45: -
B46: Total | C46: =SUM(C36:C45) -> 121820.72 | D46: =SUM(D36:D45) -> 3318 | E46: =SUM(E36:E45) -> 3205 | F46: =SUM(F36:F45) -> 1325 | G46: =SUM(G36:G45) -> 1961 | H46: =SUM(H36:H45) -> 270 | I46: =SUM(I36:I45) -> 110 | J46: =SUM(J36:J45) -> 310 | ... AH46: =SUM(AH36:AH45) -> 360 | AI46: 0 | AJ46: 0 | AK46: =SUM(AK36:AK45) -> 0 | AL46: =SUM(AL36:AL45) -> 0 | AM46: =SUM(AM36:AM45) -> 324 | AN46: =SUM(AN36:AN45) -> 870 | AO46: =SUM(AO36:AO45) -> 11647.37 | AP46: =SUM(AP36:AP45) -> 18574.34 | AQ46: =SUM(AQ36:AQ45) -> 22252.6 | AR46: =SUM(AR36:AR45) -> 5.5 | ... AX46: =SUM(AX36:AX45) -> 4900 | AY46: 2837
A47: MAY | B47: Estación | C47: =SUM(D47:AY47) -> 23222.29 | D47: 663 | E47: 329 | F47: - | G47: 230 | H47: 190 | I47: - | J47: 80 | K47: 0 | L47: 240 | M47: - | N47: - | O47: - | P47: - | Q47: 342 | R47: 178 | S47: 0 | T47: 0 | U47: 12 | V47: 28 | W47: - | X47: - | Y47: - | Z47: 50 | AA47: 220 | AB47: 582.5 | AC47: 70 | AD47: 270 | AE47: 350 | AF47: 0 | AG47: - | AH47: - | AI47: - | AJ47: - | AK47: - | AL47: - | AM47: - | AN47: - | AO47: 2636.54 | AP47: 3197.1 | AQ47: 8455.37 | AR47: 674.9 | AS47: 218 | AT47: 411.69 | AU47: 256.19 | AV47: 3538 | AW47: - | AX47: - | AY47: -
B48: Correhuela | C48: =SUM(D48:AY48) -> 17262.21 | D48: 702 | E48: 299 | F48: - | G48: 110 | H48: 120 | I48: - | J48: 0 | K48: 0 | L48: 160 | M48: - | N48: - | O48: - | P48: - | Q48: 224 | R48: 298 | S48: 0 | T48: 22 | U48: 0 | V48: 16 | W48: - | X48: - | Y48: - | Z48: 30 | AA48: 100 | AB48: 508.25 | AC48: 20 | AD48: 270 | AE48: 252 | AF48: 0 | AG48: - | AH48: - | AI48: - | AJ48: - | AK48: - | AL48: - | AM48: - | AN48: - | AO48: 2314.95 | AP48: 3979.23 | AQ48: 3998.33 | AR48: 130 | AS48: 145.45 | AT48: 336.78 | AU48: 413.22 | AV48: 2813 | AW48: - | AX48: - | AY48: -
B49: Santa Marta | C49: =SUM(D49:AY49) -> 13912.94 | D49: 546 | E49: 249 | F49: - | G49: 100 | H49: 110 | I49: - | J49: 80 | K49: 39 | L49: 110 | M49: - | N49: - | O49: - | P49: - | Q49: 72 | R49: 86 | S49: 0 | T49: 0 | U49: 12 | V49: 36 | W49: - | X49: - | Y49: - | Z49: 110 | AA49: 70 | AB49: 322.25 | AC49: 0 | AD49: 210 | AE49: 210 | AF49: 0 | AG49: - | AH49: - | AI49: - | AJ49: - | AK49: - | AL49: - | AM49: - | AN49: - | AO49: 2876.71 | AP49: 3475.93 | AQ49: 1854.54 | AR49: 150 | AS49: 132.23 | AT49: 397.11 | AU49: 99.17 | AV49: 2565 | AW49: - | AX49: - | AY49: -
B50: Peñaranda | C50: =SUM(D50:AY50) -> 10671.39 | D50: 351 | E50: 230 | F50: - | G50: 150 | H50: 0 | I50: - | J50: 0 | K50: 39 | L50: 198 | M50: - | N50: - | O50: - | P50: - | Q50: 102 | R50: 36 | S50: 0 | T50: 36 | U50: 0 | V50: 20 | W50: - | X50: - | Y50: - | Z50: 10 | AA50: 30 | AB50: 374.75 | AC50: 30 | AD50: 0 | AE50: 0 | AF50: 195 | AG50: - | AH50: - | AI50: - | AJ50: - | AK50: - | AL50: - | AM50: - | AN50: - | AO50: 1367.13 | AP50: 2340.24 | AQ50: 1494.21 | AR50: 0 | AS50: 138.84 | AT50: 341.85 | AU50: 855.37 | AV50: 2332 | AW50: - | AX50: - | AY50: -
B51: Vitigudino | C51: =SUM(D51:AY51) -> 15070.17 | D51: 556 | E51: 329 | F51: - | G51: 240 | H51: 0 | I51: - | J51: 0 | K51: 0 | L51: 99 | M51: - | N51: - | O51: - | P51: - | Q51: 102 | R51: 400 | S51: 0 | T51: 0 | U51: 0 | V51: 40 | W51: - | X51: - | Y51: - | Z51: 0 | AA51: 40 | AB51: 382.75 | AC51: 30 | AD51: 225 | AE51: 0 | AF51: 195 | AG51: - | AH51: - | AI51: - | AJ51: - | AK51: - | AL51: - | AM51: - | AN51: - | AO51: 3826.05 | AP51: 3897.26 | AQ51: 967.76 | AR51: 65 | AS51: 33.05 | AT51: 258.48 | AU51: 900.82 | AV51: 2483 | AW51: - | AX51: - | AY51: -
B52: Básico GVT | C52: =SUM(D52:AY52) -> 6964.71 | D52: 70 | E52: 80 | F52: 100 | G52: 20 | H52: - | I52: 50 | J52: - | K52: - | L52: - | M52: 200 | N52: 100 | O52: 20 | P52: 140 | Q52: - | R52: - | S52: - | T52: - | U52: - | V52: - | W52: 50 | X52: 162 | Y52: 0 | Z52: - | AA52: - | AB52: - | AC52: - | AD52: - | AE52: - | AF52: - | AG52: 0 | AH52: 80 | AI52: - | AJ52: - | AK52: 690 | AL52: 735 | AM52: 148 | AN52: 80 | AO52: 1127.31 | AP52: 16.12 | AQ52: - | AR52: - | AS52: 46.28 | AT52: 0 | AU52: - | AV52: - | AW52: 2700 | AX52: 350 | AY52: -
B53: Básico XCU | C53: =SUM(D53:AY53) -> 4113 | D53: 40 | E53: 70 | F53: 125 | G53: 0 | H53: - | I53: 0 | J53: - | K53: - | L53: - | M53: 0 | N53: 100 | O53: 60 | P53: 60 | Q53: - | R53: - | S53: - | T53: - | U53: - | V53: - | W53: 125 | X53: 108 | Y53: 0 | Z53: - | AA53: - | AB53: - | AC53: - | AD53: - | AE53: - | AF53: - | AG53: 0 | AH53: 40 | AI53: - | AJ53: - | AK53: 375 | AL53: 168 | AM53: 172 | AN53: 120 | AQ53: - | AR53: - | AU53: - | AV53: - | AW53: 2200 | AX53: 350 | AY53: -
B54: Plus NFG | C54: =SUM(D54:AY54) -> 6595 | D54: 20 | E54: 100 | F54: 45 | G54: 0 | H54: - | I54: 70 | J54: - | K54: - | L54: - | M54: 100 | N54: 100 | O54: 40 | P54: 80 | Q54: - | R54: - | S54: - | T54: - | U54: - | V54: - | W54: 225 | X54: 90 | Y54: 0 | Z54: - | AA54: - | AB54: - | AC54: - | AD54: - | AE54: - | AF54: - | AG54: 250 | AH54: 40 | AI54: - | AJ54: - | AK54: 555 | AL54: 420 | AM54: 240 | AN54: 120 | AQ54: - | AR54: - | AU54: - | AV54: - | AW54: 2700 | AX54: 1400 | AY54: -
B55: Plus N7D | C55: =SUM(D55:AY55) -> 10339 | D55: 0 | E55: 240 | F55: 425 | G55: 30 | H55: - | I55: 10 | J55: - | K55: - | L55: - | M55: 200 | N55: 500 | O55: 40 | P55: 120 | Q55: - | R55: - | S55: - | T55: - | U55: - | V55: - | W55: 75 | X55: 162 | Y55: 0 | Z55: - | AA55: - | AB55: - | AC55: - | AD55: - | AE55: - | AF55: - | AG55: 935 | AH55: 160 | AI55: - | AJ55: - | AK55: 1500 | AL55: 1470 | AM55: 192 | AN55: 180 | AQ55: - | AR55: - | AU55: - | AV55: - | AW55: 2700 | AX55: 1400 | AY55: -
B56: Plus K2Z | C56: =SUM(D56:AY56) -> 6325 | D56: 50 | E56: 100 | F56: 65 | G56: 50 | H56: - | I56: 0 | J56: - | K56: - | L56: - | M56: 100 | N56: 100 | O56: 80 | P56: 60 | Q56: - | R56: - | S56: - | T56: - | U56: - | V56: - | W56: 50 | X56: 18 | Y56: 0 | Z56: - | AA56: - | AB56: - | AC56: - | AD56: - | AE56: - | AF56: - | AG56: 560 | AH56: 40 | AI56: - | AJ56: - | AK56: 345 | AL56: 315 | AM56: 52 | AN56: 240 | AQ56: - | AR56: - | AU56: - | AV56: - | AW56: 2700 | AX56: 1400 | AY56: -
B57: Total | C57: =SUM(C47:C56) -> 114475.71 | D57: =SUM(D47:D56) -> 2998 | E57: =SUM(E47:E56) -> 2026 | F57: =SUM(F47:F56) -> 760 | G57: =SUM(G47:G56) -> 930 | H57: =SUM(H47:H56) -> 420 | I57: =SUM(I47:I56) -> 130 | J57: =SUM(J47:J56) -> 160 | ... AH57: =SUM(AH47:AH56) -> 360 | AI57: 0 | AJ57: 0 | AK57: =SUM(AK47:AK56) -> 3465 | AL57: =SUM(AL47:AL56) -> 3108 | AM57: =SUM(AM47:AM56) -> 804 | AN57: =SUM(AN47:AN56) -> 740 | AO57: =SUM(AO47:AO56) -> 14148.69 | AP57: =SUM(AP47:AP56) -> 16905.88 | AQ57: =SUM(AQ47:AQ56) -> 16770.21 | AR57: =SUM(AR47:AR56) -> 1019.9 | ... AX57: =SUM(AX47:AX56) -> 4900 | AY57: 3013
A58: JUN | B58: Estación | C58: =SUM(D58:AY58) -> 19385.98 | D58: 469 | E58: 244 | F58: - | G58: 110 | H58: 80 | I58: - | J58: 0 | K58: 0 | L58: 250 | M58: - | N58: - | O58: - | P58: - | Q58: 225 | R58: 360 | S58: 0 | T58: 0 | U58: 6 | V58: 29 | W58: - | X58: - | Y58: - | Z58: 120 | AA58: 200 | AB58: 737 | AC58: 14 | AD58: 0 | AE58: 0 | AF58: 0 | AG58: - | AH58: - | AI58: - | AJ58: - | AK58: - | AL58: - | AM58: - | AN58: - | AO58: 2025.96 | AP58: 2813.77 | AQ58: 6953.71 | AR58: 194 | AS58: 206.8 | AT58: 532.89 | AU58: 276.85 | AV58: 3538 | AW58: - | AX58: - | AY58: -
B59: Correhuela | C59: =SUM(D59:AY59) -> 21374.27 | D59: 839 | E59: 300 | F59: - | G59: 190 | H59: 100 | I59: - | J59: 0 | K59: 39 | L59: 208 | M59: - | N59: - | O59: - | P59: - | Q59: 375 | R59: 300 | S59: 0 | T59: 9 | U59: 0 | V59: 0 | W59: - | X59: - | Y59: - | Z59: 60 | AA59: 170 | AB59: 744.75 | AC59: 46 | AD59: 330 | AE59: 168 | AF59: 225 | AG59: - | AH59: - | AI59: - | AJ59: - | AK59: - | AL59: - | AM59: - | AN59: - | AO59: 1372.66 | AP59: 5181.72 | AQ59: 6170.24 | AR59: 42 | AS59: 125.61 | AT59: 1073.56 | AU59: 491.73 | AV59: 2813 | AW59: - | AX59: - | AY59: -
B60: Santa Marta | C60: =SUM(D60:AY60) -> 14019.27 | D60: 391 | E60: 96 | F60: - | G60: 60 | H60: 40 | I60: - | J60: 0 | K60: 0 | L60: 169 | M60: - | N60: - | O60: - | P60: - | Q60: 100 | R60: 225 | S60: 0 | T60: 0 | U60: 0 | V60: 0 | W60: - | X60: - | Y60: - | Z60: 80 | AA60: 160 | AB60: 241 | AC60: 32 | AD60: 0 | AE60: 0 | AF60: 285 | AG60: - | AH60: - | AI60: - | AJ60: - | AK60: - | AL60: - | AM60: - | AN60: - | AO60: 993.79 | AP60: 2159.68 | AQ60: 5245.45 | AR60: 355 | AS60: 79.33 | AT60: 543.68 | AU60: 198.34 | AV60: 2565 | AW60: - | AX60: - | AY60: -
B61: Peñaranda | C61: =SUM(D61:AY61) -> 11712.91 | D61: 234 | E61: 202 | F61: - | G61: 90 | H61: 0 | I61: - | J61: 240 | K61: 117 | L61: 307 | M61: - | N61: - | O61: - | P61: - | Q61: 75 | R61: 315 | S61: 0 | T61: 0 | U61: 25 | V61: 0 | W61: - | X61: - | Y61: - | Z61: 40 | AA61: 100 | AB61: 269 | AC61: 14 | AD61: 0 | AE61: 0 | AF61: 135 | AG61: - | AH61: - | AI61: - | AJ61: - | AK61: - | AL61: - | AM61: - | AN61: - | AO61: 950.41 | AP61: 1290.82 | AQ61: 3499.17 | AR61: 0 | AS61: 125.61 | AT61: 331.24 | AU61: 1020.66 | AV61: 2332 | AW61: - | AX61: - | AY61: -
B62: Vitigudino | C62: =SUM(D62:AY62) -> 15690.46 | D62: 536 | E62: 184 | F62: - | G62: 100 | H62: 0 | I62: - | J62: 0 | K62: 0 | L62: 188 | M62: - | N62: - | O62: - | P62: - | Q62: 50 | R62: 870 | S62: 0 | T62: 0 | U62: 0 | V62: 0 | W62: - | X62: - | Y62: - | Z62: 60 | AA62: 150 | AB62: 304.75 | AC62: 0 | AD62: 210 | AE62: 0 | AF62: 0 | AG62: - | AH62: - | AI62: - | AJ62: - | AK62: - | AL62: - | AM62: - | AN62: - | AO62: 2820.41 | AP62: 4055.28 | AQ62: 2342.06 | AR62: 0 | AS62: 66.11 | AT62: 316.31 | AU62: 954.54 | AV62: 2483 | AW62: - | AX62: - | AY62: -
B63: Básico GVT | C63: =SUM(D63:AY63) -> 7777.25 | D63: 60 | E63: 200 | F63: 395 | G63: 35 | H63: - | I63: 10 | J63: - | K63: - | L63: - | M63: 0 | N63: 200 | O63: 60 | P63: 60 | Q63: - | R63: - | S63: - | T63: - | U63: - | V63: - | W63: 50 | X63: 0 | Y63: 0 | Z63: - | AA63: - | AB63: - | AC63: - | AD63: - | AE63: - | AF63: - | AG63: 807.5 | AH63: - | AI63: - | AJ63: - | AK63: 690 | AL63: 420 | AM63: 0 | AN63: 0 | AO63: 1894.14 | AP63: 92.72 | AQ63: - | AR63: - | AS63: 52.89 | AT63: 0 | AU63: - | AV63: - | AW63: 2400 | AX63: 350 | AY63: -
B64: Básico XCU | C64: =SUM(D64:AY64) -> 4929 | D64: 120 | E64: 0 | F64: 405 | G64: 0 | H64: - | I64: 0 | J64: - | K64: - | L64: - | M64: 0 | N64: 200 | O64: 50 | P64: 0 | Q64: - | R64: - | S64: - | T64: - | U64: - | V64: - | W64: 50 | X64: 54 | Y64: 0 | Z64: - | AA64: - | AB64: - | AC64: - | AD64: - | AE64: - | AF64: - | AG64: 505 | AH64: - | AI64: - | AJ64: - | AK64: 375 | AL64: 420 | AM64: 0 | AN64: 0 | AQ64: - | AR64: - | AU64: - | AV64: - | AW64: 2400 | AX64: 350 | AY64: -
B65: Plus NFG | C65: =SUM(D65:AY65) -> 3070 | D65: 90 | E65: 0 | F65: 20 | G65: 0 | H65: - | I65: 30 | J65: - | K65: - | L65: - | M65: 0 | N65: 100 | O65: 70 | P65: 40 | Q65: - | R65: - | S65: - | T65: - | U65: - | V65: - | W65: 175 | X65: 90 | Y65: 0 | Z65: - | AA65: - | AB65: - | AC65: - | AD65: - | AE65: - | AF65: - | AG65: 90 | AH65: - | AI65: - | AJ65: - | AK65: 555 | AL65: 0 | AM65: 200 | AN65: 210 | AQ65: - | AR65: - | AU65: - | AV65: - | AW65: 0 | AX65: 1400 | AY65: -
B66: Plus N7D | C66: =SUM(D66:AY66) -> 7452 | D66: 30 | E66: 0 | F66: 155 | G66: 0 | H66: - | I66: 10 | J66: - | K66: - | L66: - | M66: 100 | N66: 0 | O66: 60 | P66: 100 | Q66: - | R66: - | S66: - | T66: - | U66: - | V66: - | W66: 400 | X66: 0 | Y66: 20 | Z66: - | AA66: - | AB66: - | AC66: - | AD66: - | AE66: - | AF66: - | AG66: 369 | AH66: - | AI66: - | AJ66: - | AK66: 1500 | AL66: 0 | AM66: 328 | AN66: 180 | AQ66: - | AR66: - | AU66: - | AV66: - | AW66: 2800 | AX66: 1400 | AY66: -
B67: Plus K2Z | C67: =SUM(D67:AY67) -> 6843.5 | D67: 0 | E67: 80 | F67: 135 | G67: 10 | H67: - | I67: 0 | J67: - | K67: - | L67: - | M67: 0 | N67: 0 | O67: 80 | P67: 60 | Q67: - | R67: - | S67: - | T67: - | U67: - | V67: - | W67: 75 | X67: 144 | Y67: 0 | Z67: - | AA67: - | AB67: - | AC67: - | AD67: - | AE67: - | AF67: - | AG67: 1318.5 | AH67: - | AI67: - | AJ67: - | AK67: 345 | AL67: 0 | AM67: 156 | AN67: 240 | AQ67: - | AR67: - | AU67: - | AV67: - | AW67: 2800 | AX67: 1400 | AY67: -
B68: Total | C68: =SUM(C58:C67) -> 112254.64 | D68: =SUM(D58:D67) -> 2769 | E68: =SUM(E58:E67) -> 1306 | F68: =SUM(F58:F67) -> 1110 | G68: =SUM(G58:G67) -> 595 | H68: =SUM(H58:H67) -> 220 | I68: =SUM(I58:I67) -> 50 | J68: =SUM(J58:J67) -> 240 | ... AG68: =SUM(AG58:AG67) -> 3090 | AH68: 0 | AI68: 0 | AJ68: 0 | AK68: =SUM(AK58:AK67) -> 3465 | AL68: =SUM(AL58:AL67) -> 840 | AM68: =SUM(AM58:AM67) -> 684 | AN68: =SUM(AN58:AN67) -> 630 | AO68: =SUM(AO58:AO67) -> 10057.37 | AP68: =SUM(AP58:AP67) -> 15593.99 | AQ68: =SUM(AQ58:AQ67) -> 24210.63 | AR68: =SUM(AR58:AR67) -> 591 | ... AX68: =SUM(AX58:AX67) -> 4900 | AY68: 3337
A69: JUL | B69: Estación | C69: =SUM(D69:AY69) -> 27315.37 | D69: 528 | E69: 186 | F69: - | G69: 560 | H69: 180 | I69: - | J69: 117 | K69: 702 | L69: 230 | M69: - | N69: - | O69: - | P69: - | Q69: 275 | R69: 300 | S69: 35 | T69: 75 | U69: 15 | V69: 25 | W69: - | X69: - | Y69: - | Z69: 25 | AA69: 100 | AB69: 509.5 | AC69: 62 | AD69: 180 | AE69: 0 | AF69: 225 | AG69: - | AH69: - | AI69: - | AJ69: - | AK69: - | AL69: - | AM69: - | AN69: - | AO69: 2189.76 | AP69: 6190.9 | AQ69: 9448.67 | AR69: 386.15 | AS69: 158.67 | AT69: 577.86 | AU69: 495.86 | AV69: 3538 | AW69: - | AX69: - | AY69: -
B70: Correhuela | C70: =SUM(D70:AY70) -> 24835.44 | D70: 518 | E70: 116 | F70: - | G70: 700 | H70: 80 | I70: - | J70: 0 | K70: 234 | L70: 130 | M70: - | N70: - | O70: - | P70: - | Q70: 350 | R70: 465 | S70: 60 | T70: 50 | U70: 15 | V70: 15 | W70: - | X70: - | Y70: - | Z70: 10 | AA70: 110 | AB70: 432.25 | AC70: 36 | AD70: 180 | AE70: 0 | AF70: 0 | AG70: - | AH70: - | AI70: - | AJ70: - | AK70: - | AL70: - | AM70: - | AN70: - | AO70: 2100.95 | AP70: 7157.97 | AQ70: 7485.86 | AR70: 659.15 | AS70: 242.76 | AT70: 572.85 | AU70: 301.65 | AV70: 2813 | AW70: - | AX70: - | AY70: -
B71: Santa Marta | C71: =SUM(D71:AY71) -> 11157.36 | D71: 226 | E71: 246 | F71: - | G71: 480 | H71: 80 | I71: - | J71: 117 | K71: 429 | L71: 120 | M71: - | N71: - | O71: - | P71: - | Q71: 50 | R71: 135 | S71: 25 | T71: 0 | U71: 30 | V71: 0 | W71: - | X71: - | Y71: - | Z71: 25 | AA71: 45 | AB71: 312.5 | AC71: 18 | AD71: 0 | AE71: 0 | AF71: 195 | AG71: - | AH71: - | AI71: - | AJ71: - | AK71: - | AL71: - | AM71: - | AN71: - | AO71: 1013.7 | AP71: 3122.3 | AQ71: 1063.63 | AR71: 71.15 | AS71: 72.72 | AT71: 421.98 | AU71: 293.38 | AV71: 2565 | AW71: - | AX71: - | AY71: -
B72: Peñaranda | C72: =SUM(D72:AY72) -> 14506.9 | D72: 283 | E72: 0 | F72: - | G72: 400 | H72: 10 | I72: - | J72: 0 | K72: 351 | L72: 80 | M72: - | N72: - | O72: - | P72: - | Q72: 100 | R72: 180 | S72: 35 | T72: 0 | U72: 15 | V72: 5 | W72: - | X72: - | Y72: - | Z72: 10 | AA72: 40 | AB72: 318.5 | AC72: 36 | AD72: 0 | AE72: 14 | AF72: 0 | AG72: - | AH72: - | AI72: - | AJ72: - | AK72: - | AL72: - | AM72: - | AN72: - | AO72: 1831.52 | AP72: 3990 | AQ72: 2657.85 | AR72: 29.15 | AS72: 171.9 | AT72: 344.26 | AU72: 1272.72 | AV72: 2332 | AW72: - | AX72: - | AY72: -
B73: Vitigudino | C73: =SUM(D73:AY73) -> 15918.1 | D73: 400 | E73: 56 | F73: - | G73: 560 | H73: 10 | I73: - | J73: 0 | K73: 78 | L73: 210 | M73: - | N73: - | O73: - | P73: - | Q73: 150 | R73: 225 | S73: 35 | T73: 0 | U73: 0 | V73: 0 | W73: - | X73: - | Y73: - | Z73: 10 | AA73: 55 | AB73: 299.25 | AC73: 26 | AD73: 0 | AE73: 14 | AF73: 0 | AG73: - | AH73: - | AI73: - | AJ73: - | AK73: - | AL73: - | AM73: - | AN73: - | AO73: 2202.3 | AP73: 3697.61 | AQ73: 3198.34 | AR73: 599.15 | AS73: 99.17 | AT73: 382.19 | AU73: 1128.09 | AV73: 2483 | AW73: - | AX73: - | AY73: -
B74: Básico GVT | C74: =SUM(D74:AY74) -> 5749.8 | D74: 20 | E74: 520 | F74: 0 | G74: 70 | H74: - | I74: 40 | J74: - | K74: - | L74: - | M74: 200 | N74: 100 | O74: 100 | P74: 20 | Q74: - | R74: - | S74: - | T74: - | U74: - | V74: - | W74: 0 | X74: 18 | Y74: 0 | Z74: - | AA74: - | AB74: - | AC74: - | AD74: - | AE74: - | AF74: - | AG74: 0 | AH74: - | AI74: - | AJ74: - | AK74: 215 | AL74: 540 | AM74: 340 | AN74: 0 | AO74: 64.76 | AP74: 463.63 | AQ74: - | AR74: - | AS74: 33.05 | AT74: 0 | AU74: - | AV74: - | AW74: 2655.36 | AX74: 350 | AY74: -
B75: Básico XCU | C75: =SUM(D75:AY75) -> 3923.36 | D75: 100 | E75: 160 | F75: 55 | G75: 40 | H75: - | I75: 20 | J75: - | K75: - | L75: - | M75: 100 | N75: 0 | O75: 30 | P75: 20 | Q75: - | R75: - | S75: - | T75: - | U75: - | V75: - | W75: 25 | X75: 18 | Y75: 0 | Z75: - | AA75: - | AB75: - | AC75: - | AD75: - | AE75: - | AF75: - | AG75: 0 | AH75: - | AI75: - | AJ75: - | AK75: 145 | AL75: 180 | AM75: 25 | AN75: 0 | AQ75: - | AR75: - | AU75: - | AV75: - | AW75: 2655.36 | AX75: 350 | AY75: -
B76: Plus NFG | C76: =SUM(D76:AY76) -> 3905 | D76: 0 | E76: 0 | F76: 125 | G76: 60 | H76: - | I76: 0 | J76: - | K76: - | L76: - | M76: 0 | N76: 100 | O76: 100 | P76: 0 | Q76: - | R76: - | S76: - | T76: - | U76: - | V76: - | W76: 150 | X76: 90 | Y76: 0 | Z76: - | AA76: - | AB76: - | AC76: - | AD76: - | AE76: - | AF76: - | AG76: 0 | AH76: - | AI76: - | AJ76: - | AK76: 260 | AL76: 300 | AM76: 0 | AN76: 0 | AQ76: - | AR76: - | AU76: - | AV76: - | AW76: 1320 | AX76: 1400 | AY76: -
B77: Plus N7D | C77: =SUM(D77:AY77) -> 3994 | D77: 0 | E77: 240 | F77: 0 | G77: 40 | H77: - | I77: 0 | J77: - | K77: - | L77: - | M77: 0 | N77: 100 | O77: 60 | P77: 40 | Q77: - | R77: - | S77: - | T77: - | U77: - | V77: - | W77: 200 | X77: 54 | Y77: 0 | Z77: - | AA77: - | AB77: - | AC77: - | AD77: - | AE77: - | AF77: - | AG77: 0 | AH77: - | AI77: - | AJ77: - | AK77: 460 | AL77: 300 | AM77: 0 | AN77: 0 | AQ77: - | AR77: - | AU77: - | AV77: - | AW77: 1100 | AX77: 1400 | AY77: -
B78: Plus K2Z | C78: =SUM(D78:AY78) -> 5200 | D78: 100 | E78: 0 | F78: 0 | G78: 120 | H78: - | I78: 10 | J78: - | K78: - | L78: - | M78: 200 | N78: 100 | O78: 80 | P78: 0 | Q78: - | R78: - | S78: - | T78: - | U78: - | V78: - | W78: 100 | X78: 0 | Y78: 0 | Z78: - | AA78: - | AB78: - | AC78: - | AD78: - | AE78: - | AF78: - | AG78: 0 | AH78: - | AI78: - | AJ78: - | AK78: 660 | AL78: 450 | AM78: 0 | AN78: 0 | AQ78: - | AR78: - | AU78: - | AV78: - | AW78: 1980 | AX78: 1400 | AY78: -
B79: Total | C79: =SUM(C69:C78) -> 116505.33 | D79: =SUM(D69:D78) -> 2175 | E79: =SUM(E69:E78) -> 1524 | F79: =SUM(F69:F78) -> 180 | G79: =SUM(G69:G78) -> 3030 | H79: =SUM(H69:H78) -> 360 | I79: =SUM(I69:I78) -> 70 | J79: =SUM(J69:J78) -> 234 | ... AG79: =SUM(AG69:AG78) -> 0 | AH79: 0 | AI79: 0 | AJ79: 0 | AK79: =SUM(AK69:AK78) -> 1740 | AL79: =SUM(AL69:AL78) -> 1770 | AM79: =SUM(AM69:AM78) -> 365 | AN79: =SUM(AN69:AN78) -> 0 | AO79: =SUM(AO69:AO78) -> 9402.99 | AP79: =SUM(AP69:AP78) -> 24622.41 | AQ79: =SUM(AQ69:AQ78) -> 23854.35 | AR79: =SUM(AR69:AR78) -> 1744.75 | ... AX79: =SUM(AX69:AX78) -> 4900 | AY79: 3200
A80: AGO | B80: Estación | C80: =SUM(D80:AY80) -> 23639.51 | D80: 665 | E80: 690 | F80: - | G80: 450 | H80: 220 | I80: - | J80: 0 | K80: 0 | L80: 637 | M80: - | N80: - | O80: - | P80: - | Q80: 225 | R80: 390 | S80: 15 | T80: 100 | U80: 30 | V80: 0 | W80: - | X80: - | Y80: - | Z80: 35 | AA80: 125 | AB80: 506 | AC80: 35 | AD80: 225 | AE80: 420 | AF80: 375 | AG80: - | AH80: - | AI80: - | AJ80: - | AK80: - | AL80: - | AM80: - | AN80: - | AO80: 2110.75 | AP80: 5033.47 | AQ80: 5562.8 | AR80: 515.18 | AS80: 238.01 | AT80: 932.19 | AU80: 566.11 | AV80: 3538 | AW80: - | AX80: - | AY80: -
B81: Correhuela | C81: =SUM(D81:AY81) -> 15434.71 | D81: 616 | E81: 498 | F81: - | G81: 380 | H81: 180 | I81: - | J81: 0 | K81: 0 | L81: 751 | M81: - | N81: - | O81: - | P81: - | Q81: 125 | R81: 180 | S81: 25 | T81: 0 | U81: 30 | V81: 10 | W81: - | X81: - | Y81: - | Z81: 5 | AA81: 15 | AB81: 515.25 | AC81: 26 | AD81: 210 | AE81: 322 | AF81: 330 | AG81: - | AH81: - | AI81: - | AJ81: - | AK81: - | AL81: - | AM81: - | AN81: - | AO81: 1061.96 | AP81: 4578.5 | AQ81: 637.16 | AR81: 404.18 | AS81: 163.63 | AT81: 921.67 | AU81: 636.36 | AV81: 2813 | AW81: - | AX81: - | AY81: -
B82: Santa Marta | C82: =SUM(D82:AY82) -> 11091.75 | D82: 411 | E82: 208 | F82: - | G82: 290 | H82: 140 | I82: - | J82: 0 | K82: 0 | L82: 421 | M82: - | N82: - | O82: - | P82: - | Q82: 75 | R82: 105 | S82: 10 | T82: 0 | U82: 0 | V82: 0 | W82: - | X82: - | Y82: - | Z82: 20 | AA82: 15 | AB82: 264.5 | AC82: 45 | AD82: 135 | AE82: 266 | AF82: 195 | AG82: - | AH82: - | AI82: - | AJ82: - | AK82: - | AL82: - | AM82: - | AN82: - | AO82: 993.11 | AP82: 3534.7 | AQ82: 321.48 | AR82: 322.68 | AS82: 104.13 | AT82: 385.69 | AU82: 264.46 | AV82: 2565 | AW82: - | AX82: - | AY82: -
B83: Peñaranda | C83: =SUM(D83:AY83) -> 16256.73 | D83: 98 | E83: 282 | F83: - | G83: 330 | H83: 0 | I83: - | J83: 0 | K83: 0 | L83: 250 | M83: - | N83: - | O83: - | P83: - | Q83: 50 | R83: 345 | S83: 20 | T83: 0 | U83: 0 | V83: 0 | W83: - | X83: - | Y83: - | Z83: 25 | AA83: 0 | AB83: 345.75 | AC83: 0 | AD83: 0 | AE83: 0 | AF83: 210 | AG83: - | AH83: - | AI83: - | AJ83: - | AK83: - | AL83: - | AM83: - | AN83: - | AO83: 2330.41 | AP83: 5539.58 | AQ83: 1814.87 | AR83: 21.68 | AS83: 216.52 | AT83: 504.6 | AU83: 1541.32 | AV83: 2332 | AW83: - | AX83: - | AY83: -
B84: Vitigudino | C84: =SUM(D84:AY84) -> 19902.53 | D84: 566 | E84: 476 | F84: - | G84: 340 | H84: 0 | I84: - | J84: 39 | K84: 0 | L84: 178 | M84: - | N84: - | O84: - | P84: - | Q84: 175 | R84: 405 | S84: 20 | T84: 0 | U84: 0 | V84: 0 | W84: - | X84: - | Y84: - | Z84: 35 | AA84: 30 | AB84: 412.75 | AC84: 21 | AD84: 210 | AE84: 14 | AF84: 285 | AG84: - | AH84: - | AI84: - | AJ84: - | AK84: - | AL84: - | AM84: - | AN84: - | AO84: 2226.64 | AP84: 8775.19 | AQ84: 724.79 | AR84: 252.68 | AS84: 84.29 | AT84: 616.14 | AU84: 1533.05 | AV84: 2483 | AW84: - | AX84: - | AY84: -
B85: Básico GVT | C85: =SUM(D85:AY85) -> 6322.12 | D85: 30 | E85: 170 | F85: 235 | G85: 0 | H85: - | I85: 10 | J85: - | K85: - | L85: - | M85: 100 | N85: 400 | O85: 3 | P85: 0 | Q85: - | R85: - | S85: - | T85: - | U85: - | V85: - | W85: 175 | X85: 126 | Y85: 0 | Z85: - | AA85: - | AB85: - | AC85: - | AD85: - | AE85: - | AF85: - | AG85: 720 | AH85: - | AI85: - | AJ85: - | AK85: 484 | AL85: 696 | AM85: 340 | AN85: 0 | AO85: 98.01 | AP85: 226.44 | AQ85: - | AR85: - | AS85: 26.44 | AT85: 32.23 | AU85: - | AV85: - | AW85: 2100 | AX85: 350 | AY85: -
B86: Básico XCU | C86: =SUM(D86:AY86) -> 4740 | D86: 0 | E86: 90 | F86: 320 | G86: 0 | H86: - | I86: 20 | J86: - | K86: - | L86: - | M86: 300 | N86: 0 | O86: 50 | P86: 0 | Q86: - | R86: - | S86: - | T86: - | U86: - | V86: - | W86: 25 | X86: 0 | Y86: 0 | Z86: - | AA86: - | AB86: - | AC86: - | AD86: - | AE86: - | AF86: - | AG86: 580 | AH86: - | AI86: - | AJ86: - | AK86: 400 | AL86: 480 | AM86: 25 | AN86: 0 | AQ86: - | AR86: - | AU86: - | AV86: - | AW86: 2100 | AX86: 350 | AY86: -
B87: Plus NFG | C87: =SUM(D87:AY87) -> 8603 | D87: 0 | E87: 160 | F87: 245 | G87: 40 | H87: - | I87: 10 | J87: - | K87: - | L87: - | M87: 0 | N87: 200 | O87: 40 | P87: 20 | Q87: - | R87: - | S87: - | T87: - | U87: - | V87: - | W87: 50 | X87: 18 | Y87: 0 | Z87: - | AA87: - | AB87: - | AC87: - | AD87: - | AE87: - | AF87: - | AG87: 140 | AH87: - | AI87: - | AJ87: - | AK87: 260 | AL87: 420 | AM87: 0 | AN87: 0 | AQ87: - | AR87: - | AU87: - | AV87: - | AW87: 5600 | AX87: 1400 | AY87: -
B88: Plus N7D | C88: =SUM(D88:AY88) -> 9450 | D88: 0 | E88: 0 | F88: 255 | G88: 0 | H88: - | I88: 10 | J88: - | K88: - | L88: - | M88: 400 | N88: 0 | O88: 40 | P88: 20 | Q88: - | R88: - | S88: - | T88: - | U88: - | V88: - | W88: 125 | X88: 0 | Y88: 0 | Z88: - | AA88: - | AB88: - | AC88: - | AD88: - | AE88: - | AF88: - | AG88: 360 | AH88: - | AI88: - | AJ88: - | AK88: 600 | AL88: 840 | AM88: 0 | AN88: 0 | AQ88: - | AR88: - | AU88: - | AV88: - | AW88: 5400 | AX88: 1400 | AY88: -
B89: Plus K2Z | C89: =SUM(D89:AY89) -> 8226 | D89: 20 | E89: 0 | F89: 90 | G89: 0 | H89: - | I89: 10 | J89: - | K89: - | L89: - | M89: 0 | N89: 200 | O89: 20 | P89: 80 | Q89: - | R89: - | S89: - | T89: - | U89: - | V89: - | W89: 25 | X89: 18 | Y89: 0 | Z89: - | AA89: - | AB89: - | AC89: - | AD89: - | AE89: - | AF89: - | AG89: 90 | AH89: - | AI89: - | AJ89: - | AK89: 330 | AL89: 343 | AM89: 0 | AN89: 0 | AQ89: - | AR89: - | AU89: - | AV89: - | AW89: 5600 | AX89: 1400 | AY89: -
B90: Total | C90: =SUM(C80:C89) -> 123666.35 | D90: =SUM(D80:D89) -> 2406 | E90: =SUM(E80:E89) -> 2574 | F90: =SUM(F80:F89) -> 1145 | G90: =SUM(G80:G89) -> 1830 | H90: =SUM(H80:H89) -> 540 | I90: =SUM(I80:I89) -> 60 | J90: =SUM(J80:J89) -> 39 | ... AG90: =SUM(AG80:AG89) -> 1890 | AH90: 0 | AI90: 0 | AJ90: 0 | AK90: =SUM(AK80:AK89) -> 2074 | AL90: =SUM(AL80:AL89) -> 2779 | AM90: =SUM(AM80:AM89) -> 365 | AN90: =SUM(AN80:AN89) -> 0 | AO90: =SUM(AO80:AO89) -> 8820.88 | AP90: =SUM(AP80:AP89) -> 27687.88 | AQ90: =SUM(AQ80:AQ89) -> 9061.1 | AR90: =SUM(AR80:AR89) -> 1516.4 | ... AX90: =SUM(AX80:AX89) -> 4900 | AY90: 3775.8
A91: SEP | B91: Estación | C91: =SUM(D91:AY91) -> 26485.19 | D91: 1134 | E91: 644 | F91: - | G91: 460 | H91: 240 | I91: - | J91: 150 | K91: 0 | L91: 510 | M91: - | N91: - | O91: - | P91: - | Q91: 425 | R91: 315 | S91: 5 | T91: 0 | U91: 45 | V91: 0 | W91: - | X91: - | Y91: - | Z91: 30 | AA91: 120 | AB91: 508.5 | AC91: 4 | AD91: 390 | AE91: 462 | AF91: 360 | AG91: - | AH91: - | AI91: - | AJ91: - | AK91: - | AL91: - | AM91: - | AN91: - | AO91: 2486.51 | AP91: 6599.17 | AQ91: 6552.06 | AR91: 302 | AS91: 152.06 | AT91: 656.2 | AU91: 396.69 | AV91: 3538 | AW91: - | AX91: - | AY91: -
B92: Correhuela | C92: =SUM(D92:AY92) -> 17735.92 | D92: 1331 | E92: 420 | F92: - | G92: 390 | H92: 140 | I92: - | J92: 0 | K92: 0 | L92: 195 | M92: - | N92: - | O92: - | P92: - | Q92: 225 | R92: 330 | S92: 25 | T92: 0 | U92: 30 | V92: 25 | W92: - | X92: - | Y92: - | Z92: 0 | AA92: 75 | AB92: 709.5 | AC92: 11 | AD92: 435 | AE92: 420 | AF92: 240 | AG92: - | AH92: - | AI92: - | AJ92: - | AK92: - | AL92: - | AM92: - | AN92: - | AO92: 1631.66 | AP92: 3909.91 | AQ92: 3247.93 | AR92: 0 | AS92: 223.14 | AT92: 226.97 | AU92: 681.81 | AV92: 2813 | AW92: - | AX92: - | AY92: -
B93: Santa Marta | C93: =SUM(D93:AY93) -> 16667 | D93: 675 | E93: 408 | F93: - | G93: 210 | H93: 80 | I93: - | J93: 0 | K93: 0 | L93: 130 | M93: - | N93: - | O93: - | P93: - | Q93: 275 | R93: 135 | S93: 0 | T93: 0 | U93: 15 | V93: 0 | W93: - | X93: - | Y93: - | Z93: 10 | AA93: 0 | AB93: 313.25 | AC93: 8 | AD93: 240 | AE93: 210 | AF93: 270 | AG93: - | AH93: - | AI93: - | AJ93: - | AK93: - | AL93: - | AM93: - | AN93: - | AO93: 1405.76 | AP93: 3103.83 | AQ93: 5412.31 | AR93: 417.5 | AS93: 218.18 | AT93: 375.09 | AU93: 190.08 | AV93: 2565 | AW93: - | AX93: - | AY93: -
B94: Peñaranda | C94: =SUM(D94:AY94) -> 12020.31 | D94: 440 | E94: 252 | F94: - | G94: 370 | H94: 0 | I94: - | J94: 0 | K94: 0 | L94: 75 | M94: - | N94: - | O94: - | P94: - | Q94: 75 | R94: 165 | S94: 15 | T94: 0 | U94: 15 | V94: 0 | W94: - | X94: - | Y94: - | Z94: 5 | AA94: 15 | AB94: 266 | AC94: 4 | AD94: 150 | AE94: 0 | AF94: 0 | AG94: - | AH94: - | AI94: - | AJ94: - | AK94: - | AL94: - | AM94: - | AN94: - | AO94: 1292.82 | AP94: 3503.29 | AQ94: 1401.65 | AR94: 0 | AS94: 145.45 | AT94: 262.57 | AU94: 1235.53 | AV94: 2332 | AW94: - | AX94: - | AY94: -
B95: Vitigudino | C95: =SUM(D95:AY95) -> 18072.24 | D95: 625 | E95: 318 | F95: - | G95: 380 | H95: 0 | I95: - | J95: 0 | K95: 0 | L95: 280 | M95: - | N95: - | O95: - | P95: - | Q95: 125 | R95: 345 | S95: 5 | T95: 0 | U95: 0 | V95: 0 | W95: - | X95: - | Y95: - | Z95: 0 | AA95: 65 | AB95: 286 | AC95: 8 | AD95: 225 | AE95: 0 | AF95: 0 | AG95: - | AH95: - | AI95: - | AJ95: - | AK95: - | AL95: - | AM95: - | AN95: - | AO95: 1782.67 | AP95: 5345.44 | AQ95: 4083.47 | AR95: 190.5 | AS95: 72.72 | AT95: 340.87 | AU95: 1111.57 | AV95: 2483 | AW95: - | AX95: - | AY95: -
B96: Básico GVT | C96: =SUM(D96:AY96) -> 6993.22 | D96: 0 | E96: 160 | F96: 220 | G96: 10 | H96: - | I96: 0 | J96: - | K96: - | L96: - | M96: 200 | N96: 200 | O96: 100 | P96: 20 | Q96: - | R96: - | S96: - | T96: - | U96: - | V96: - | W96: 100 | X96: 18 | Y96: 0 | Z96: - | AA96: - | AB96: - | AC96: - | AD96: - | AE96: - | AF96: - | AG96: 350 | AH96: - | AI96: - | AJ96: - | AK96: 500 | AL96: 696 | AM96: 340 | AN96: 300 | AO96: 465.17 | AP96: 531 | AQ96: - | AR96: - | AS96: 33.05 | AT96: 0 | AU96: - | AV96: - | AW96: 2400 | AX96: 350 | AY96: -
B97: Básico XCU | C97: =SUM(D97:AY97) -> 4432 | D97: 50 | E97: 160 | F97: 150 | G97: 40 | H97: - | I97: 0 | J97: - | K97: - | L97: - | M97: 200 | N97: 0 | O97: 70 | P97: 0 | Q97: - | R97: - | S97: - | T97: - | U97: - | V97: - | W97: 25 | X97: 72 | Y97: 0 | Z97: - | AA97: - | AB97: - | AC97: - | AD97: - | AE97: - | AF97: - | AG97: 430 | AH97: - | AI97: - | AJ97: - | AK97: 310 | AL97: 480 | AM97: 25 | AN97: 210 | AQ97: - | AR97: - | AU97: - | AV97: - | AW97: 1860 | AX97: 350 | AY97: -
B98: Plus NFG | C98: =SUM(D98:AY98) -> 5144 | D98: 0 | E98: 10 | F98: 20 | G98: 0 | H98: - | I98: 0 | J98: - | K98: - | L98: - | M98: 0 | N98: 200 | O98: 80 | P98: 0 | Q98: - | R98: - | S98: - | T98: - | U98: - | V98: - | W98: 50 | X98: 54 | Y98: 30 | Z98: - | AA98: - | AB98: - | AC98: - | AD98: - | AE98: - | AF98: - | AG98: 0 | AH98: - | AI98: - | AJ98: - | AK98: 380 | AL98: 420 | AM98: 0 | AN98: 240 | AQ98: - | AR98: - | AU98: - | AV98: - | AW98: 2260 | AX98: 1400 | AY98: -
B99: Plus N7D | C99: =SUM(D99:AY99) -> 6243 | D99: 150 | E99: 0 | F99: 30 | G99: 0 | H99: - | I99: 0 | J99: - | K99: - | L99: - | M99: 200 | N99: 100 | O99: 60 | P99: 100 | Q99: - | R99: - | S99: - | T99: - | U99: - | V99: - | W99: 125 | X99: 108 | Y99: 0 | Z99: - | AA99: - | AB99: - | AC99: - | AD99: - | AE99: - | AF99: - | AG99: 0 | AH99: - | AI99: - | AJ99: - | AK99: 550 | AL99: 840 | AM99: 0 | AN99: 180 | AQ99: - | AR99: - | AU99: - | AV99: - | AW99: 2400 | AX99: 1400 | AY99: -
B100: Plus K2Z | C100: =SUM(D100:AY100) -> 5224 | D100: 20 | E100: 0 | F100: 35 | G100: 0 | H100: - | I100: 0 | J100: - | K100: - | L100: - | M100: 100 | N100: 100 | O100: 70 | P100: 80 | Q100: - | R100: - | S100: - | T100: - | U100: - | V100: - | W100: 0 | X100: 36 | Y100: 0 | Z100: - | AA100: - | AB100: - | AC100: - | AD100: - | AE100: - | AF100: - | AG100: 0 | AH100: - | AI100: - | AJ100: - | AK100: 330 | AL100: 343 | AM100: 0 | AN100: 210 | AQ100: - | AR100: - | AU100: - | AV100: - | AW100: 2500 | AX100: 1400 | AY100: -
...

Sheet Reclamaciones
A1: 2016 RECLAMACIONES PENDIENTES | D1: Contractual | K1: Nacional | AM1: Territorial | AW1: Retribución | BA1: Otros
D2: FFVV | E2: FFVV | F2: FFVV | G2: PDV | H2: PDV | I2: FFVV | J2: PDV | K2: FFVV | L2: FFVV | M2: PDV | N2: FFVV | O2: PDV | P2: PDV | Q2: PDV | R2: PDV | S2: PDV | T2: PDV | U2: PDV | V2: PDV | W2: PDV | X2: PDV | Y2: PDV | Z2: FFVV | AA2: PDV | AB2: PDV | AC2: PDV | AD2: PDV | AE2: FFVV | AF2: FFVV | AG2: FFVV | AH2: FFVV | AI2: FFVV | AJ2: FFVV | AK2: FFVV | AL2: FFVV | AM2: PDV | AN2: PDV | AO2: FFVV | AP2: FFVV | AQ2: FFVV | AR2: FFVV | AS2: FFVV | AT2: PDV | AU2: FFVV | AV2: FFVV | AW2: PDV | AX2: FFVV | AY2: FFVV | AZ2: FFVV | BA2: PDV | BB2: PDV | BC2: Todos
D3: # Alta/Por BV | E3: # Alta/Por MV | F3: # Alta/Por AV | G3: # Alta/Por/Mig BV # Tuenti | H3: # Alta/Por/Mig AV | I3: # Alta ADSL # Alta FTTH | J3: # Alta ADSL # Alta FTTH | K3: # Alta/Por MV | L3: # Alta/Por AV | M3: # Alta/Por/Mig AV | N3: # Repo a AV | O3: # Extra Terminal BV | P3: # Extra Terminal MV | Q3: # Extra Terminal AV | R3: # Terminal Transcanalidad | S3: # Prepago # MultiSIM | T3: # Financia # Siempre N | U3: # Seguro | V3: # Canje BV | W3: # Canje MV | X3: # Canje AV | Y3: # Alta ADSL # Alta FTTH | Z3: # Alta ADSL # Alta FTTH | AA3: # Migra FTTH | AB3: # Alta TV | AC3: # Paquete TV | AD3: # Opción TV | AE3: # Migra MFE ADSL | AF3: # Migra MFE FTTH | AG3: # Alta MFE ADSL | AH3: # Alta MFE FTTH | AI3: # Servicio TI | AJ3: # TMA BV | AK3: # TMA MV | AL3: # TMA AV | AM3: # Alta ADSL # Alta FTTH | AN3: # Alta TV | AO3: # Alta ADSL # Alta FTTH | AP3: # Alta/Mig MFE ADSL/FTTH | AQ3: # Servicio TI | AR3: # TMA | AS3: # Fusión Pro | AT3: # Alta/Por/Mig AV | AU3: # Alta/Por AV / MV / BV | AV3: # Repo a AV | AW3: # Retribución Base | AX3: # Acuerdo PRV | AY3: # Cierre Pre-Liq PRV | AZ3: # Preliq PRV | BA3: # Comisión Terminal | BB3: # Aportación Terminal | BC3: # Otras reclamaciones
A4: ENERO | B4: MicroShop | C4: =SUM(D4:BC4) -> 0
B5: Estación | C5: =SUM(D5:BC5) -> 0
B6: Correhuela | C6: =SUM(D6:BC6) -> 0
B7: Santa Marta | C7: =SUM(D7:BC7) -> 0
B8: Peñaranda | C8: =SUM(D8:BC8) -> 0
B9: Vitigudino | C9: =SUM(D9:BC9) -> 0
B10: MovilFree | C10: =SUM(D10:BC10) -> 0
B11: Básico GVT | C11: =SUM(D11:BC11) -> 0
B12: Básico XCU | C12: =SUM(D12:BC12) -> 0
B13: Plus NFG | C13: =SUM(D13:BC13) -> 0
B14: Plus N7D | C14: =SUM(D14:BC14) -> 0
B15: Plus K2Z | C15: =SUM(D15:BC15) -> 0
B16: Totales | C16: =SUM(C4:C15) -> 0 | D16: =SUM(D4:D15) -> 0 | E16: =SUM(E4:E15) -> 0 | F16: =SUM(F4:F15) -> 0 | G16: =SUM(G4:G15) -> 0 | H16: =SUM(H4:H15) -> 0 | I16: =SUM(I4:I15) -> 0 | J16: =SUM(J4:J15) -> 0 | ... BC16: =SUM(BC4:BC15) -> 0
A17: FEBRERO | B17: MicroShop | C17: =SUM(D17:BC17) -> 0
B18: Estación | C18: =SUM(D18:BC18) -> 0
B19: Correhuela | C19: =SUM(D19:BC19) -> 0
B20: Santa Marta | C20: =SUM(D20:BC20) -> 0
B21: Peñaranda | C21: =SUM(D21:BC21) -> 0
B22: Vitigudino | C22: =SUM(D22:BC22) -> 0
B23: MovilFree | C23: =SUM(D23:BC23) -> 0
B24: Básico GVT | C24: =SUM(D24:BC24) -> 0
B25: Básico XCU | C25: =SUM(D25:BC25) -> 0
B26: Plus NFG | C26: =SUM(D26:BC26) -> 0
B27: Plus N7D | C27: =SUM(D27:BC27) -> 0
B28: Plus K2Z | C28: =SUM(D28:BC28) -> 0
B29: Totales | C29: =SUM(C17:C28) -> 0 | D29: =SUM(D17:D28) -> 0 | E29: =SUM(E17:E28) -> 0 | F29: =SUM(F17:F28) -> 0 | G29: =SUM(G17:G28) -> 0 | H29: =SUM(H17:H28) -> 0 | I29: =SUM(I17:I28) -> 0 | J29: =SUM(J17:J28) -> 0 | ... BC29: =SUM(BC17:BC28) -> 0
A30: MARZO | B30: MicroShop | C30: =SUM(D30:BC30) -> 0
B31: Estación | C31: =SUM(D31:BC31) -> 0
B32: Correhuela | C32: =SUM(D32:BC32) -> 0
B33: Santa Marta | C33: =SUM(D33:BC33) -> 0
B34: Peñaranda | C34: =SUM(D34:BC34) -> 0
B35: Vitigudino | C35: =SUM(D35:BC35) -> 0
B36: MovilFree | C36: =SUM(D36:BC36) -> 0
B37: Básico GVT | C37: =SUM(D37:BC37) -> 0
B38: Básico XCU | C38: =SUM(D38:BC38) -> 0
B39: Plus NFG | C39: =SUM(D39:BC39) -> 0
B40: Plus N7D | C40: =SUM(D40:BC40) -> 0
B41: Plus K2Z | C41: =SUM(D41:BC41) -> 0
B42: Totales | C42: =SUM(C30:C41) -> 0 | D42: =SUM(D30:D41) -> 0 | E42: =SUM(E30:E41) -> 0 | F42: =SUM(F30:F41) -> 0 | G42: =SUM(G30:G41) -> 0 | H42: =SUM(H30:H41) -> 0 | I42: =SUM(I30:I41) -> 0 | J42: =SUM(J30:J41) -> 0 | ... BC42: =SUM(BC30:BC41) -> 0
A43: ABRIL | B43: MicroShop | C43: =SUM(D43:BC43) -> 0
B44: Estación | C44: =SUM(D44:BC44) -> 0
B45: Correhuela | C45: =SUM(D45:BC45) -> 0
B46: Santa Marta | C46: =SUM(D46:BC46) -> 0
B47: Peñaranda | C47: =SUM(D47:BC47) -> 0
B48: Vitigudino | C48: =SUM(D48:BC48) -> 0
B49: MovilFree | C49: =SUM(D49:BC49) -> 0
B50: Básico GVT | C50: =SUM(D50:BC50) -> 0
B51: Básico XCU | C51: =SUM(D51:BC51) -> 0
B52: Plus NFG | C52: =SUM(D52:BC52) -> 0
B53: Plus N7D | C53: =SUM(D53:BC53) -> 0
B54: Plus K2Z | C54: =SUM(D54:BC54) -> 0
B55: Totales | C55: =SUM(C43:C54) -> 0 | D55: =SUM(D43:D54) -> 0 | E55: =SUM(E43:E54) -> 0 | F55: =SUM(F43:F54) -> 0 | G55: =SUM(G43:G54) -> 0 | H55: =SUM(H43:H54) -> 0 | I55: =SUM(I43:I54) -> 0 | J55: =SUM(J43:J54) -> 0 | ... BC55: =SUM(BC43:BC54) -> 0
A56: MAYO | B56: MicroShop | C56: =SUM(D56:BC56) -> 0
B57: Estación | C57: =SUM(D57:BC57) -> 0
B58: Correhuela | C58: =SUM(D58:BC58) -> 0
B59: Santa Marta | C59: =SUM(D59:BC59) -> 0
B60: Peñaranda | C60: =SUM(D60:BC60) -> 0
B61: Vitigudino | C61: =SUM(D61:BC61) -> 0
B62: MovilFree | C62: =SUM(D62:BC62) -> 0
B63: Básico GVT | C63: =SUM(D63:BC63) -> 0
B64: Básico XCU | C64: =SUM(D64:BC64) -> 0
B65: Plus NFG | C65: =SUM(D65:BC65) -> 0
B66: Plus N7D | C66: =SUM(D66:BC66) -> 0
B67: Plus K2Z | C67: =SUM(D67:BC67) -> 0
B68: Totales | C68: =SUM(C56:C67) -> 0 | D68: =SUM(D56:D67) -> 0 | E68: =SUM(E56:E67) -> 0 | F68: =SUM(F56:F67) -> 0 | G68: =SUM(G56:G67) -> 0 | H68: =SUM(H56:H67) -> 0 | I68: =SUM(I56:I67) -> 0 | J68: =SUM(J56:J67) -> 0 | ... BC68: =SUM(BC56:BC67) -> 0
A69: JUNIO | B69: MicroShop | C69: =SUM(D69:BC69) -> 0
B70: Estación | C70: =SUM(D70:BC70) -> 0
B71: Correhuela | C71: =SUM(D71:BC71) -> 0
B72: Santa Marta | C72: =SUM(D72:BC72) -> 0
B73: Peñaranda | C73: =SUM(D73:BC73) -> 0
B74: Vitigudino | C74: =SUM(D74:BC74) -> 0
B75: MovilFree | C75: =SUM(D75:BC75) -> 0
B76: Básico GVT | C76: =SUM(D76:BC76) -> 0
B77: Básico XCU | C77: =SUM(D77:BC77) -> 0
B78: Plus NFG | C78: =SUM(D78:BC78) -> 0
B79: Plus N7D | C79: =SUM(D79:BC79) -> 0
B80: Plus K2Z | C80: =SUM(D80:BC80) -> 0
B81: Totales | C81: =SUM(C69:C80) -> 0 | D81: =SUM(D69:D80) -> 0 | E81: =SUM(E69:E80) -> 0 | F81: =SUM(F69:F80) -> 0 | G81: =SUM(G69:G80) -> 0 | H81: =SUM(H69:H80) -> 0 | I81: =SUM(I69:I80) -> 0 | J81: =SUM(J69:J80) -> 0 | ... BC81: =SUM(BC69:BC80) -> 0
A82: JULIO | B82: MicroShop | C82: =SUM(D82:BC82) -> 0
B83: Estación | C83: =SUM(D83:BC83) -> 0
B84: Correhuela | C84: =SUM(D84:BC84) -> 0
B85: Santa Marta | C85: =SUM(D85:BC85) -> 0
B86: Peñaranda | C86: =SUM(D86:BC86) -> 0
B87: Vitigudino | C87: =SUM(D87:BC87) -> 0
B88: MovilFree | C88: =SUM(D88:BC88) -> 0
B89: Básico GVT | C89: =SUM(D89:BC89) -> 0
B90: Básico XCU | C90: =SUM(D90:BC90) -> 0
B91: Plus NFG | C91: =SUM(D91:BC91) -> 0
B92: Plus N7D | C92: =SUM(D92:BC92) -> 0
B93: Plus K2Z | C93: =SUM(D93:BC93) -> 0
B94: Totales | C94: =SUM(C82:C93) -> 0 | D94: =SUM(D82:D93) -> 0 | E94: =SUM(E82:E93) -> 0 | F94: =SUM(F82:F93) -> 0 | G94: =SUM(G82:G93) -> 0 | H94: =SUM(H82:H93) -> 0 | I94: =SUM(I82:I93) -> 0 | J94: =SUM(J82:J93) -> 0 | ... BC94: =SUM(BC82:BC93) -> 0
A95: AGOSTO | B95: MicroShop | C95: =SUM(D95:BC95) -> 0
B96: Estación | C96: =SUM(D96:BC96) -> 0
B97: Correhuela | C97: =SUM(D97:BC97) -> 0
B98: Santa Marta | C98: =SUM(D98:BC98) -> 0
B99: Peñaranda | C99: =SUM(D99:BC99) -> 0
B100: Vitigudino | C100: =SUM(D100:BC100) -> 0
...

Sheet Penalizaciones
A1: 2016 PENALIZAC. | C1: Totales | D1: PRV FFVV (No poner nada, son deducciones) | E1: Calidad de la Venta | F1: Calidad de la Venta Calcing (cliente no ha pedido nada) | G1: PRV PDV | H1: Exceso de Bajas (ver detalle para fecha) | I1: 900 100 104 | J1: Documentac | K1: Fraude | L1: Exceso de Bajas FIja | M1: Botes Fusión
A2: ENERO | B2: Estación | C2: =SUM(E2:M2) -> 0
B3: Correhuela | C3: =SUM(E3:M3) -> 50 | J3: 50
B4: Santa Marta | C4: =SUM(E4:M4) -> 1556.5 | E4: 150 | G4: 256.5 | H4: 750 | K4: 300 | L4: 100
B5: Peñaranda | C5: =SUM(E5:M5) -> 200 | H5: 50 | J5: 100 | L5: 50
B6: Vitigudino | C6: =SUM(E6:M6) -> 250 | H6: 150 | L6: 100
B7: Básico GVT | C7: =SUM(E7:M7) -> 0
B8: Básico XCU | C8: =SUM(E8:M8) -> 0
B9: Plus NFG | C9: =SUM(E9:M9) -> 50 | E9: 50
B10: Plus N7D | C10: =SUM(E10:M10) -> 0
B11: Plus K2Z | C11: =SUM(E11:M11) -> 0
B12: Total | C12: =SUM(C2:C11) -> 2106.5 | D12: =SUM(D2:D11) -> 0 | E12: =SUM(E2:E11) -> 200 | F12: =SUM(F2:F11) -> 0 | G12: =SUM(G2:G11) -> 256.5 | H12: =SUM(H2:H11) -> 950 | I12: =SUM(I2:I11) -> 0 | J12: =SUM(J2:J11) -> 150 | ... M12: =SUM(M2:M11) -> 0
A13: FEBRERO | B13: Estación | C13: =SUM(E13:M13) -> 60 | E13: 60
B14: Correhuela | C14: =SUM(E14:M14) -> 100 | E14: 50 | H14: 50
B15: Santa Marta | C15: =SUM(E15:M15) -> 450 | H15: 400 | J15: 50
B16: Peñaranda | C16: =SUM(E16:M16) -> 600 | E16: 50 | F16: 200 | H16: 250 | L16: 100
B17: Vitigudino | C17: =SUM(E17:M17) -> 50 | J17: 50
B18: Básico GVT | C18: =SUM(E18:M18) -> 50 | E18: 50
B19: Básico XCU | C19: =SUM(E19:M19) -> 0
B20: Plus NFG | C20: =SUM(E20:M20) -> 50 | E20: 50
B21: Plus N7D | C21: =SUM(E21:M21) -> 0
B22: Plus K2Z | C22: =SUM(E22:M22) -> 0
B23: Total | C23: =SUM(C13:C22) -> 1360 | D23: =SUM(D13:D22) -> 0 | E23: =SUM(E13:E22) -> 260 | F23: =SUM(F13:F22) -> 200 | G23: =SUM(G13:G22) -> 0 | H23: =SUM(H13:H22) -> 700 | I23: =SUM(I13:I22) -> 0 | J23: =SUM(J13:J22) -> 100 | ... M23: =SUM(M13:M22) -> 0
A24: MARZO | B24: Estación | C24: =SUM(E24:M24) -> 100 | H24: 50 | L24: 50
B25: Correhuela | C25: =SUM(E25:M25) -> 100 | E25: 50 | H25: 50
B26: Santa Marta | C26: =SUM(E26:M26) -> 230 | E26: 180 | J26: 50
B27: Peñaranda | C27: =SUM(E27:M27) -> 180 | E27: 30 | H27: 100 | J27: 50
B28: Vitigudino | C28: =SUM(E28:M28) -> 0
B29: Básico GVT | C29: =SUM(E29:M29) -> 0
B30: Básico XCU | C30: =SUM(E30:M30) -> 0
B31: Plus NFG | C31: =SUM(E31:M31) -> 0
B32: Plus N7D | C32: =SUM(E32:M32) -> 50 | E32: 50
B33: Plus K2Z | C33: =SUM(E33:M33) -> 0
B34: Total | C34: =SUM(C24:C33) -> 660 | D34: =SUM(D24:D33) -> 0 | E34: =SUM(E24:E33) -> 310 | F34: =SUM(F24:F33) -> 0 | G34: =SUM(G24:G33) -> 0 | H34: =SUM(H24:H33) -> 200 | I34: =SUM(I24:I33) -> 0 | J34: =SUM(J24:J33) -> 100 | ... M34: =SUM(M24:M33) -> 0
A35: ABRIL | B35: Estación | C35: =SUM(E35:M35) -> 150 | H35: 150
B36: Correhuela | C36: =SUM(E36:M36) -> 30 | J36: 30
B37: Santa Marta | C37: =SUM(E37:M37) -> 50 | J37: 50
B38: Peñaranda | C38: =SUM(E38:M38) -> 0
B39: Vitigudino | C39: =SUM(E39:M39) -> 0
B40: Básico GVT | C40: =SUM(E40:M40) -> 0
B41: Básico XCU | C41: =SUM(E41:M41) -> 100 | E41: 100
B42: Plus NFG | C42: =SUM(E42:M42) -> 0
B43: Plus N7D | C43: =SUM(E43:M43) -> 100 | E43: 100
B44: Plus K2Z | C44: =SUM(E44:M44) -> 0
B45: Total | C45: =SUM(C35:C44) -> 430 | D45: =SUM(D35:D44) -> 0 | E45: =SUM(E35:E44) -> 200 | F45: =SUM(F35:F44) -> 0 | G45: =SUM(G35:G44) -> 0 | H45: =SUM(H35:H44) -> 150 | I45: =SUM(I35:I44) -> 0 | J45: =SUM(J35:J44) -> 80 | ... M45: =SUM(M35:M44) -> 0
A46: MAYO | B46: Estación | C46: =SUM(E46:M46) -> 236.65 | E46: 100 | I46: 106.65 | J46: 30
B47: Correhuela | C47: =SUM(E47:M47) -> 0
B48: Santa Marta | C48: =SUM(E48:M48) -> 402.7 | E48: 50 | H48: 350 | I48: 2.7
B49: Peñaranda | C49: =SUM(E49:M49) -> 350 | E49: 50 | H49: 250 | J49: 50
B50: Vitigudino | C50: =SUM(E50:M50) -> 2.7 | I50: 2.7
B51: Básico GVT | C51: =SUM(E51:M51) -> 0
B52: Básico XCU | C52: =SUM(E52:M52) -> 0
B53: Plus NFG | C53: =SUM(E53:M53) -> 0
B54: Plus N7D | C54: =SUM(E54:M54) -> 0
B55: Plus K2Z | C55: =SUM(E55:M55) -> 0
B56: Total | C56: =SUM(C46:C55) -> 992.05 | D56: =SUM(D46:D55) -> 0 | E56: =SUM(E46:E55) -> 200 | F56: =SUM(F46:F55) -> 0 | G56: =SUM(G46:G55) -> 0 | H56: =SUM(H46:H55) -> 600 | I56: =SUM(I46:I55) -> 112.05 | J56: =SUM(J46:J55) -> 80 | ... M56: =SUM(M46:M55) -> 0
A57: JUNIO | B57: Estación | C57: =SUM(E57:M57) -> 2.7 | I57: 2.7
B58: Correhuela | C58: =SUM(E58:M58) -> 362.7 | E58: 310 | H58: 50 | I58: 2.7
B59: Santa Marta | C59: =SUM(E59:M59) -> 700 | H59: 550 | J59: 150
B60: Peñaranda | C60: =SUM(E60:M60) -> 250 | E60: 250
B61: Vitigudino | C61: =SUM(E61:M61) -> 0
B62: Básico GVT | C62: =SUM(E62:M62) -> 200 | E62: 200
B63: Básico XCU | C63: =SUM(E63:M63) -> 0
B64: Plus NFG | C64: =SUM(E64:M64) -> 0
B65: Plus N7D | C65: =SUM(E65:M65) -> 0
B66: Plus K2Z | C66: =SUM(E66:M66) -> 0
B67: Total | C67: =SUM(C57:C66) -> 1515.4 | D67: =SUM(D57:D66) -> 0 | E67: =SUM(E57:E66) -> 760 | F67: =SUM(F57:F66) -> 0 | G67: =SUM(G57:G66) -> 0 | H67: =SUM(H57:H66) -> 600 | I67: =SUM(I57:I66) -> 5.4 | J67: =SUM(J57:J66) -> 150 | ... M67: =SUM(M57:M66) -> 0
A68: JULIO | B68: Estación | C68: =SUM(E68:M68) -> 150 | H68: 150
B69: Correhuela | C69: =SUM(E69:M69) -> 250 | E69: 150 | J69: 100
B70: Santa Marta | C70: =SUM(E70:M70) -> 550 | E70: 400 | J70: 50 | K70: 100
B71: Peñaranda | C71: =SUM(E71:M71) -> 0
B72: Vitigudino | C72: =SUM(E72:M72) -> 0
B73: Básico GVT | C73: =SUM(E73:M73) -> 0
B74: Básico XCU | C74: =SUM(E74:M74) -> 100 | E74: 100
B75: Plus NFG | C75: =SUM(E75:M75) -> 0
B76: Plus N7D | C76: =SUM(E76:M76) -> 100 | E76: 100
B77: Plus K2Z | C77: =SUM(E77:M77) -> 0
B78: Total | C78: =SUM(C68:C77) -> 1150 | D78: =SUM(D68:D77) -> 0 | E78: =SUM(E68:E77) -> 750 | F78: =SUM(F68:F77) -> 0 | G78: =SUM(G68:G77) -> 0 | H78: =SUM(H68:H77) -> 150 | I78: =SUM(I68:I77) -> 0 | J78: =SUM(J68:J77) -> 150 | ... M78: =SUM(M68:M77) -> 0
A79: AGOSTO | B79: Estación | C79: =SUM(E79:M79) -> 50 | H79: 50
B80: Correhuela | C80: =SUM(E80:M80) -> 0
B81: Santa Marta | C81: =SUM(E81:M81) -> 50 | H81: 50
B82: Peñaranda | C82: =SUM(E82:M82) -> 0
B83: Vitigudino | C83: =SUM(E83:M83) -> 0
B84: Básico GVT | C84: =SUM(E84:M84) -> 200 | E84: 200
B85: Básico XCU | C85: =SUM(E85:M85) -> 0
B86: Plus NFG | C86: =SUM(E86:M86) -> 0
B87: Plus N7D | C87: =SUM(E87:M87) -> 0
B88: Plus K2Z | C88: =SUM(E88:M88) -> 0
B89: Total | C89: =SUM(C79:C88) -> 300 | D89: =SUM(D79:D88) -> 0 | E89: =SUM(E79:E88) -> 200 | F89: =SUM(F79:F88) -> 0 | G89: =SUM(G79:G88) -> 0 | H89: =SUM(H79:H88) -> 100 | I89: =SUM(I79:I88) -> 0 | J89: =SUM(J79:J88) -> 0 | ... M89: =SUM(M79:M88) -> 0
A90: SEPTIEMB | B90: Estación | C90: =SUM(E90:M90) -> 100 | E90: 100
B91: Correhuela | C91: =SUM(E91:M91) -> 50 | E91: 50
B92: Santa Marta | C92: =SUM(E92:M92) -> 0
B93: Peñaranda | C93: =SUM(E93:M93) -> 0
B94: Vitigudino | C94: =SUM(E94:M94) -> 0
B95: Básico GVT | C95: =SUM(E95:M95) -> 0
B96: Básico XCU | C96: =SUM(E96:M96) -> 0
B97: Plus NFG | C97: =SUM(E97:M97) -> 100 | E97: 100
B98: Plus N7D | C98: =SUM(E98:M98) -> 50 | E98: 50
B99: Plus K2Z | C99: =SUM(E99:M99) -> 0
B100: Total | C100: =SUM(C90:C99) -> 300 | D100: =SUM(D90:D99) -> 0 | E100: =SUM(E90:E99) -> 300 | F100: =SUM(F90:F99) -> 0 | G100: =SUM(G90:G99) -> 0 | H100: =SUM(H90:H99) -> 0 | I100: =SUM(I90:I99) -> 0 | J100: =SUM(J90:J99) -> 0 | ... M100: =SUM(M90:M99) -> 0
...

Sheet FFVV 2016
B2: PRV FFVV 2016 | C2: Totales | D2: Enero | E2: Febrero | F2: Marzo | G2: Abril | H2: Mayo | I2: Junio | J2: Julio | K2: Agosto | L2: Septiembre | M2: Octubre | N2: Noviembre | O2: Diciembre
B3: Acuerdo Plan Retribución Variable | C3: =SUM(D3:O3) -> 152365.32 | D3: =Ingresos!AW13 -> 12294.6 | E3: =Ingresos!AW24 -> 10950 | F3: =Ingresos!AW35 -> 8400 | G3: =Ingresos!AW46 -> 17400 | H3: =Ingresos!$AW57 -> 13000 | I3: =Ingresos!$AW68 -> 10400 | J3: =Ingresos!$AW79 -> 9710.72 | K3: =Ingresos!$AW90 -> 20800 | L3: =Ingresos!$AW101 -> 11420 | M3: =Ingresos!$AW112 -> 12460 | N3: =Ingresos!$AW123 -> 12330 | O3: =Ingresos!$AW134 -> 13200
B4: Acuerdo Trimestral (Pre-Liquidación) | C4: =SUM(D4:O4) -> 57750 | D4: =Ingresos!AX13 -> 4550 | E4: =Ingresos!AX24 -> 4550 | F4: =Ingresos!AX35 -> 4550 | G4: =Ingresos!AX46 -> 4900 | H4: =Ingresos!$AX57 -> 4900 | I4: =Ingresos!$AX68 -> 4900 | J4: =Ingresos!$AX79 -> 4900 | K4: =Ingresos!$AX90 -> 4900 | L4: =Ingresos!$AX101 -> 4900 | M4: =Ingresos!$AX112 -> 4900 | N4: =Ingresos!$AX123 -> 4900 | O4: =Ingresos!$AX134 -> 4900
B5: Total cobrado | C5: =SUM(D5:O5) -> 210115.32 | D5: =D3+D4 -> 16844.6 | E5: =E3+E4 -> 15500 | F5: =F3+F4 -> 12950 | G5: =G3+G4 -> 22300 | H5: =H3+H4 -> 17900 | I5: =I3+I4 -> 15300 | J5: =J3+J4 -> 14610.72 | K5: =K3+K4 -> 25700 | ... O5: =O3+O4 -> 18100
B7: Territorial FFVV Plus 2016 | C7: Totales | D7: Enero | E7: Febrero | F7: Marzo | G7: Abril | H7: Mayo | I7: Junio | J7: Julio | K7: Agosto | L7: Septiembre | M7: Octubre | N7: Noviembre | O7: Diciembre
B8: Altas y Portas | C8: =SUM(D8:O8) -> 9752.5 | D8: =SUM(Ingresos!AG$10:AG$12) -> 939 | E8: =SUM(Ingresos!AG$21:AG$23) -> 1396 | F8: =SUM(Ingresos!AG$32:AG$34) -> 1570 | G8: =SUM(Ingresos!AG$43:AG$45) -> 1735 | H8: =SUM(Ingresos!$AG$54:$AG$56) -> 1745 | I8: =SUM(Ingresos!$AG$65:$AG$67) -> 1777.5 | J8: =SUM(Ingresos!$AG$76:$AG$78) -> 0 | K8: =SUM(Ingresos!$AG$87:$AG$89) -> 590 | L8: =SUM(Ingresos!$AG$98:$AG$100) -> 0 | M8: =SUM(Ingresos!$AG$109:$AG$111) -> 0 | N8: =SUM(Ingresos!$AG$120:$AG$122) -> 0 | O8: =SUM(Ingresos!$AG$131:$AG$133) -> 0
B9: Reposicionamientos AV | C9: =SUM(D9:O9) -> 1120 | D9: =SUM(Ingresos!AH$10:AH$12) -> 200 | E9: =SUM(Ingresos!AH$21:AH$23) -> 220 | F9: =SUM(Ingresos!AH$32:AH$34) -> 220 | G9: =SUM(Ingresos!AH$43:AH$45) -> 240 | H9: =SUM(Ingresos!$AH$54:$AH$56) -> 240
B10: Alta BAF, BAF Fibra y MFE Todos | C10: =SUM(D10:O10) -> 234 | D10: =SUM(Ingresos!AI$10:AI$12) -> 234
B11: Migraciones FTTH y MFE Todos | C11: =SUM(D11:O11) -> 160 | D11: =SUM(Ingresos!AJ$10:AJ$12) -> 160
B12: Alta ADSL, FTTH, MFE Todos, Migra FTTH, MFE Todos | C12: =SUM(D12:O12) -> 12382 | E12: =SUM(Ingresos!AK$21:AK$23) -> 1800 | F12: =SUM(Ingresos!AK$32:AK$34) -> 1302 | G12: =SUM(Ingresos!AK$43:AK$45) -> 0 | H12: =SUM(Ingresos!$AK$54:$AK$56) -> 2400 | I12: =SUM(Ingresos!$AK$65:$AK$67) -> 2400 | J12: =SUM(Ingresos!$AK$76:$AK$78) -> 1380 | K12: =SUM(Ingresos!$AK$87:$AK$89) -> 1190 | L12: =SUM(Ingresos!$AK$98:$AK$100) -> 1260 | M12: =SUM(Ingresos!$AK$109:$AK$111) -> 650 | N12: =SUM(Ingresos!$AK$120:$AK$122) -> 0 | O12: =SUM(Ingresos!$AK$131:$AK$133) -> 0
B13: Altas y Migras MFE Cloud Todos | C13: =SUM(D13:O13) -> 12231 | D13: =SUM(Ingresos!AL$10:AL$12) -> 200 | E13: =SUM(Ingresos!AL$21:AL$23) -> 660 | F13: =SUM(Ingresos!AL$32:AL$34) -> 1200 | G13: =SUM(Ingresos!AL$43:AL$45) -> 0 | H13: =SUM(Ingresos!$AL$54:$AL$56) -> 2205 | I13: =SUM(Ingresos!$AL$65:$AL$67) -> 0 | J13: =SUM(Ingresos!$AL$76:$AL$78) -> 1050 | K13: =SUM(Ingresos!$AL$87:$AL$89) -> 1603 | L13: =SUM(Ingresos!$AL$98:$AL$100) -> 1603 | M13: =SUM(Ingresos!$AL$109:$AL$111) -> 1645 | N13: =SUM(Ingresos!$AL$120:$AL$122) -> 0 | O13: =SUM(Ingresos!$AL$131:$AL$133) -> 2065
B14: TMA | C14: =SUM(D14:O14) -> 2260 | G14: =SUM(Ingresos!AM$43:AM$45) -> 324 | H14: =SUM(Ingresos!$AM$54:$AM$56) -> 484 | I14: =SUM(Ingresos!$AM$65:$AM$67) -> 684 | J14: =SUM(Ingresos!$AM$76:$AM$78) -> 0 | K14: =SUM(Ingresos!$AM$87:$AM$89) -> 0 | L14: =SUM(Ingresos!$AM$98:$AM$100) -> 0 | M14: =SUM(Ingresos!$AM$109:$AM$111) -> 768 | N14: =SUM(Ingresos!$AM$120:$AM$122) -> 0 | O14: =SUM(Ingresos!$AM$131:$AM$133) -> 0
B15: Servicios TI | C15: =SUM(D15:O15) -> 5779 | D15: =SUM(Ingresos!AN$10:AN$12) -> 549 | E15: =SUM(Ingresos!AN$21:AN$23) -> 780 | F15: =SUM(Ingresos!AN$32:AN$34) -> 660 | G15: =SUM(Ingresos!AN$43:AN$45) -> 480 | H15: =SUM(Ingresos!$AN$54:$AN$56) -> 540 | I15: =SUM(Ingresos!$AN$65:$AN$67) -> 630 | J15: =SUM(Ingresos!$AN$76:$AN$78) -> 0 | K15: =SUM(Ingresos!$AN$87:$AN$89) -> 0 | L15: =SUM(Ingresos!$AN$98:$AN$100) -> 630 | M15: =SUM(Ingresos!$AN$109:$AN$111) -> 780 | N15: =SUM(Ingresos!$AN$120:$AN$122) -> 560 | O15: =SUM(Ingresos!$AN$131:$AN$133) -> 170
B16: Total cobrado | C16: =SUM(D16:O16) -> 43918.5 | D16: =SUM(D8:D15) -> 2282 | E16: =SUM(E8:E15) -> 4856 | F16: =SUM(F8:F15) -> 4952 | G16: =SUM(G8:G15) -> 2779 | H16: =SUM(H8:H15) -> 7614 | I16: =SUM(I8:I15) -> 5491.5 | J16: =SUM(J8:J15) -> 2430 | K16: =SUM(K8:K15) -> 3383 | ... O16: =SUM(O8:O15) -> 2235
B17: Previsión Según Nuestro Cuadro | C17: =SUM(D17:O17) -> 39878 | D17: 2064 | E17: 4937 | F17: 4139 | G17: 2723 | H17: 7318 | I17: 3051 | J17: 3556 | K17: 2718 | L17: 2319 | M17: 3540 | N17: 1526 | O17: 1987
B19: Territorial FFVV Básico 2016 | C19: Totales | D19: Enero | E19: Febrero | F19: Marzo | G19: Abril | H19: Mayo | I19: Junio | J19: Julio | K19: Agosto | L19: Septiembre | M19: Octubre | N19: Noviembre | O19: Diciembre
B20: Altas y Portas | C20: =SUM(D20:O20) -> 13550 | D20: =SUM(Ingresos!AG$8:AG$9) -> 1136 | E20: =SUM(Ingresos!AG$19:AG$20) -> 1467 | F20: =SUM(Ingresos!AG$30:AG$31) -> 1309.5 | G20: =SUM(Ingresos!AG$41:AG$42) -> 1645 | H20: =SUM(Ingresos!$AG$52:$AG$53) -> 0 | I20: =SUM(Ingresos!$AG$63:$AG$64) -> 1312.5 | J20: =SUM(Ingresos!$AG$74:$AG$75) -> 0 | K20: =SUM(Ingresos!$AG$85:$AG$86) -> 1300 | L20: =SUM(Ingresos!$AG$96:$AG$97) -> 780 | M20: =SUM(Ingresos!$AG$107:$AG$108) -> 850 | N20: =SUM(Ingresos!$AG$118:$AG$119) -> 850 | O20: =SUM(Ingresos!$AG$129:$AG$130) -> 2900
B21: Reposicionamientos AV | C21: =SUM(D21:O21) -> 340 | D21: =SUM(Ingresos!AH$8:AH$9) -> 20 | E21: =SUM(Ingresos!AH$19:AH$20) -> 40 | F21: =SUM(Ingresos!AH$30:AH$31) -> 40 | G21: =SUM(Ingresos!AH$41:AH$42) -> 120 | H21: =SUM(Ingresos!$AH$52:$AH$53) -> 120
B22: Alta BAF, BAF Fibra y MFE Todos | C22: =SUM(D22:O22) -> 262.5 | D22: =SUM(Ingresos!AI$8:AI$9) -> 262.5
B23: Migraciones FTTH y MFE Todos | C23: =SUM(D23:O23) -> 60 | D23: =SUM(Ingresos!AJ$8:AJ$9) -> 60
B24: Altas y Migras MFE Todos | C24: =SUM(D24:O24) -> 10116 | D24: =SUM(Ingresos!AL$8:AL$9) -> 100 | E24: =SUM(Ingresos!AL$19:AL$20) -> 330 | F24: =SUM(Ingresos!AL$30:AL$31) -> 800 | G24: =SUM(Ingresos!AL$41:AL$42) -> 0 | H24: =SUM(Ingresos!$AL$52:$AL$53) -> 903 | I24: =SUM(Ingresos!$AL$63:$AL$64) -> 840 | J24: =SUM(Ingresos!$AL$74:$AL$75) -> 720 | K24: =SUM(Ingresos!$AL$85:$AL$86) -> 1176 | L24: =SUM(Ingresos!$AL$96:$AL$97) -> 1176 | M24: =SUM(Ingresos!$AL$107:$AL$108) -> 1376 | N24: =SUM(Ingresos!$AL$118:$AL$119) -> 1470 | O24: =SUM(Ingresos!$AL$129:$AL$130) -> 1225
B25: Alta ADSL, FTTH, MFE Todos, Migra FTTH, MFE Todos | C25: =SUM(D25:O25) -> 7768 | E25: =SUM(Ingresos!AK$19:AK$20) -> 765 | F25: =SUM(Ingresos!AK$30:AK$31) -> 849 | G25: =SUM(Ingresos!AK$41:AK$42) -> 0 | H25: =SUM(Ingresos!$AK$52:$AK$53) -> 1065 | I25: =SUM(Ingresos!$AK$63:$AK$64) -> 1065 | J25: =SUM(Ingresos!$AK$74:$AK$75) -> 360 | K25: =SUM(Ingresos!$AK$85:$AK$86) -> 884 | L25: =SUM(Ingresos!$AK$96:$AK$97) -> 810 | M25: =SUM(Ingresos!$AK$107:$AK$108) -> 1050 | N25: =SUM(Ingresos!$AK$118:$AK$119) -> 460 | O25: =SUM(Ingresos!$AK$129:$AK$130) -> 460
B26: TMA | C26: =SUM(D26:O26) -> 2276 | G26: =SUM(Ingresos!AM$41:AM$42) -> 0 | H26: =SUM(Ingresos!$AM$52:$AM$53) -> 320 | I26: =SUM(Ingresos!$AM$63:$AM$64) -> 0 | J26: =SUM(Ingresos!$AM$74:$AM$75) -> 365 | K26: =SUM(Ingresos!$AM$85:$AM$86) -> 365 | L26: =SUM(Ingresos!$AM$96:$AM$97) -> 365 | M26: =SUM(Ingresos!$AM$107:$AM$108) -> 385 | N26: =SUM(Ingresos!$AM$118:$AM$119) -> 476 | O26: =SUM(Ingresos!$AM$129:$AM$130) -> 0
B27: Servicios TI | C27: =SUM(D27:O27) -> 2736 | D27: =SUM(Ingresos!AN$8:AN$9) -> 159 | E27: =SUM(Ingresos!AN$19:AN$20) -> 243 | F27: =SUM(Ingresos!AN$30:AN$31) -> 228 | G27: =SUM(Ingresos!AN$41:AN$42) -> 390 | H27: =SUM(Ingresos!$AN$52:$AN$53) -> 200 | I27: =SUM(Ingresos!$AN$63:$AN$64) -> 0 | J27: =SUM(Ingresos!$AN$74:$AN$75) -> 0 | K27: =SUM(Ingresos!$AN$85:$AN$86) -> 0 | L27: =SUM(Ingresos!$AN$96:$AN$97) -> 510 | M27: =SUM(Ingresos!$AN$107:$AN$108) -> 660 | N27: =SUM(Ingresos!$AN$118:$AN$119) -> 346 | O27: =SUM(Ingresos!$AN$129:$AN$130) -> 0
B28: Total cobrado | C28: =SUM(D28:O28) -> 37108.5 | D28: =SUM(D20:D27) -> 1737.5 | E28: =SUM(E20:E27) -> 2845 | F28: =SUM(F20:F27) -> 3226.5 | G28: =SUM(G20:G27) -> 2155 | H28: =SUM(H20:H27) -> 2608 | I28: =SUM(I20:I27) -> 3217.5 | J28: =SUM(J20:J27) -> 1445 | K28: =SUM(K20:K27) -> 3725 | ... O28: =SUM(O20:O27) -> 4585
B29: Previsión Según Nuestro Cuadro | C29: =SUM(D29:O29) -> 33641 | D29: 1724 | E29: 3118 | F29: 3782 | G29: 2951 | H29: 2208 | I29: 4160 | J29: 390 | K29: 3010 | L29: 2374 | M29: 4000 | N29: 3229 | O29: 2695
B31: TOTAL TERRITORIAL PLUS + BÁSICO | C31: =C16+C28 -> 81027 | D31: =D16+D28 -> 4019.5 | E31: =E16+E28 -> 7701 | F31: =F16+F28 -> 8178.5 | G31: =G16+G28 -> 4934 | H31: =H16+H28 -> 10222 | I31: =I16+I28 -> 8709 | J31: =J16+J28 -> 3875 | ... O31: =O16+O28 -> 6820

Sheet PDV 2016
B2: Territorial Tiendas 2016 | C2: Totales | D2: Enero | E2: Febrero | F2: Marzo | G2: Abril | H2: Mayo | I2: Junio | J2: Julio | K2: Agosto | L2: Septiembre | M2: Octubre | N2: Noviembre | O2: Diciembre
B3: Alta BAF y BAF 300 | C3: =SUM(D3:O3) -> 10230 | D3: =SUM(Ingresos!AD$3:AD$7) -> 1230 | E3: =SUM(Ingresos!AD$14:AD$18) -> 1185 | F3: =SUM(Ingresos!AD$25:AD$29) -> 660 | G3: =SUM(Ingresos!AD$36:AD$40) -> 855 | H3: =SUM(Ingresos!$AD$47:$AD$51) -> 975 | I3: =SUM(Ingresos!$AD$58:$AD$62) -> 540 | J3: =SUM(Ingresos!$AD$69:$AD$73) -> 360 | K3: =SUM(Ingresos!$AD$80:$AD$84) -> 780 | L3: =SUM(Ingresos!$AD$91:$AD$95) -> 1440 | M3: =SUM(Ingresos!$AD$102:$AD$106) -> 525 | N3: =SUM(Ingresos!$AD$113:$AD$117) -> 360 | O3: =SUM(Ingresos!$AD$124:$AD$128) -> 1320
B4: Alta y Migra BAF 300 | C4: =SUM(D4:O4) -> 7224 | D4: =SUM(Ingresos!AE$3:AE$7) -> 630 | E4: =SUM(Ingresos!AE$14:AE$18) -> 504 | F4: =SUM(Ingresos!AE$25:AE$29) -> 644 | G4: =SUM(Ingresos!AE$36:AE$40) -> 602 | H4: =SUM(Ingresos!$AE$47:$AE$51) -> 812 | I4: =SUM(Ingresos!$AE$58:$AE$62) -> 168 | J4: =SUM(Ingresos!$AE$69:$AE$73) -> 28 | K4: =SUM(Ingresos!$AE$80:$AE$84) -> 1022 | L4: =SUM(Ingresos!$AE$91:$AE$95) -> 1092 | M4: =SUM(Ingresos!$AE$102:$AE$106) -> 938 | N4: =SUM(Ingresos!$AE$113:$AE$117) -> 14 | O4: =SUM(Ingresos!$AE$124:$AE$128) -> 770
B5: Contratos AV y Migras Todas | C5: =SUM(D5:O5) -> 9585 | D5: =SUM(Ingresos!AF$3:AF$7) -> 2190 | E5: =SUM(Ingresos!AF$14:AF$18) -> 1005 | F5: =SUM(Ingresos!AF$25:AF$29) -> 1440 | G5: =SUM(Ingresos!AF$36:AF$40) -> 255 | H5: =SUM(Ingresos!$AF$47:$AF$51) -> 390 | I5: =SUM(Ingresos!$AF$58:$AF$62) -> 645 | J5: =SUM(Ingresos!$AF$69:$AF$73) -> 420 | K5: =SUM(Ingresos!$AF$80:$AF$84) -> 1395 | L5: =SUM(Ingresos!$AF$91:$AF$95) -> 870 | M5: =SUM(Ingresos!$AF$102:$AF$106) -> 150 | N5: =SUM(Ingresos!$AF$113:$AF$117) -> 0 | O5: =SUM(Ingresos!$AF$124:$AF$128) -> 825
B6: Total cobrado | C6: =SUM(D6:O6) -> 27039 | D6: =SUM(D3:D5) -> 4050 | E6: =SUM(E3:E5) -> 2694 | F6: =SUM(F3:F5) -> 2744 | G6: =SUM(G3:G5) -> 1712 | H6: =SUM(H3:H5) -> 2177 | I6: =SUM(I3:I5) -> 1353 | J6: =SUM(J3:J5) -> 808 | K6: =SUM(K3:K5) -> 3197 | ... O6: =SUM(O3:O5) -> 2915
B7: Previsión Según Nuestro Cuadro | C7: =SUM(D7:O7) -> 29033 | D7: 3689 | E7: 3126 | F7: 2559 | G7: 1616 | H7: 2534 | I7: 2000 | J7: 1900 | K7: 2760 | L7: 3966 | M7: 1716 | N7: 1401 | O7: 1766
B9: Retribución Base Mensual | C9: =SUM(D9:O9) -> 164515.5 | D9: 13474.5 | E9: 13731 | F9: 13731 | G9: 13731 | H9: 13731 | I9: 13731 | J9: 13731 | K9: 13731 | L9: 13731 | M9: 13731 | N9: 13731 | O9: 13731
B10: Total cobrado Territorial + Base Mensual | C10: =C6+C9 -> 191554.5 | D10: =D6+D9 -> 17524.5 | E10: =E6+E9 -> 16425 | F10: =F6+F9 -> 16475 | G10: =G6+G9 -> 15443 | H10: =H6+H9 -> 15908 | I10: =I6+I9 -> 15084 | J10: =J6+J9 -> 14539 | ... O10: =O6+O9 -> 16646

Sheet PyG
A1: Ingresos y Gastos Tiendas 2016 | B1: Enero | C1: Febrero | D1: Marzo | E1: Abril | F1: Mayo | G1: Junio | H1: Julio | I1: Agosto | J1: Septiembre | K1: Octubre | L1: Noviembre | M1: Diciembre | N1: Totales | O1: Media
A2: Caja Tiendas | B2: 22646 | C2: 18605 | D2: 21158 | E2: 18393 | F2: 15076 | G2: 18876.75 | H2: 18380 | I2: 19841 | J2: 20051.12 | K2: 15538 | L2: 15970 | M2: 18141 | N2: =SUM(B2:M2) -> 222675.87 | O2: =SUM(B2:M2)/11 -> 20243.261
A3: Territorial 2015 Canal MoviStar | B3: ='PDV 2016'!D6 -> 4050 | C3: ='PDV 2016'!E6 -> 2694 | D3: ='PDV 2016'!F6 -> 2744 | E3: ='PDV 2016'!G6 -> 1712 | F3: ='PDV 2016'!H6 -> 2177 | G3: ='PDV 2016'!I6 -> 1353 | H3: ='PDV 2016'!J6 -> 808 | I3: ='PDV 2016'!K6 -> 3197 | ... M3: ='PDV 2016'!O6 -> 2915 | N3: =SUM(B3:M3) -> 27039 | O3: =SUM(B3:M3)/7 -> 3862.7143
A4: RETRIBUCION BASE TIENDAS 2016 | B4: ='PDV 2016'!D9 -> 13474.5 | C4: ='PDV 2016'!E9 -> 13731 | D4: ='PDV 2016'!F9 -> 13731 | E4: ='PDV 2016'!G9 -> 13731 | F4: ='PDV 2016'!H9 -> 13731 | G4: ='PDV 2016'!I9 -> 13731 | H4: ='PDV 2016'!J9 -> 13731 | I4: ='PDV 2016'!K9 -> 13731 | ... M4: ='PDV 2016'!O9 -> 13731 | N4: =SUM(B4:M4) -> 164515.5 | O4: =SUM(B4:M4)/10 -> 16451.55
A5: Total Ingresos Tiendas 2016 | B5: =SUM(B2:B4) -> 40170.5 | C5: =SUM(C2:C4) -> 35030 | D5: =SUM(D2:D4) -> 37633 | E5: =SUM(E2:E4) -> 33836 | F5: =SUM(F2:F4) -> 30984 | G5: =SUM(G2:G4) -> 33960.75 | H5: =SUM(H2:H4) -> 32919 | I5: =SUM(I2:I4) -> 36769 | ... M5: =SUM(M2:M4) -> 34787 | N5: =SUM(B5:M5) -> 414230.37 | O5: =SUM(O2:O4) -> 40557.525
A6: Gastos Tiendas 2016 (Sin Comisiones) | B6: =Gastos!K37+Gastos!L37 -> 29498.27 | C6: =Gastos!O37+Gastos!P37 -> 28131.89 | D6: =Gastos!S37+Gastos!T37 -> 31315.39 | E6: =Gastos!W37+Gastos!X37 -> 30542.84 | F6: =Gastos!AA37+Gastos!AB37 -> 29884.07 | G6: =Gastos!AE37+Gastos!AF37 -> 29098.329 | H6: =Gastos!AI37+Gastos!AJ37 -> 46112.79 | I6: =Gastos!AM37+Gastos!AN37 -> 38693.11 | J6: =Gastos!AQ37+Gastos!AR37 -> 31636.9 | K6: =Gastos!AU37+Gastos!AV37 -> 29222.66 | L6: =Gastos!AY37+Gastos!AZ37 -> 41728.45 | M6: =Gastos!BC37+Gastos!BD37 -> 44706.69 | N6: =SUM(B6:M6) -> 410571.39 | O6: =SUM(B6:M6)/11 -> 37324.672
A7: Comisiones Tiendas | B7: 1332.5 | C7: 854 | D7: 686 | E7: 550 | F7: 686 | G7: 410 | H7: 320 | I7: 483 | J7: 483 | K7: 300 | L7: 300 | M7: 300 | N7: =SUM(B7:M7) -> 6704.5 | O7: =SUM(B7:M7)/10 -> 670.45
A8: Gastos Tiendas 2016 | B8: =SUM(B6:B7) -> 30830.77 | C8: =SUM(C6:C7) -> 28985.89 | D8: =SUM(D6:D7) -> 32001.39 | E8: =SUM(E6:E7) -> 31092.84 | F8: =SUM(F6:F7) -> 30570.07 | G8: =SUM(G6:G7) -> 29508.329 | H8: =SUM(H6:H7) -> 46432.79 | I8: =SUM(I6:I7) -> 39176.11 | ... M8: =SUM(M6:M7) -> 45006.69 | N8: =SUM(B8:M8) -> 417275.89 | O8: =SUM(O6:O7) -> 37995.122
A9: GANANCIAS O PERDIDAS TIENDAS | B9: =B5-B8 -> 9339.73 | C9: =C5-C8 -> 6044.11 | D9: =D5-D8 -> 5631.61 | E9: =E5-E8 -> 2743.16 | F9: =F5-F8 -> 413.93 | G9: =G5-G8 -> 4452.421 | H9: =H5-H8 -> -13513.79 | I9: =I5-I8 -> -2407.11 | ... M9: =M5-M8 -> -10219.69 | N9: =SUM(B9:M9) -> -3045.519 | O9: =SUM(B9:M9)/11 -> -276.86536
A10: Comisiones Resto | B10: =(Gastos!M35-B7-B22)/2 -> 1172.95 | C10: =(Gastos!Q35-C7-C22)/2 -> 1328 | D10: =(Gastos!U35-D7-D22)/2 -> 2383.5 | E10: =(Gastos!Y35-E7-E22)/2 -> 663 | F10: =(Gastos!AC35-F7-F22)/2 -> 2411 | G10: =(Gastos!AG35-G7-G22)/2 -> 2609.25 | H10: =(Gastos!AK35-H7-H22)/2 -> 305.5 | I10: =(Gastos!AO35-I7-I22)/2 -> 634.5 | J10: =(Gastos!AS35-J7-J22)/2 -> 1002 | K10: =(Gastos!AW35-K7-K22)/2 -> 2708.5 | L10: =(Gastos!BA35-L7-L22)/2 -> 1415 | M10: =(Gastos!BE35-M7-M22)/2 -> 4006 | N10: =SUM(B10:M10) -> 20639.2 | O10: =SUM(B10:M10)/10 -> 2063.92
A11: Intereses prestamo + Adeslas | B11: =(Gastos!M16+Gastos!M17)/2 -> 615.07 | C11: =(Gastos!Q16+Gastos!Q17)/2 -> 613.07 | D11: =(Gastos!U16+Gastos!U17)/2 -> 613.07 | E11: =(Gastos!Y16+Gastos!Y17)/2 -> 613.07 | F11: =(Gastos!AC16+Gastos!AC17)/2 -> 613.07 | G11: =(Gastos!AG16+Gastos!AG17)/2 -> 613.07 | H11: =(Gastos!AK16+Gastos!AK17)/2 -> 613.07 | I11: =(Gastos!AO16+Gastos!AO17)/2 -> 589.415 | J11: =(Gastos!AS16+Gastos!AS17)/2 -> 589.415 | K11: =(Gastos!AW16+Gastos!AW17)/2 -> 589.415 | L11: =(Gastos!BA16+Gastos!BA17)/2 -> 589.415 | M11: =(Gastos!BE16+Gastos!BE17)/2 -> 588.33 | N11: =SUM(B11:M11) -> 7239.48 | O11: =SUM(B11:M11)/10 -> 723.948
A12: GANANCIAS O PERDIDAS TIENDAS TOTAL | B12: =B9-B10-B11 -> 7551.71 | C12: =C9-C10-C11 -> 4103.04 | D12: =D9-D10-D11 -> 2635.04 | E12: =E9-E10-E11 -> 1467.09 | F12: =F9-F10-F11 -> -2610.14 | G12: =G9-G10-G11 -> 1230.101 | H12: =H9-H10-H11 -> -14432.36 | I12: =I9-I10-I11 -> -3631.025 | ... M12: =M9-M10-M11 -> -14814.02 | N12: =SUM(B12:M12) -> -30924.199 | O12: =SUM(O6:O11) -> 78501.246
A14: Ingresos y Gastos FFVV 2016 | B14: Enero | C14: Febrero | D14: Marzo | E14: Abril | F14: Mayo | G14: Junio | H14: Julio | I14: Agosto | J14: Septiembre | K14: Octubre | L14: Noviembre | M14: Diciembre | N14: Totales | O14: Media
A15: Caja Fuerza de Ventas | B15: 2948 | C15: 4861 | D15: 4449 | E15: 5554 | F15: 5580 | G15: 6386 | H15: 3152 | I15: 4307 | J15: 4602 | K15: 5627 | L15: 4479 | M15: 5062 | N15: =SUM(B15:M15) -> 57007 | O15: =SUM(B15:M15)/11 -> 5182.4545
A16: ACUERDO PLAN RETRIBUCION VARIABLE | B16: ='FFVV 2016'!D3 -> 12294.6 | C16: ='FFVV 2016'!E3 -> 10950 | D16: ='FFVV 2016'!F3 -> 8400 | E16: ='FFVV 2016'!G3 -> 17400 | F16: ='FFVV 2016'!H3 -> 13000 | G16: ='FFVV 2016'!I3 -> 10400 | H16: ='FFVV 2016'!J3 -> 9710.72 | I16: ='FFVV 2016'!K3 -> 20800 | ... M16: ='FFVV 2016'!O3 -> 13200 | N16: =SUM(B16:M16) -> 152365.32 | O16: =SUM(B16:M16)/10 -> 15236.532
A17: PLAN RETRIBUCION VARIABLE TRIMESTRAL | B17: ='FFVV 2016'!D4 -> 4550 | C17: ='FFVV 2016'!E4 -> 4550 | D17: ='FFVV 2016'!F4 -> 4550 | E17: ='FFVV 2016'!G4 -> 4900 | F17: ='FFVV 2016'!H4 -> 4900 | G17: ='FFVV 2016'!I4 -> 4900 | H17: ='FFVV 2016'!J4 -> 4900 | I17: 4900 | J17: ='FFVV 2016'!L4 -> 4900 | K17: ='FFVV 2016'!M4 -> 4900 | L17: ='FFVV 2016'!N4 -> 4900 | M17: ='FFVV 2016'!O4 -> 4900 | N17: =SUM(B17:M17) -> 57750 | O17: =SUM(B17:M17)/10 -> 5775
A18: Producción Plus 2016 | B18: ='FFVV 2016'!D16 -> 2282 | C18: ='FFVV 2016'!E16 -> 4856 | D18: ='FFVV 2016'!F16 -> 4952 | E18: ='FFVV 2016'!G16 -> 2779 | F18: ='FFVV 2016'!H16 -> 7614 | G18: ='FFVV 2016'!I16 -> 5491.5 | H18: ='FFVV 2016'!J16 -> 2430 | I18: ='FFVV 2016'!K16 -> 3383 | ... M18: ='FFVV 2016'!O16 -> 2235 | N18: =SUM(B18:M18) -> 43918.5 | O18: =SUM(B18:M18)/7 -> 6274.0714
A19: Producción Básico 2016 | B19: ='FFVV 2016'!D28 -> 1737.5 | C19: ='FFVV 2016'!E28 -> 2845 | D19: ='FFVV 2016'!F28 -> 3226.5 | E19: ='FFVV 2016'!G28 -> 2155 | F19: ='FFVV 2016'!H28 -> 2608 | G19: ='FFVV 2016'!I28 -> 3217.5 | H19: ='FFVV 2016'!J28 -> 1445 | I19: ='FFVV 2016'!K28 -> 3725 | ... M19: ='FFVV 2016'!O28 -> 4585 | N19: =SUM(B19:M19) -> 37108.5 | O19: =SUM(B19:M19)/7 -> 5301.2143
A20: Total Ingresos FFVV 2016 | B20: =SUM(B15:B19) -> 23812.1 | C20: =SUM(C15:C19) -> 28062 | D20: =SUM(D15:D19) -> 25577.5 | E20: =SUM(E15:E19) -> 32788 | F20: =SUM(F15:F19) -> 33702 | G20: =SUM(G15:G19) -> 30395 | H20: =SUM(H15:H19) -> 21637.72 | I20: =SUM(I15:I19) -> 37115 | ... M20: =SUM(M15:M19) -> 29982 | N20: =SUM(B20:M20) -> 348149.32 | O20: =SUM(O15:O19) -> 37769.272
A21: Gastos FFVV 2016 (Sin Comisiones) | B21: =Gastos!J37 -> 15586.45 | C21: =Gastos!N37 -> 15749.48 | D21: =Gastos!R37 -> 15792.94 | E21: =Gastos!V37 -> 20684.6 | F21: =Gastos!Z37 -> 18290.74 | G21: =Gastos!AD37 -> 18528.29 | H21: =Gastos!AH37 -> 30568.01 | I21: =Gastos!AL37 -> 20158.76 | J21: =Gastos!AP37 -> 19638.48 | K21: =Gastos!AT37 -> 20221.75 | L21: =Gastos!AX37 -> 27990.38 | M21: =Gastos!BB37 -> 28331.32 | N21: =SUM(B21:M21) -> 251541.2 | O21: =SUM(B21:M21)/11 -> 22867.382
A22: Comisiones FFVV | B22: 2339.6 | C22: 2852 | D22: 2817 | E22: 2934 | F22: 2525 | G22: 1935 | H22: 2415 | I22: 1388 | J22: 1533 | K22: 2393 | L22: 930 | M22: 1471 | N22: =SUM(B22:M22) -> 25532.6 | O22: =SUM(B22:M22)/10 -> 2553.26
A23: Gastos FFVV 2016 | B23: =SUM(B21:B22) -> 17926.05 | C23: =SUM(C21:C22) -> 18601.48 | D23: =SUM(D21:D22) -> 18609.94 | E23: =SUM(E21:E22) -> 23618.6 | F23: =SUM(F21:F22) -> 20815.74 | G23: =SUM(G21:G22) -> 20463.29 | H23: =SUM(H21:H22) -> 32983.01 | I23: =SUM(I21:I22) -> 21546.76 | ... M23: =SUM(M21:M22) -> 29802.32 | N23: =SUM(B23:M23) -> 277073.8 | O23: =SUM(O21:O22) -> 25420.642
A24: GANANCIAS O PERDIDAS FFVV | B24: =B20-B23 -> 5886.05 | C24: =C20-C23 -> 9460.52 | D24: =D20-D23 -> 6967.56 | E24: =E20-E23 -> 9169.4 | F24: =F20-F23 -> 12886.26 | G24: =G20-G23 -> 9931.71 | H24: =H20-H23 -> -11345.29 | I24: =I20-I23 -> 15568.24 | ... M24: =M20-M23 -> 179.68 | N24: =SUM(B24:M24) -> 71075.52 | O24: =SUM(B24:M24)/7 -> 10153.646
A25: Comisiones Resto | B25: =(Gastos!M35-B7-B22)/2 -> 1172.95 | C25: =(Gastos!Q35-C7-C22)/2 -> 1328 | D25: =(Gastos!U35-D7-D22)/2 -> 2383.5 | E25: =(Gastos!Y35-E7-E22)/2 -> 663 | F25: =(Gastos!AC35-F7-F22)/2 -> 2411 | G25: =(Gastos!AG35-G7-G22)/2 -> 2609.25 | H25: =(Gastos!AK35-H7-H22)/2 -> 305.5 | I25: =(Gastos!AO35-I7-I22)/2 -> 634.5 | J25: =(Gastos!AS35-J7-J22)/2 -> 1002 | K25: =(Gastos!AW35-K7-K22)/2 -> 2708.5 | L25: =(Gastos!BA35-L7-L22)/2 -> 1415 | M25: =(Gastos!BE35-M7-M22)/2 -> 4006 | N25: =SUM(B25:M25) -> 20639.2 | O25: =SUM(B25:M25)/7 -> 2948.4571
A26: Intereses prestamo + Adeslas | B26: =(Gastos!M16+Gastos!M17)/2 -> 615.07 | C26: =(Gastos!Q16+Gastos!Q17)/2 -> 613.07 | D26: =(Gastos!U16+Gastos!U17)/2 -> 613.07 | E26: =(Gastos!Y16+Gastos!Y17)/2 -> 613.07 | F26: =(Gastos!AC16+Gastos!AC17)/2 -> 613.07 | G26: =(Gastos!AG16+Gastos!AG17)/2 -> 613.07 | H26: =(Gastos!AK16+Gastos!AK17)/2 -> 613.07 | I26: =(Gastos!AO16+Gastos!AO17)/2 -> 589.415 | J26: =(Gastos!AS16+Gastos!AS17)/2 -> 589.415 | K26: =(Gastos!AW16+Gastos!AW17)/2 -> 589.415 | L26: =(Gastos!BA16+Gastos!BA17)/2 -> 589.415 | M26: =(Gastos!BE16+Gastos!BE17)/2 -> 588.33 | N26: =SUM(B26:M26) -> 7239.48 | O26: =SUM(B26:M26)/7 -> 1034.2114
A27: GANANCIAS O PERDIDAS FFVV TOTAL | B27: =B24-B25-B26 -> 4098.03 | C27: =C24-C25-C26 -> 7519.45 | D27: =D24-D25-D26 -> 3970.99 | E27: =E24-E25-E26 -> 7893.33 | F27: =F24-F25-F26 -> 9862.19 | G27: =G24-G25-G26 -> 6709.39 | H27: =H24-H25-H26 -> -12263.86 | I27: =I24-I25-I26 -> 14344.325 | ... M27: =M24-M25-M26 -> -4414.65 | N27: =SUM(B27:M27) -> 43196.84 | O27: =SUM(B27:M27)/5 -> 8639.368
A29: Ganancias de Tiendas | B29: =B12 -> 7551.71 | C29: =C12 -> 4103.04 | D29: =D12 -> 2635.04 | E29: =E12 -> 1467.09 | F29: =F12 -> -2610.14 | G29: =G12 -> 1230.101 | H29: =H12 -> -14432.36 | I29: =I12 -> -3631.025 | ... M29: =M12 -> -14814.02 | N29: =SUM(B29:M29) -> -30924.199 | O29: =SUM(B29:M29)/8 -> -3865.5249
A30: Ganancias de FFVV | B30: =B27 -> 4098.03 | C30: =C27 -> 7519.45 | D30: =D27 -> 3970.99 | E30: =E27 -> 7893.33 | F30: =F27 -> 9862.19 | G30: =G27 -> 6709.39 | H30: =H27 -> -12263.86 | I30: =I27 -> 14344.325 | ... M30: =M27 -> -4414.65 | N30: =SUM(B30:M30) -> 43196.84 | O30: =SUM(B30:M30)/8 -> 5399.605
A31: Ganancias o Perdidas TOTALES | B31: =B29+B30 -> 11649.74 | C31: =C29+C30 -> 11622.49 | D31: =D29+D30 -> 6606.03 | E31: =E29+E30 -> 9360.42 | F31: =F29+F30 -> 7252.05 | G31: =G29+G30 -> 7939.491 | H31: =H29+H30 -> -26696.22 | I31: =I29+I30 -> 10713.3 | ... M31: =M29+M30 -> -19228.67 | N31: =SUM(B31:M31) -> 12272.641 | O31: =SUM(B31:M31)/8 -> 1534.0801
A33: Total Ingresos 2016 | B33: =B5+B20 -> 63982.6 | C33: =C5+C20 -> 63092 | D33: =D5+D20 -> 63210.5 | E33: =E5+E20 -> 66624 | F33: =F5+F20 -> 64686 | G33: =G5+G20 -> 64355.75 | H33: =H5+H20 -> 54556.72 | I33: =I5+I20 -> 73884 | ... M33: =M5+M20 -> 64769 | N33: =sum(B33:M33) -> 762379.69 | O33: =N33/8 -> 95297.461
A34: Total Gastos 2016 | B34: =B8+B23 -> 48756.82 | C34: =C8+C23 -> 47587.37 | D34: =D8+D23 -> 50611.33 | E34: =E8+E23 -> 54711.44 | F34: =F8+F23 -> 51385.81 | G34: =G8+G23 -> 49971.619 | H34: =H8+H23 -> 79415.8 | I34: =I8+I23 -> 60722.87 | ... M34: =M8+M23 -> 74809.01 | N34: =sum(B34:M34) -> 694349.69 | O34: =N34/6 -> 115724.95
A35: Total 2016 | B35: =B33-B34 -> 15225.78 | C35: =C33-C34 -> 15504.63 | D35: =D33-D34 -> 12599.17 | E35: =E33-E34 -> 11912.56 | F35: =F33-F34 -> 13300.19 | G35: =G33-G34 -> 14384.131 | H35: =H33-H34 -> -24859.08 | I35: =I33-I34 -> 13161.13 | ... O35: =O33-O34 -> -20427.487
A37: Total Ingresos 2015 | B37: 61608.7 | C37: 62380 | D37: 68345 | E37: 65874.2 | F37: 65465 | G37: 73782 | H37: 65780 | I37: 64139 | J37: 61848.9 | K37: 61005.7 | L37: 63257.9 | M37: 59917 | N37: =SUM(B37:M37) -> 773403.4 | O37: =N37/12 -> 64450.283
A38: Total Gastos 2015 | B38: 51044.1 | C38: 55209.21 | D38: 58129.17 | E38: 59135.6 | F38: 56611.69 | G38: 72277.69 | H38: 85261.05 | I38: 52873.49 | J38: 53593 | K38: 54689.27 | L38: 53558.15 | M38: 77621.77 | N38: =SUM(B38:M38) -> 730004.19 | O38: =N38/12 -> 60833.683
A39: Total 2015 | B39: =B37-B38 -> 10564.6 | C39: =C37-C38 -> 7170.79 | D39: =D37-D38 -> 10215.83 | E39: =E37-E38 -> 6738.6 | F39: =F37-F38 -> 8853.31 | G39: =G37-G38 -> 1504.31 | H39: =H37-H38 -> -19481.05 | I39: =I37-I38 -> 11265.51 | ... O39: =O37-O38 -> 3616.6008
A41: Total Ingresos 2014 | B41: 69393.9 | C41: 63307.53 | D41: 66823.67 | E41: 58103.95 | F41: 53932.16 | G41: 69107.27 | H41: 72454.33 | I41: 54315.35 | J41: 53095.96 | K41: 62359.29 | L41: 56681.92 | M41: 78415.72 | N41: =sum(B41:M41) -> 757991.05 | O41: =N41/12 -> 63165.921
A42: Total Gastos 2014 | B42: 51516.22 | C42: 50323.7 | D42: 67257.31 | E42: 52539.52 | F42: 58558.07 | G42: 61032.21 | H42: 77805.64 | I42: 52253.94 | J42: 55241.07 | K42: 51916.07 | L42: 54129.12 | M42: 75071.44 | N42: =sum(B42:M42) -> 707644.31 | O42: =N42/12 -> 58970.359
A43: Total 2014 | B43: =B41-B42 -> 17877.68 | C43: =C41-C42 -> 12983.83 | D43: =D41-D42 -> -433.64 | E43: =E41-E42 -> 5564.43 | F43: =F41-F42 -> -4625.91 | G43: =G41-G42 -> 8075.06 | H43: =H41-H42 -> -5351.31 | I43: =I41-I42 -> 2061.41 | ... O43: =O41-O42 -> 4195.5617

Sheet Fondo de Maniobra
B1: Enero | C1: Febrero | D1: Marzo | E1: Abril | F1: Mayo | G1: Junio | H1: Julio | I1: Agosto | J1: Septiembre | K1: Octubre | L1: Noviembre | M1: Diciembre
A2: Ingresos acumulados
A3: NF Promociones I
A4: NF Promociones II
A5: Acuerdo Plan Retribución Variable
A6: Movistar Contrato
A7: Movistar Fidelización
A8: Movistar Fidelización P1
A9: Movistar Fidelización P2
A10: Movistar Fidelización P3
A11: Plan Retribución Variable Trimestral
A12: Promociones Movistar I
A13: Promociones Movistar II
... A16: Servicios Especiales
A17: Total | B17: =SUM(B3:B16) -> 0 | C17: =SUM(C3:C16) -> 0 | D17: =SUM(D3:D16) -> 0 | E17: =SUM(E3:E16) -> 0 | F17: =SUM(F3:F16) -> 0 | G17: =SUM(G3:G16) -> 0 | H17: =SUM(H3:H16) -> 0 | I17: =SUM(I3:I16) -> 0 | ... M17: =SUM(M3:M16) -> 0 | N17: =SUM(B17:M17) -> 0
A18: Gastos acumulados
A19: Préstamo padres | B19: -27000
A20: Total | B20: =SUM(B19) -> -27000 | C20: =SUM(C19) -> 0 | D20: =SUM(D19) -> 0 | E20: =SUM(E19) -> 0 | F20: =SUM(F19) -> 0 | G20: =SUM(G19) -> 0 | H20: =SUM(H19) -> 0 | I20: =SUM(I19) -> 0 | ... M20: =SUM(M19) -> 0 | N20: =SUM(B20:M20) -> -27000
A21: Reclamaciones acumuladas
A22: Posibles reclamaciones
A23: Total | B23: =SUM(B22) -> 0 | C23: =SUM(C22) -> 0 | D23: =SUM(D22) -> 0 | E23: =SUM(E22) -> 0 | F23: =SUM(F22) -> 0 | G23: =SUM(G22) -> 0 | H23: =SUM(H22) -> 0 | I23: =SUM(I22) -> 0 | ... M23: =SUM(M22) -> 0 | N23: =SUM(B23:M23) -> 0

Sheet Estimación de Tesorería
B1: Actual | C1: Final de mes
A2: Ingresos esperados
A3: Caja Duero (Efectivo) | C3: 758.76
A4: Banco Popular (Efectivo) | C4: 5128.89
A5: Telefónica Consumer Finance | C5: 6000
A6: Tiendas Tarjeta (Banco Popular) | C6: 3000
A7: Previsión Ingresos MoviStar | C7: 0
A8: Ingresos en Ventanilla | C8: 5000
A9: Disponibilidad Cuenta de Credito | C9: 68265.39
A10: Total | B10: =SUM(B3:B9) -> 0 | C10: =SUM(C3:C9) -> 88153.04 | D10: =SUM(C10) -> 88153.04
A11: Gastos esperados
A12: Vencimientos | C12: -15000
A13: Nóminas | C13: -21900
A14: Pagas Extra | C14: 0
A15: Seguridad Social | C15: -10800
A16: Alquiler | C16: 0
A17: Otros gastos | C17: 0
A18: Impuestos Hacienda
A19: Total | B19: =SUM(B12:B18) -> 0 | C19: =SUM(C12:C18) -> -47700 | D19: =SUM(C19) -> -47700
A21: Tesorería Actual | B21: =SUM(B10+B19) -> 0 | C21: Estimación Tesorería | D21: =SUM(D10+D19) -> 40453.04

Sheet Intereses
B1: Banco Popular | E1: Zeleris | H1: Total Pagado | K1: 2016 JULIO Banco Popular | M1: Condiciones Zeleris | O1: 2016 MARZO Banco Popular | Q1: Condiciones 2015 Banco Popular
B2: Fecha | C2: Importe | E2: Fecha | F2: Importe | H2: Fecha | I2: Importe | K2: Fechas de Vencimiento | M2: Importe | O2: Fechas de Vencimiento | Q2: Fechas de Vencimiento
B3: 19/01/2015 Caja Duero | C3: 248 | E3: 42005 | F3: 540.63 | H3: 42005 | I3: =C3+F3 -> 788.63 | K3: 42944 | M3: Sin Fecha | O3: 42812 | Q3: 42448
B4: 19/02/2015 Caja Duero | C4: 149.97 | E4: 42036 | F4: 995.18 | H4: 42036 | I4: =C4+F4 -> 1145.15 | K4: Tipo Vigente | M4: Importe | O4: Tipo Vigente | Q4: Tipo Vigente
B5: 20 mar. 2015 Apertura de la nueva Línea de Credito al 0,75% | C5: 900.42 | E5: 42064 | F5: 686.19 | H5: 42082 | I5: =C5+F5 -> 1586.61 | K5: 0.015 | M5: 0.0912 | O5: 0.0215 | Q5: 0.03
B6: 42112 | C6: 342.2 | E6: 42095 | F6: 697.51 | H6: 42112 | I6: =C6+F6 -> 1039.71 | K6: Apertura | M6: Importe | O6: Apertura | Q6: Apertura
B7: 42144 | C7: 383.16 | E7: 42125 | F7: 755.77 | H7: 42144 | I7: =C7+F7 -> 1138.93 | K7: 0.005 | M7: 0 | O7: 0.0075 | Q7: 0.0075
B8: 42175 | C8: 374.97 | E8: 42156 | F8: 639.45 | H8: 42176 | I8: =C8+F8 -> 1014.42 | K8: Tipo Vigente | M8: Tipo Vigente | O8: Tipo Vigente | Q8: Tipo Vigente
B9: 42203 | C9: 365.17 | E9: 42186 | F9: 706.68 | H9: 42208 | I9: =C9+F9 -> 1071.85 | K9: 0,10% Nominal | M9: 0 | O9: 0,10% Nominal | Q9: 0,10% Nominal
B10: 42236 | C10: 327.66 | E10: 42217 | F10: 577.91 | H10: 42240 | I10: =C10+F10 -> 905.57 | K10: Importe | M10: Importe | O10: Importe | Q10: Importe
B11: 42266 | C11: 273.93 | E11: 42248 | F11: 448.27 | H11: 42272 | I11: =C11+F11 -> 722.2 | K11: 200000 | M11: 70000 | O11: 150000 | Q11: 120000
B12: 42297 | C12: 273.73 | E12: 42278 | F12: 878.8 | H12: 42304 | I12: =C12+F12 -> 1152.53 | K12: Interés Anual | M12: Interés Anual | O12: Interés Anual | Q12: Interés Anual
B13: 42328 | C13: 364.12 | E13: 42309 | F13: 627.06 | H13: 42336 | I13: =C13+F13 -> 991.18 | K13: 0.015 | M13: 0.0924 | O13: 0.0215 | Q13: 0.03
B14: 42358 | C14: 277.54 | E14: 42339 | F14: 506.84 | H14: 42368 | I14: =C14+F14 -> 784.38 | K14: Importe Anual | M14: Importe Anual | O14: Importe Anual | Q14: Importe Anual
B15: 42389 | C15: 227.93 | E15: 42370 | F15: 573.33 | H15: 42370 | I15: =C15+F15 -> 801.26 | K15: =K11*K13 -> 3000 | M15: =M11*M13 -> 6468 | O15: =O11*O13 -> 3225 | Q15: =Q11*Q13 -> 3600
B16: 42420 | C16: 299.62 | E16: 42401 | F16: 496.54 | H16: 42401 | I16: =C16+F16 -> 796.16 | K16: TAE (APERTURA) Mensual | M16: SIN TAE | O16: TAE (APERTURA) Mensual | Q16: TAE (APERTURA) Mensual
B17: 42447 | C17: 288.84 | E17: 42430 | F17: 398.11 | H17: 42430 | I17: =C17+C18+F17 -> 1812.4 | K17: =(K7*K11)/12 -> 83.333333 | O17: =(O7*O11)/12 -> 93.75 | Q17: =(Q7*Q11)/12 -> 75
B18: 20 mar. 2016 Apertura de la nueva Línea de Credito al 0,75% | C18: 1125.45 | K18: Interes Mensual + TAE | M18: Interes Mensual TAE 0,77% | O18: Interes Mensual + TAE | Q18: Interes Mensual + TAE
B19: 42480 | C19: 338.77 | E19: 42461 | F19: 252.2 | H19: 42461 | I19: =C19+F19 -> 590.97 | K19: =(K11*K13)/12+K17 -> 333.33333 | M19: =M15/12 -> 539 | O19: =(O11*O13)/12+O17 -> 362.5 | Q19: =(Q11*Q13)/12+Q17 -> 375
B20: 42510 | C20: 367.47 | E20: 42492 | F20: 0 | H20: 42492 | I20: =C20+F20 -> 367.47
B21: 42541 | C21: 337.59 | E21: 42523 | F21: 0 | H21: 42523 | I21: =C21+F21 -> 337.59
B22: 20 jul. 2016 Ampliación Línea de Credito 250€ | C22: 701.21 | E22: 42554 | F22: 0 | H22: 42554 | I22: =C22+F22 -> 701.21
B23: 42610 | C23: 229.14 | E23: 42585 | F23: 0 | H23: 42585 | I23: =C23+F23 -> 229.14
B24: 42641 | C24: 228.66 | E24: 42616 | F24: 0 | H24: 42616 | I24: =C24+F24 -> 228.66
B25: 42671 | C25: 231.02 | E25: 42647 | F25: 0 | H25: 42647 | I25: =C25+F25 -> 231.02
B26: 42702 | C26: 232.77 | E26: 42678 | F26: 0 | H26: 42678 | I26: =C26+F26 -> 232.77
B27: 42732 | C27: 231.57 | E27: 42709 | F27: 0 | H27: 42709 | I27: =C27+F27 -> 231.57
B28: 42763 | C28: 232.6 | E28: 42740 | F28: 0 | H28: 42740 | I28: =C28+F28 -> 232.6
B29: 42794 | C29: 0 | E29: 42771 | F29: 0 | H29: 42771 | I29: =C29+F29 -> 0
B30: 42822 | C30: 0 | E30: 42799 | F30: 0 | H30: 42799 | I30: =C30+F30 -> 0
B31: 42853 | C31: 0 | E31: 42830 | F31: 0 | H31: 42830 | I31: =C31+F31 -> 0
B32: 42883 | C32: 0 | E32: 42860 | F32: 0 | H32: 42860 | I32: =C32+F32 -> 0
B33: 42914 | C33: 0 | E33: 42891 | F33: 0 | H33: 42891 | I33: =C33+F33 -> 0
B34: 42944 | C34: 0 | E34: 42921 | F34: 0 | H34: 42921 | I34: =C34+F34 -> 0
B35: 42975 | C35: 0 | I35: =C35+F35 -> 0
B36: 43006 | C36: 0 | I36: =C36+F36 -> 0
B37: 43036 | C37: 0 | I37: =C37+F37 -> 0
B38: 43067 | C38: 0 | I38: =C38+F38 -> 0
B39: 43097 | C39: 0 | I39: =C39+F39 -> 0
I40: =C40+F40 -> 0
I41: =C41+F41 -> 0
I42: =C42+F42 -> 0
I43: =C43+F43 -> 0
I44: =C44+F44 -> 0
I45: =C45+F45 -> 0

Sheet E. Gastos
A1: Ejemplos | B1: Gastos Fijos | C1: TOTAL Mensual | D1: Mensual Total Comerc.( 7) | E1: Mensual Total Tiendas (11) | F1: MensualTotal MovilFree (1) | G1: Control
A2: A cada uno lo suyo (FFVV y Tiendas) Cristina y Aluis se divide entre todos y se multiplica por el total | B2: Sueldos | C2: =SUM(D2:F2) -> 1032.38 | D2: 0 | E2: 0 | F2: 1032.38
A3: A cada uno lo suyo (FFVV y Tiendas) Cristina y Aluis se divide entre todos y se multiplica por el total | B3: Seguridad Social Empresa | C3: =SUM(D3:F3) -> 0 | D3: 0 | E3: 0 | F3: 0
A4: A cada uno se le imputa su gasto a ecepción de Estación (50% FFVV y 50% Tiendas) | B4: Arrendamientos | C4: =SUM(D4:F4) -> 6081.74 | D4: 873.8 | E4: 5207.94 | G4: 7031.74
A5: A cada uno se le imputa su gasto a ecepción de Estación (50% FFVV y 50% Tiendas) | B5: Luz | C5: =SUM(D5:F5) -> 0 | D5: 0 | E5: 0 | F5: 0
A6: FFVV y Salva para tiendas | B6: Gasoil Solred | C6: =SUM(D6:F6) -> 0 | D6: 0 | E6: 0 | F6: 0
A7: A cada uno lo suyo (FFVV y Tiendas) Cristina Tiendas y Aluis FFVV | B7: Teléfono Fijo | C7: =SUM(D7:F7) -> 0 | D7: 0 | E7: 0 | F7: 0
A8: A cada uno lo suyo (FFVV y Tiendas) Cristina Tiendas y Aluis FFVV | B8: Teléfono Móvil | C8: =SUM(D8:F8) -> 0 | D8: 0 | E8: 0 | F8: 0
A9: Dividido entre todos los trabajadores a ecepción de Cristina y Aluis y multiplicado por cada uno | B9: Asesoria Laboral | C9: =SUM(D9:F9) -> 370.00579 | D9: =(G9/19)*7 -> 136.31579 | E9: 214.2 | F9: 19.49 | G9: 370
A10: Dividido entre todos los trabajadores a ecepción de Cristina y Aluis y multiplicado por cada uno | B10: Abogado | C10: =SUM(D10:F10) -> 170.01737 | D10: 62.62 | E10: 98.45 | F10: =(G10/19)*1 -> 8.9473684 | G10: 170
A11: A cada uno la suya | B11: Dietas Tiendas y Comerciales | C11: =SUM(D11:F11) -> 0 | D11: 0 | E11: 0 | F11: 0 | G11: 0
A12: A cada uno se le imputa su gasto a ecepción de Estación (50% FFVV y 50% Tiendas) | B12: Limpieza de Cristales | C12: =SUM(D12:F12) -> 0 | D12: 0 | E12: 0 | F12: 0
A13: Dividido entre todos los trabajadores a ecepción de Cristina y Aluis y multiplicado por cada uno | B13: Transportes | C13: =SUM(D13:F13) -> 74.08 | D13: 27.29 | E13: 39 | F13: 7.79 | G13: 74.08
A14: A cada uno se le imputa su gasto a ecepción de Estación (50% FFVV y 50% Tiendas) | B14: Agua | C14: =SUM(D14:F14) -> 0 | D14: 0 | E14: 0 | F14: 0
A15: A cada uno se le imputa su gasto a ecepción de Estación (50% FFVV y 50% Tiendas) | B15: Comunidades | C15: =SUM(D15:F15) -> 0 | D15: 0 | E15: 0 | F15: 0
A16: A ninguno (ponerlo en el Total Mensual) | B16: Intereses Prestamo Piso | C16: =SUM(D16:F16) -> 0 | D16: 0 | E16: 0 | F16: 0
A17: A ninguno (ponerlo en el Total Mensual) | B17: Adeslas (Angel Luis) | C17: =SUM(D17:F17) -> 0 | D17: 0 | E17: 0 | F17: 0
A18: Total | C18: =SUM(C2:C17) -> 7728.2232 | D18: =SUM(D2:D17) -> 1100.0258 | E18: =SUM(E2:E17) -> 5559.59 | F18: 26.095205
A19: Ejemplos | B19: Gastos Variables | C19: TOTAL Mensual | D19: Mensual Total Comerc. (7) | E19: Mensual Total Tiendas (11) | F19: MensualTotal MovilFree (1)
A20: A cada uno la suya | B20: Arreglo Tiendas | C20: =SUM(D20:F20) -> 0 | G20: =SUM(D20:F20) -> 0
A21: A cada uno la suya | B21: Sueldos Fuera Nómi. (Idemni) | C21: =SUM(D21:F21) -> 0 | G21: =SUM(D21:F21) -> 0
A22: A cada uno la suya | B22: Impuestos (Basur, IBI, Circ.) | C22: =SUM(D22:F22) -> 0 | G22: =SUM(D22:F22) -> 0
A23: A cada uno la suya | B23: Publicidad | C23: =SUM(D23:F23) -> 0 | G23: =SUM(D23:F23) -> 0
A24: A cada uno la suya | B24: Mantenimiento Vehiculos | C24: =SUM(D24:F24) -> 0 | G24: =SUM(D24:F24) -> 0
A25: Dividido entre todos los trabajadores a ecepción de Cristina y Aluis y multiplicado por cada uno | B25: Arsys Internet + Golden Soft | C25: =SUM(D25:F25) -> 324 | D25: =(G25/19)*7 -> 119.36842 | E25: =(G25/19)*10 -> 170.52632 | F25: =(G25/19)*2 -> 34.105263 | G25: 324
A26: Dividido entre todos los trabajadores a ecepción de Cristina y Aluis y multiplicado por cada uno | B26: Comisiones Bancarias | C26: =SUM(D26:F26) -> 264.81 | D26: =(G26/19)*7 -> 97.561579 | E26: =(G26/19)*10 -> 139.37368 | F26: =(G26/19)*2 -> 27.874737 | G26: 264.81
A27: Dividido entre todos los trabajadores a ecepción de Cristina y Aluis y multiplicado por cada uno | B27: Material de Oficina | C27: =SUM(D27:F27) -> 271.06 | D27: =(G27/19)*7 -> 99.864211 | E27: =(G27/19)*10 -> 142.66316 | F27: =(G27/19)*2 -> 28.532632 | G27: 271.06
A28: A cada uno se le imputa su gasto a ecepción de Estación (50% FFVV y 50% Tiendas) | B28: Seguros Tiendas | C28: =SUM(D28:F28) -> 0 | G28: =SUM(D28:F28) -> 0
A29: A cada uno la suya | B29: Varios (Multas,etc) | C29: =SUM(D29:F29) -> 0 | G29: =SUM(D29:F29) -> 0
A30: FFVV | B30: Seguros Automovil | C30: =SUM(D30:F30) -> 0 | G30: =SUM(D30:F30) -> 0
A31: Dividido entre todos los trabajadores a ecepción de Cristina y Aluis y multiplicado por cada uno | B31: Mutua | C31: =SUM(D31:F31) -> 139.19 | D31: =(G31/19)*7 -> 51.280526 | E31: =(G31/19)*10 -> 73.257895 | F31: =(G31/19)*2 -> 14.651579 | G31: 139.19
A32: Dividido entre todos los trabajadores a ecepción de Cristina y Aluis y multiplicado por cada uno | B32: Tarjetas Vodafone | C32: =SUM(D32:F32) -> 150 | D32: =(G32/19)*7 -> 55.263158 | E32: =(G32/19)*10 -> 78.947368 | F32: =(G32/19)*2 -> 15.789474 | G32: 150
A33: A cada uno la suya | B33: Penalizaciones Teléfonica | C33: =SUM(D33:F33) -> 0 | G33: 0
A34: Dividido entre todos los trabajadores a ecepción de Cristina y Aluis y multiplicado por cada uno | B34: Alquiler plaza Garage | C34: =SUM(D34:F34) -> 825 | D34: =(G34/19)*7 -> 303.94737 | E34: =(G34/19)*10 -> 434.21053 | F34: =(G34/19)*2 -> 86.842105 | G34: 825
A35: A ninguno (ponerlo en el Total Mensual) | B35: Salidas Angel Luis | C35: 3000 | G35: 3000
A36: Total | C36: =SUM(C20:C35) -> 4974.06 | D36: =SUM(D20:D35) -> 727.28526 | E36: =SUM(E20:E35) -> 1038.9789 | F36: =SUM(F20:F35) -> 207.79579

Sheet IVA
B2: AÑO 2016
B3: MES | C3: ENERO | D3: FEBRERO | E3: MARZO | F3: ABRIL | G3: MAYO | H3: JUNIO | I3: JULIO | J3: AGOSTO | K3: SEPTIEMBRE | L3: OCTUBRE | M3: NOVIEMBRE | N3: DICIEMBRE | O3: Totales
B4: IVA Móviles | C4: 13263.48 | D4: 10942.73 | E4: 9426.4 | F4: 12725.79 | G4: 12497.75 | H4: 8576.43 | I4: 7682.4 | J4: 9682.83 | K4: 19991.92 | L4: 9002.93 | M4: 10282.87 | N4: 13506.89 | O4: =SUM(C4:N4) -> 137582.42
B5: IVA a Clientes | C5: 10974.54 | D5: 9064.51 | E5: 9852.21 | F5: 9306.01 | G5: 10551.57 | H5: 13687.21 | I5: 11823.83 | J5: 9407.24 | K5: 393.96 | L5: 10647.84 | M5: 12179.58 | N5: 8776.42 | O5: =SUM(C5:N5) -> 116664.92
B6: Total Mes | C6: =SUM(C4:C5) -> 24238.02 | D6: =SUM(D4:D5) -> 20007.24 | E6: =SUM(E4:E5) -> 19278.61 | F6: =SUM(F4:F5) -> 22031.8 | G6: =SUM(G4:G5) -> 23049.32 | H6: =SUM(H4:H5) -> 22263.64 | I6: =SUM(I4:I5) -> 19506.23 | J6: =SUM(J4:J5) -> 19090.07 | ... N6: =SUM(N4:N5) -> 22283.31 | O6: =SUM(C6:N6) -> 254247.34
B7: Total Trimestre | C7: =SUM(C6:E6) -> 63523.87 | F7: =SUM(F6:H6) -> 67344.76 | I7: =SUM(I6:K6) -> 58982.18 | L7: =SUM(L6:N6) -> 64396.53 | O7: =C7+F7+I7+L7 -> 254247.34
B10: AÑO 2015
B11: MES | C11: ENERO | D11: FEBRERO | E11: MARZO | F11: ABRIL | G11: MAYO | H11: JUNIO | I11: JULIO | J11: AGOSTO | K11: SEPTIEMBRE | L11: OCTUBRE | M11: NOVIEMBRE | N11: DICIEMBRE | O11: Totales
B12: IVA Móviles | C12: 12345 | D12: 22752 | E12: 15669 | F12: 20883.09 | G12: 17669.12 | H12: 19526.55 | I12: 15968.44 | J12: 12386.3 | K12: 24282.65 | L12: 17326.78 | M12: 14004.79 | N12: 15855.92 | O12: =SUM(C12:N12) -> 208669.64
B13: IVA a Clientes | C13: 11855.14 | D13: 136.66 | E13: 8538.01 | F13: 1650.99 | G13: 15250.9 | H13: 2455.97 | I13: 13713.98 | J13: 8112.42 | K13: -8972.86 | L13: 11493.9 | M13: 16997.19 | N13: 15449.31 | O13: =SUM(C13:N13) -> 96681.61
B14: Total Mes | C14: =SUM(C12:C13) -> 24200.14 | D14: =SUM(D12:D13) -> 22888.66 | E14: =SUM(E12:E13) -> 24207.01 | F14: =SUM(F12:F13) -> 22534.08 | G14: =SUM(G12:G13) -> 32920.02 | H14: =SUM(H12:H13) -> 21982.52 | I14: =SUM(I12:I13) -> 29682.42 | J14: =SUM(J12:J13) -> 20498.72 | ... N14: =SUM(N12:N13) -> 31305.23 | O14: =SUM(C14:N14) -> 305351.25
B15: Total Trimestre | C15: =SUM(C14:E14) -> 71295.81 | F15: =SUM(F14:H14) -> 77436.62 | I15: =SUM(I14:K14) -> 65490.93 | L15: =SUM(L14:N14) -> 91127.89 | O15: =C15+F15+I15+L15 -> 305351.25

Sheet Penalizaciones v1
C2: Enero | D2: Febrero | E2: Marzo | F2: Abril | G2: Mayo | H2: Junio | I2: Julio | J2: Agosto | K2: Septiembre | L2: Octubre | M2: Noviembre | N2: Diciembre
B3: FFVV ACUERDO PRV
B4: FFVV CALIDAD DE LA VENTA
B5: PDV CALIDAD DE LA VENTA
B6: PDV MOVISTAR CONTRATO
B8: Penalizaciones
B9: Tienda o Responsables | C9: Mes | D9: Motivo | E9: NIF Cliente | F9: Nombre del Cliente | G9: Importe Penalización | H9: Se puede reclamar | I9: Cobrado a los responsables
B10: Álvaro | C10: Enero | D10: Cliente no ha pedido nada. Los Instaladores contactaron con la secretaria que no sabía nada, en lugar del interesado. En ODIN se había puesto bien el contacto del interesado | E10: B37220837 | F10: Geshprocor | G10: 200 | H10: Si
B11: Juan Carlos | C11: Febrero | D11: Migra a fibra de Cloud. Cliente dice que no ha solicitado nada | E11: B37480449 | F11: Kristal Cerrajeros | G11: 200 | H11: si
B12: Luis | C12: Enero | D12: Mala información comercial (Y03) | E12: 50024366X | F12: Fernando Urbina Casillas | G12: 100 | H12: si
B13: Luis | C13: Enero | D13: cliente ilocalizable (N11) | E13: 06522860Z | F13: Jose Manuel Martín | G13: 50 | H13: si
B14: Luis | C14: Febrero | D14: Cliente ilocalizable | E14: 07988998V | F14: Miguel Angel Sanchez Sanchez | G14: 50 | H14: si
B15: Luis | C15: Marzo | D15: Cliente ilocalizable | E15: 46703954Q | F15: Ana Yolanda Arias Carpintero | G15: 50 | H15: si
B16: LUis | C16: Marzo | D16: Cliente ilocalizable | E16: 07925774C | F16: Concepción Lobato Vazquez | G16: 50 | H16: si
B17: Luis | C17: Marzo | D17: Cliente ilocalizable | E17: 07925774C | F17: Concepción Lobato Vazquez | G17: 50 | H17: si
B18: Luis | C18: Junio | D18: cliente ilocalizable (N11) | E18: 07856971x | G18: 50 | H18: SI
B19: Toñi | C19: Junio | D19: Error de tramitacion en P/s N06 | E19: 29395418S | G19: 50 | H19: SI
B20: Luis | C20: junio | D20: Mala informacion comercial sobre características del p/s (N03) | E20: 70960387M | G20: 50 | H20: SI
B21: Luis | C21: junio | D21: Mala informacion comercial sobre características del p/s (N03) | E21: 70960387M | G21: 50 | H21: SI
B22: Andres | C22: junio | D22: Error de tramitacion en P/s N06 | E22: 7975995D | F22: El cliente le dijo al comercial que quería fusion plus TV y cuando llegaron los instaladores cambio de opinión y dijo que prefería de satélite | G22: 50 | H22: si
B23: Diego | C23: julio | D23: Error de tramitacion en P/s N06 | E23: A37047354 | G23: 50 | H23: SI
B24: Diego | C24: julio | D24: Error de tramitacion en P/s N06 | E24: A37047354 | G24: 50 | H24: SI
B25: Diego | C25: julio | D25: Error de tramitacion en P/s N06 | E25: A37047354 | G25: 50 | H25: SI
B26: Diego | C26: julio | D26: Error de tramitacion en P/s N06 | E26: A37047354 | G26: 50 | H26: SI
B27: Marta | C27: julio | D27: Error de tramitación en el domicilio de instalación | E27: X2259452R | F27: la dirección en todo momento ha sido la correcta se puede comprobar en el pedido instalado. | G27: 100 | H27: SI
B28: carmen | C28: julio | D28: Mala info comercial sobre características del P/S | E28: 07789711W | F28: Fue tema de instalación ya que no habia en el momento que la quería y cuando fueron a instalarasela ya no le interesaba para nada fue una mala información comercial (se puede llamar a la señora). El contrato está firmado | G28: 50 | H28: SI
B29: Juan Carlos | C29: julio | D29: Error de tramitación por error en aplicación del procedimiento | E29: B37299054 | F29: PROARCI | G29: 50 | H29: SI
B30: Juan Carlos | C30: julio | D30: Mala info comercial sobre características del P/S | E30: Q3768438H | F30: IES GUIJUELO | G30: 50 | H30: SI
B31: Javier | C31: julio | D31: Error de tramitación en P/S | E31: B37278454 | F31: SERSA VETERUNARIOS | G31: 50 | H31: SI
B32: carmen | C32: 42383 | D32: se mando por 2ª vez el 18/02 lo que ocurre que después se hizo un cambio de titular | E32: 71418351Q | F32: VALIJA | G32: 50 | H32: si | I32: si
B33: Toñi | C33: 42384 | D33: Se envió con firma el día 10/02 | E33: 18829866l | F33: VALIJA | G33: 30 | H33: si | I33: si
B34: Toñi | C34: 42391 | D34: Se envió con firma el día 10/02 | E34: 28311345R | F34: VALIJA | G34: 30 | H34: si | I34: si
B35: cristina tienda | C35: 42403 | D35: Enviado con firma el día 08/03 | E35: 07874670E | F35: VALIJA | G35: 30 | H35: si | I35: si
B36: FFVV | C36: 42404 | D36: Enviado con firma el día 08/03 | E36: 07959251D | F36: VALIJA | G36: 30 | H36: si | I36: si
B37: Toñi | C37: 42419 | D37: Enviado 08/03 y enviado por segunda vez el 17/05 con firma | E37: 28532798X | F37: VALIJA | G37: 30 | H37: si | I37: si
B38: Cristina Telemarketing | C38: 42423 | D38: Envidao con firma 08/03 | E38: 07725663D | F38: VALIJA | G38: 30 | H38: si | I38: si
B39: Cristina Telemarketing | C39: 42431 | D39: Enviado con firma 08/04 | E39: 70957337z | F39: VALIJA | G39: 30 | H39: si | I39: si
B40: Toñi | C40: 42457 | D40: Enviado por 3º vez y con firma 17/06 | E40: 70930526K | F40: VALIJA | G40: 30 | H40: si | I40: si
B41: FFVV | C41: 42478 | D41: Enviado con firma el día 13/05 | E41: G47751938 | F41: VALIJA | G41: 30 | H41: si | I41: si
B42: Maria | C42: 42482 | D42: Enviado con firma el día 13/05 | E42: 07783311l | F42: VALIJA | G42: 50 | H42: si | I42: si
B43: cristina tienda | C43: 42509 | D43: PENALIZADO POR FIRMA PERO SE ENVIO CON FIRMA | E43: 07992116F | F43: VALIJA | G43: 30 | H43: SI | I43: RECLAMAR
B44: FFVV | C44: 42539 | D44: 629774261 | E44: 07956327Y | F44: VALIJA ENVIADO | G44: 50 | H44: SI
B45: MARTA | C45: 42549 | D45: 618165920 | E45: 06995546G | F45: VALIJA SE ANULÓ EL ALTA | G45: 50 | H45: SI
B46: CARmen | C46: 42541 | D46: 608207658 | E46: 07784213R | F46: VALIJA ENVIADO CON FIRMA | G46: 30 | H46: SI
B47: CARmen | C47: 42531 | D47: 646695040 | E47: 07959335R | F47: VALIJA ENVIADO CON FIRMA | G47: 30 | H47: SI
B48: MARTA | C48: 42528 | D48: 620013874 | E48: 70902316D | F48: VALIJA ENVIADO | G48: 50 | H48: SI
B49: MARTA | C49: 42544 | D49: 646252377 | E49: 07857578L | F49: VALIJA ENVIADO | G49: 50 | H49: SI
B50: Toñi | C50: Enero | D50: Cliente no ha pedido nada (N02) | E50: 45002209H | F50: Juan Borrego Pousa | G50: 200 | H50: Se esta intentando
B51: TOÑI | C51: 42522 | D51: 606230569 | E51: 45036736E | F51: VAlija no enviado contrato | G51: 50 | H51: NO
B52: Santa Marta | C52: Enero | D52: Porta carteles A4 sin carteles | G52: 256.5 | H52: NO | I52: SI
B53: Toñi | C53: Enero | D53: Pedido duplicado (N09) | E53: 27992197R | F53: Herminia Garcia Fernandez | G53: 50 | H53: NO | I53: SI
B54: Peñaranda | C54: Marzo | D54: Cartelería Tuenti | G54: 252 | H54: No | I54: SI
B55: Álvaro | C55: Enero | D55: Mala Información Comercial. No quiere instalación, ni subida de precios | E55: B37400033 | F55: Autoservicios Celmar | G55: 50 | H55: No
B56: Alvaro | C56: Diciembre | D56: Error de tramitacion en P/s N06 | E56: B37289360 | F56: Camporsi | G56: 50 | H56: No | I56: si
B57: Toñi | C57: Enero | D57: clienta no ha pedidio nada N02 | E57: 27992197R | F57: Herminia Garcia Fernandez | G57: 200 | H57: No | I57: si
B58: Toñi | C58: Diciembre | D58: Mala Información Comercial. (n03) | E58: 45019672R | F58: Josefa Herrero Bravo | G58: 50 | H58: No | I58: si
B59: Toñi | C59: Febrero | D59: Penalización calcing (N02) | E59: 07579231H | F59: Juan Garcia Santos | G59: 200 | H59: No | I59: si
B60: Toñi | C60: Febrero | D60: Error de tramitación en P/S | E60: 08546304X | F60: Antonio Nuñez Reyes | G60: 50 | H60: NO | I60: si
B61: Alvaro | C61: Abril | D61: Pedido duplicado: Se instala el 1º y se anula el 2º | E61: B37424850 | F61: AMTELTILS | G61: 50 | H61: no
B62: cristina tienda | C62: mayo | D62: error de tramitacion en el domicilio de instalación (Y07) | E62: 07820312J | G62: 50 | H62: no | I62: si
B63: cristina tienda | C63: mayo | D63: error de tramitacion en el domicilio de instalación (Y07) | E63: 07820312J | G63: 50 | H63: no | I63: si
B64: Higinio | C64: Junio | D64: cliente ilocalizable (N11) | E64: 70908370Z | G64: 50 | H64: NO | I64: SI
B65: Toñi | C65: Julio | D65: Cliente no ha pedidio nada N02 | E65: 7892038W | G65: 200 | H65: no | I65: si
B66: toni | C66: julio | D66: Cliente no ha pedidio nada N02 | E66: 06517374W | F66: no tenemos documentacion | G66: 200 | H66: no | I66: SI
B67: estacion | C67: septiembre | D67: por teminal perdido | F67: j5 (356258079172809) | G67: 138.98 | H67: no | I67: si
B68: peñaranda | C68: septiembre | D68: por teminal perdido | F68: huawei Y5 (869622027924266) | G68: 62.06 | H68: no | I68: si
B69: Diego | C69: julio | D69: Mala info comercial sobre características del P/S | E69: B37323789 | F69: MEVA Y LLORENTE | G69: 50 | H69: no
B70: LUIS | C70: JULIO | D70: IMPORTE USO INDEBIDO/FRAUDE ALTA | E70: 06522860Z | F70: EN MOVISTAR CONTATO | G70: 100 | H70: no
B71: TOÑI | C71: 42506 | D71: JOAQUINA (CLIENTE NO APARECE) | E71: 07859072H | F71: VALIJA | G71: 50 | H71: NO | I71: si
B72: TOÑI | C72: 42522 | D72: 606108174 | E72: 27841223E | F72: VALIJA LO ANULO EL CLIENTE | G72: 50 | H72: NO
B73: Luis | C73: Marzo | D73: Cliente ilocalizable | E73: 09700805A | F73: Maria Teresa Garcia Vela | G73: 50 | H73: NO | I73: NO
B74: LUIS | C74: 42541 | D74: Cliente ilocalizable | E74: 0007856971X | F74: se le instaló con el mismo número de contacto | G74: 50 | H74: SI
B75: LUIS | C75: 42543 | D75: Cliente ilocalizable | E75: 0071060213B | F75: cliente se cambió de domicilio | G75: 50 | H75: SI
B76: LUIS | C76: 42543 | D76: Cliente ilocalizable | E76: 0071060213B | F76: cliente se cambió de domicilio | G76: 50 | H76: SI
B77: FFVV | C77: 42594 | D77: Error de tramitación en P/S | E77: 00A37047354 | F77: Cartonajes Fervi(Cloud) | G77: 50 | H77: pasado correo a Juan antonio y Angel Luis
B78: FFVV | C78: 42594 | D78: Error de tramitación en P/S | E78: 00A37047354 | F78: Cartonajes Fervi(Cloud) | G78: 50 | H78: pasado correo a Juan antonio y Angel Luis
B79: TOÑI | C79: 42522 | D79: DEDUCCION POR PERDIDA | E79: 45036736E | F79: 606230569 no enviado | G79: 50 | H79: no | I79: si
B80: FFVV | C80: 42539 | D80: DEDUCCION POR PERDIDA | E80: 07956327Y | F80: 629774261 enviado ok | G80: 50 | H80: si
B81: MARTA | C81: 42549 | D81: DEDUCCION POR PERDIDA | E81: 06995546G | F81: 618165920 se anuló | G81: 50 | H81: si
B82: CARMEN | C82: 42541 | D82: DEDUCCION POR INCIDENCIA | E82: 07784213R | F82: 608207658 enviado ok | G82: 30 | H82: si
B83: TOÑI | C83: 42522 | D83: DEDUCCION POR PERDIDA | E83: 27841223E | F83: 606108174 baja el mismo día | G83: 50 | H83: si
B84: CARMEN | C84: 42531 | D84: DEDUCCION POR INCIDENCIA | E84: 07959335R | F84: 646695040 enviado ok | G84: 30 | H84: si
B85: MARTA | C85: 42528 | D85: DEDUCCION POR PERDIDA | E85: 70902316D | F85: 620013874 enviado ok | G85: 50 | H85: si
B86: MARTA | C86: 42544 | D86: DEDUCCION POR PERDIDA | E86: 07857578L | F86: 646252377 Se anuló | G86: 50 | H86: si
B87: Carmen | C87: 42555 | D87: Mala info comercial sobre características del P/S | E87: 0007789711W | F87: Pidió ADSL y no habia pares pq es una urbanización y( tardaron mucho en llamarle de nuevo) le llamaron a finales de julio y la cliente ya no lo quería pq solo está ahí en verano. Estan firmados todos los contratos. | G87: 50 | H87: si
B88: Marta | C88: 42579 | D88: Error de tramitación en el domicilio de instalación | E88: 00X2259452R | G88: 50 | H88: si
B89: Marta | C89: 42579 | D89: Error de tramitación en el domicilio de instalación | E89: 00X2259452R | G89: 50 | H89: si
B90: FFVV | C90: 42578 | D90: Error de tramitación por error en aplicación del procedimiento | E90: 00B37299054 | F90: Proarci (cloud) | G90: 50 | H90: pasado correo a Juan antonio y Angel Luis
B91: FFVV | C91: 42571 | D91: Mala info comercial sobre características del P/S | E91: 00Q3768438H | F91: IES Guijuelo (Cloud) | G91: 50 | H91: pasado correo a Juan antonio y Angel Luis
B92: FFVV | C92: 42573 | D92: Mala info comercial sobre características del P/S | E92: 00B37323789 | G92: 50
B93: FFVV | C93: 42559 | D93: Error de tramitación en P/S | E93: 00B37278454 | F93: Sersa Veterinarios (Cloud) | G93: 50 | H93: pasado correo a Juan antonio y Angel Luis
B94: FFVV | C94: 42594 | D94: Error de tramitación en P/S | E94: 00A37047354 | F94: Cartonajes Fervi(Cloud) | G94: 50 | H94: pasado correo a Juan antonio y Angel Luis
B95: FFVV | C95: 42594 | D95: Error de tramitación en P/S | E95: 00A37047354 | F95: Cartonajes Fervi(Cloud) | G95: 50 | H95: pasado correo a Juan antonio y Angel Luis
B96: ffvv | C96: 42625 | D96: Cliente ilocalizable | E96: 00Y0687170J | F96: Phone Factory | G96: 50
B97: Cristina HS | C97: 42636 | D97: Error de tramitación en el domicilio de instalación | E97: 0052413720D | G97: 50
B98: Carlos | C98: 42637 | D98: Cliente ilocalizable | E98: 0070880993F | F98: SE pide primero con el telefono de contacto que nos da el cliente se vuelve a tramitar con otro telefono que nos da el cliente y se instala. | G98: 50 | H98: si
B99: Marta | C99: 42616 | D99: Error de tramitación en P/S | E99: 0007801911N | F99: Esta reformulado por caol pq se tramito como fibra y como no se podia instalar lo pasaron a cobre | G99: 50 | H99: si
B100: Luis | C100: 42649 | D100: Error de tramitación en el domicilio de instalación | E100: 00B37454824 | F100: Se tramito dos veces y no se instaló porque el vecino no le dejo atravesar su nave | G100: 50 | H100: si
B101: luis | C101: 42669 | D101: Error de tramitación en el domicilio de instalación | E101: 00B37454824 | F101: Se tramito dos veces y no se instaló porque el vecino no le dejo atravesar su nave | G101: 50 | H101: si
B102: Luis | C102: 42649 | D102: Error de tramitación en P/S | E102: 0046324728Z | F102: El cliente no nos informó que quería la TV por parabolica y se tramito normal al llegar el instalador la rechazo porque quería parabolica | G102: 50 | H102: si
...
