Workbook

Sheet Retrospectiva Creditos
A1: ='Liquidez Angel Luis'!B2 -> A FECHA 4 de Mayo 2026 | B1: 2008 | C1: 2009 | D1: 2010 | E1: 2011 | F1: 2012 | G1: 2013 | H1: 2014 | I1: 2015 | J1: 2016 | K1: 2017 | L1: 2018 | M1: 2019 | N1: 2020 | O1: 2021 | P1: 2022 | Q1: 2023 | R1: 2024 | S1: 2025 | T1: 2026
A2: Línea de Credito + Cuenta Empresa Santander | F2: -109844 | G2: -109844 | H2: -109844 | I2: -139789 | J2: -150053 | K2: -125695 | L2: -159432.82 | M2: -180558.71 | N2: -170057.72 | O2: -178953.32 | P2: -119518 | Q2: 37398.15 | R2: -37500 | S2: -20000 | T2: -88000
A3: Cuenta Corriente Empresa Unicaja | O3: 2006.78 | P3: 5476.45 | Q3: 4250.21 | R3: 6700 | S3: 605.78 | T3: 0
A4: 1º ICO de Unicaja (ES58 2103 2210 7605 5010 0648) | N4: -146212.72 | O4: -96041.78 | P4: 0 | Q4: 0 | R4: 0 | S4: 0 | T4: 0
A5: Deposito que me devuelven al final del préstamo Iberabal | L5: 45293.46 | M5: 10437.26 | N5: 3500.91 | O5: 2970 | P5: 2970 | Q5: 2970 | R5: 0 | S5: 0 | T5: 0
A6: 2º ICO de Unicaja (ES4821032210710550100782) | O6: -5540 | P6: 0 | Q6: 2.17 | R6: 0 | S6: 0 | T6: 0
A7: Impuestos Hacienda IVA, etc | B7: -101127.89 | C7: -101127.89 | D7: -101127.89 | E7: -101127.89 | F7: -101127.89 | G7: -101127.89 | H7: -101127.89 | I7: -101127.89 | J7: -66650.09 | K7: -83625.44 | L7: -88603.68 | M7: -86514.63 | N7: -67297 | O7: -35000 | P7: -49357 | Q7: -59231.63 | R7: -30000 | S7: -30000 | T7: 0
A8: Aplazamiento Hacienda ó Banco AHORA (Tito) | G8: -17500 | H8: -17500 | I8: -17500 | J8: -25009 | K8: -10000 | L8: -40000 | M8: -60000 | N8: 6345 | O8: 0 | P8: 0 | Q8: 0 | R8: 0 | S8: 0 | T8: 0
A9: Prestamo de mis Padres | G9: -30000 | H9: -30000 | I9: -30000 | J9: -24000 | K9: -12000 | L9: 0 | M9: 0 | N9: 0 | O9: 0 | P9: 0 | Q9: 0 | R9: 0 | S9: 0 | T9: 0
A10: Pago Multa Hacienda (descontado la devolución) | J10: -73079 | K10: 0 | L10: 0 | M10: 0 | N10: 0 | O10: 0 | P10: 0 | Q10: 0 | R10: 0 | S10: 0 | T10: 0
A11: Despidos Graci, Mª José, Higinio | K11: -34000 | L11: 0 | M11: 0 | N11: 0 | O11: 0 | P11: 0 | Q11: 0 | R11: 0 | S11: 0 | T11: 0
A12: Inversión Oficinas FFVV + Tiendas + TINTARED | K12: -81203 | L12: 0 | M12: 0 | N12: 0 | O12: 0 | P12: 0 | Q12: 0 | R12: 0 | S12: 0 | T12: 0
A13: Credito Tito Piso C/ Vergara (Engloba otros prestamos) | B13: -760404.38 | C13: -448520.88 | D13: -396289.4 | E13: -319620.98 | F13: -232943.62 | G13: -201512.6 | H13: -169995.78 | I13: -128403.06 | J13: -86727.94 | K13: -47779.63 | L13: -15877.57 | M13: 0 | N13: 0 | O13: 0 | P13: 0 | Q13: 0 | R13: 0 | S13: 0 | T13: 0
A14: Crédito a Micro Infor (Tito) | K14: -80000 | L14: -51662.67 | M14: -46957.36 | N14: 0 | O14: -145000 | P14: -235000 | Q14: -200000 | R14: -235000 | S14: -305000 | T14: -304500
A15: Credito Empresa Piso C/ Vergara y Otros (Tito) | B15: -123708.33 | C15: -299827.7 | D15: -235511.05 | E15: -134712.46 | F15: -125972.94 | G15: -116945.11 | H15: -107619.47 | I15: -91174.52 | J15: -78931.51 | K15: -55965.66 | L15: -39836.56 | M15: 0 | N15: 0 | O15: 0 | P15: 0 | Q15: 0 | R15: 0 | S15: 0 | T15: 0
A16: TOTAL CREDITOS + IMPUESTOS | B16: =SUM(B2:B15) -> -985240.6 | C16: =SUM(C2:C15) -> -849476.47 | D16: =SUM(D2:D15) -> -732928.34 | E16: =SUM(E2:E15) -> -555461.33 | F16: =SUM(F2:F15) -> -569888.45 | G16: =SUM(G2:G15) -> -576929.6 | H16: =SUM(H2:H15) -> -536087.14 | I16: =SUM(I2:I15) -> -507994.47 | ... T16: =SUM(T2:T15) -> -392500
A17: Stock MoviStar + Accesorios | B17: 40000 | C17: 40000 | D17: 40000 | E17: 40000 | F17: 40000 | G17: 40000 | H17: 40000 | I17: 45000 | J17: 41118 | K17: 69446 | L17: 43130 | M17: 62221 | N17: 65219 | O17: 115638 | P17: 87406 | Q17: 81572.39 | R17: 79943.83 | S17: 89883.27 | T17: 96538
A18: Deuda a Zeleris | Q18: -123551.03 | R18: -68000 | S18: -82000 | T18: -87000
A19: Stock MovilFree + Accesorios | B19: 9000 | C19: 9000 | D19: 9000 | E19: 9000 | F19: 9000 | G19: 9000 | H19: 9000 | I19: 9000 | J19: 9000 | K19: 12000 | L19: 12000 | M19: 12816 | N19: 10756 | O19: 10756 | P19: 10756 | Q19: 10756 | R19: 10756 | S19: 10756 | T19: 10756
A20: Debe MoviStar | B20: 96826 | C20: 96826 | D20: 96826 | E20: 96826 | F20: 96826 | G20: 96826 | H20: 97259 | I20: 97259 | J20: 83471 | K20: 90909 | L20: 100000 | M20: 100000 | N20: 120000 | O20: 120000 | P20: 120000 | Q20: 120000 | R20: 120000 | S20: 140000 | T20: 140000
A21: A FAVOR | B21: 120000 | C21: 120000 | D21: 120000 | E21: 120000 | F21: =SUM(F17:F20) -> 145826 | G21: =SUM(G17:G20) -> 145826 | H21: =SUM(H17:H20) -> 146259 | I21: =SUM(I17:I20) -> 151259 | J21: =SUM(J17:J20) -> 133589 | K21: =SUM(K17:K20) -> 172355 | L21: =SUM(L17:L20) -> 155130 | M21: =SUM(M17:M20) -> 175037 | ... T21: =SUM(T17:T20) -> 160294
A22: TOTAL DEVE MOVISTAR + CREDITOS + IMPUESTOS + STOCK | B22: =B16+B21 -> -865240.6 | C22: =C16+C21 -> -729476.47 | D22: =D16+D21 -> -612928.34 | E22: =E16+E21 -> -435461.33 | F22: =F16+F21 -> -424062.45 | G22: =G16+G21 -> -431103.6 | H22: =H16+H21 -> -389828.14 | I22: =I16+I21 -> -356735.47 | ... T22: =T16+T21 -> -232206
A23: Valor EMPRESA | B23: 360000 | C23: 360000 | D23: 340000 | E23: 340000 | F23: 340000 | G23: 340000 | H23: 340000 | I23: 340000 | J23: 340000 | K23: 450000 | L23: 450000 | M23: 450000 | N23: 450000 | O23: 450000 | P23: 450000 | Q23: 529770 | R23: 529770 | S23: 529770 | T23: 529770
A24: VALOR DE EMPRESA CON BALANCE DE SITUACIÓN | B24: =B23+B22 -> -505240.6 | C24: =C23+C22 -> -369476.47 | D24: =D23+D22 -> -272928.34 | E24: =E23+E22 -> -95461.33 | F24: =F23+F22 -> -84062.45 | G24: =G23+G22 -> -91103.6 | H24: =H23+H22 -> -49828.14 | I24: =I23+I22 -> -16735.47 | ... T24: =T23+T22 -> 297564
A25: Plan de Pensiones | I25: 8002.8 | J25: 15996.75 | K25: 23940.34 | L25: 31053 | M25: 40321 | N25: 47912.89 | O25: 51104.07 | P25: 48608.25 | Q25: ='Liquidez Angel Luis'!M9 -> 52052.21 | R25: ='Liquidez Angel Luis'!O9 -> 55513.31 | S25: ='Liquidez Angel Luis'!Q9 -> 58106.23 | T25: ='Liquidez Angel Luis'!S9 -> 58622.63
A26: En Cuentas y Caja | M26: 277824.52 | N26: 340291.12 | O26: 5736.39 | P26: 51922.59 | Q26: ='Liquidez Angel Luis'!M4+'Liquidez Angel Luis'!M5 -> 28913.56 | R26: ='Liquidez Angel Luis'!O4+'Liquidez Angel Luis'!O5 -> 51226.17 | S26: ='Liquidez Angel Luis'!Q4+'Liquidez Angel Luis'!Q5 -> 50868 | T26: ='Liquidez Angel Luis'!S4+'Liquidez Angel Luis'!S5 -> 73107.59
A27: En prestamos a la Empresa | M27: 106957.36 | N27: 0 | O27: 145000 | P27: 235000 | Q27: ='Liquidez Angel Luis'!M12 -> 200000 | R27: ='Liquidez Angel Luis'!O12 -> 235000 | S27: ='Liquidez Angel Luis'!Q12 -> 305000 | T27: ='Liquidez Angel Luis'!S12 -> 304500
A28: En Prestamos (Hipoteca Campoamor) | N28: -77979.81 | O28: -69841.83 | P28: -119033.73 | Q28: ='Liquidez Angel Luis'!M19+'Liquidez Angel Luis'!M20 -> 0 | R28: ='Liquidez Angel Luis'!O19+'Liquidez Angel Luis'!O20 -> 0 | S28: ='Liquidez Angel Luis'!Q19+'Liquidez Angel Luis'!Q20 -> 0 | T28: ='Liquidez Angel Luis'!S19+'Liquidez Angel Luis'!S20 -> 0
A29: Pisos Campoamor, Recreo y Villaviciosa | N29: 194783.55 | O29: 473679.24 | P29: 476719.24 | Q29: 476719.24 | R29: 476719.24 | S29: 612000 | T29: 612000
A30: Pisos Principe de Vergara + Independencia | B30: 955000 | C30: 955000 | D30: 955000 | E30: 955000 | F30: 955000 | G30: 955000 | H30: 955000 | I30: 955000 | J30: 955000 | K30: 955000 | L30: 955000 | M30: 575000 | N30: 575000 | O30: 575000 | P30: 575000 | Q30: 575000 | R30: 575000 | S30: 670000 | T30: 670000
A31: Valor Coche | B31: 50000 | C31: 50000 | D31: 60000 | E31: 30000 | F31: 28000 | G31: 26000 | H31: 24000 | I31: 22000 | J31: 20000 | K31: 18000 | L31: 16000 | M31: 71500 | N31: 71500 | O31: 71500 | P31: 52000 | Q31: 41322 | R31: 88000 | S31: 70000 | T31: 70000
A32: PATRIMONIO PERSONAL | B32: =SUM(B25:B31) -> 1005000 | C32: =SUM(C25:C31) -> 1005000 | D32: =SUM(D25:D31) -> 1015000 | E32: =SUM(E25:E31) -> 985000 | F32: =SUM(F25:F31) -> 983000 | G32: =SUM(G25:G31) -> 981000 | H32: =SUM(H25:H31) -> 979000 | I32: =SUM(I25:I31) -> 985002.8 | ... T32: =SUM(T25:T31) -> 1788230.2
A33: Patrimonio Incluyendo valor Empresa con Balance de Situación | B33: =B32+B24 -> 499759.4 | C33: =C32+C24 -> 635523.53 | D33: =D32+D24 -> 742071.66 | E33: =E32+E24 -> 889538.67 | F33: =F32+F24 -> 898937.55 | G33: =G32+G24 -> 889896.4 | H33: =H32+H24 -> 929171.86 | I33: =I32+I24 -> 968267.33 | ... T33: =T32+T24 -> 2085794.2
A34: Ganancias por Año | B34: 0 | C34: =C33-B33 -> 135764.13 | D34: =D33-C33 -> 106548.13 | E34: =E33-D33 -> 147467.01 | F34: =F33-E33 -> 9398.88 | G34: =G33-F33 -> -9041.15 | H34: =H33-G33 -> 39275.46 | I34: =I33-H33 -> 39095.47 | J34: =J33-I33 -> -8132.12 | ... T34: =T33-S33 -> -14195.06
V38: -200000
V39: 185461.39

Sheet Liquidez Angel Luis
B2: A FECHA 4 de Mayo 2026 | C2: Importe Año 2018 | D2: Diferencia | E2: Importe Año 2019 | F2: Diferencia | G2: Importe Año 2020 | H2: Diferencia | I2: Importe Año 2021 | J2: Diferencia | K2: Importe Año 2022 | L2: Diferencia | M2: Importe Año 2023 | N2: Diferencia | O2: Importe Año 2024 | P2: Diferencia | Q2: Importe Año 2025 | R2: Diferencia | S2: Importe Año 2026 | T2: Diferencia
B3: Banco Santander Cuenta Personal | C3: 252642.43 | D3: 0 | E3: 277824.52 | F3: =E3-C3 -> 25182.09 | G3: 100918.01 | H3: =G3-E3 -> -176906.51 | I3: 0 | J3: =I3-G3 -> -100918.01 | K3: 0 | L3: =K3-I3 -> 0 | M3: 0 | N3: =M3-K3 -> 0 | O3: 0 | P3: =O3-M3 -> 0 | Q3: 0 | R3: =Q3-O3 -> 0 | S3: 0 | T3: =S3-Q3 -> 0
B4: Unicaja Cuenta Personal | C4: 0 | D4: 0 | E4: 0 | F4: 0 | G4: 239373.11 | H4: =G4-E4 -> 239373.11 | I4: 5736.39 | J4: =I4-G4 -> -233636.72 | K4: 50722.59 | L4: =K4-I4 -> 44986.2 | M4: 27713.56 | N4: =M4-K4 -> -23009.03 | O4: 47000 | P4: =O4-M4 -> 19286.44 | Q4: 36368 | R4: =Q4-O4 -> -10632 | S4: 61107.59 | T4: =S4-Q4 -> 24739.59
B5: Caja Metálico | C5: 18000 | D5: 0 | E5: 1200 | F5: =E5-C5 -> -16800 | G5: 1200 | H5: =G5-E5 -> 0 | I5: 1200 | J5: =I5-G5 -> 0 | K5: 1200 | L5: =K5-I5 -> 0 | M5: 1200 | N5: =M5-K5 -> 0 | O5: 4226.17 | P5: =O5-M5 -> 3026.17 | Q5: 14500 | R5: =Q5-O5 -> 10273.83 | S5: 12000 | T5: =S5-Q5 -> -2500
B6: Renta Piso Avenida de Campoamor | C6: 0 | D6: 0 | E6: 0 | F6: 0 | G6: 0 | H6: =G6-E6 -> 0 | I6: 0 | J6: =I6-G6 -> 0 | K6: 0 | L6: =K6-I6 -> 0 | M6: 0 | N6: =M6-K6 -> 0 | O6: 0 | P6: =O6-M6 -> 0 | Q6: 0 | R6: =Q6-O6 -> 0 | S6: 9075 | T6: =S6-Q6 -> 9075
B7: Renta Piso Calle Recreo | C7: 0 | D7: 0 | E7: 0 | F7: =E7-C7 -> 0 | G7: 0 | H7: =G7-E7 -> 0 | I7: 0 | J7: =I7-G7 -> 0 | K7: 0 | L7: =K7-I7 -> 0 | M7: 0 | N7: =M7-K7 -> 0 | O7: 0 | P7: =O7-M7 -> 0 | Q7: 0 | R7: =Q7-O7 -> 0 | S7: 6975 | T7: =S7-Q7 -> 6975
B8: Renta Piso Calle Villaviciosa | C8: 0 | D8: 0 | E8: 0 | F8: =E8-C8 -> 0 | G8: 0 | H8: =G8-E8 -> 0 | I8: 0 | J8: =I8-G8 -> 0 | K8: 0 | L8: =K8-I8 -> 0 | M8: 0 | N8: =M8-K8 -> 0 | O8: 0 | P8: =O8-M8 -> 0 | Q8: 0 | R8: =Q8-O8 -> 0 | S8: 6585.26 | T8: =S8-Q8 -> 6585.26
B9: Plan de Pensiones | C9: 31053 | D9: 0 | E9: 40321 | F9: =E9-C9 -> 9268 | G9: 47912.89 | H9: =G9-E9 -> 7591.89 | I9: 51104.07 | J9: =I9-G9 -> 3191.18 | K9: 48608.25 | L9: =K9-I9 -> -2495.82 | M9: 52052.21 | N9: =M9-K9 -> 3443.96 | O9: 55513.31 | P9: =O9-M9 -> 3461.1 | Q9: 58106.23 | R9: =Q9-O9 -> 2592.92 | S9: 58622.63 | T9: =S9-Q9 -> 516.4
B10: Prestamo mio a la Empresa del Piso | C10: 39170 | D10: 0 | E10: 0 | F10: =E10-C10 -> -39170 | G10: 0 | H10: =G10-E10 -> 0 | I10: 0 | J10: =I10-G10 -> 0 | K10: 0 | L10: =K10-I10 -> 0 | M10: 0 | N10: =M10-K10 -> 0 | O10: 0 | P10: =O10-M10 -> 0 | Q10: 0 | R10: =Q10-O10 -> 0 | S10: 0 | T10: =S10-Q10 -> 0
B11: Prestamo mio a la Empresa | C11: 49457.36 | D11: 0 | E11: 21957.36 | F11: =E11-C11 -> -27500 | G11: 0 | H11: =G11-E11 -> -21957.36 | I11: 0 | J11: =I11-G11 -> 0 | K11: 0 | L11: =K11-I11 -> 0 | M11: 0 | N11: =M11-K11 -> 0 | O11: 0 | P11: =O11-M11 -> 0 | Q11: 0 | R11: =Q11-O11 -> 0 | S11: 0 | T11: =S11-Q11 -> 0
B12: Prestamo mio a la Empresa Impuestos | C12: 0 | D12: 0 | E12: 60000 | F12: =E12-C12 -> 60000 | G12: 0 | H12: =G12-E12 -> -60000 | I12: 145000 | J12: =I12-G12 -> 145000 | K12: 235000 | L12: =K12-I12 -> 90000 | M12: 200000 | N12: =M12-K12 -> -35000 | O12: 235000 | P12: =O12-M12 -> 35000 | Q12: 305000 | R12: =Q12-O12 -> 70000 | S12: 304500 | T12: =S12-Q12 -> -500
B13: Prestamo mio a la Empresa Fin de Mes | C13: 0 | D13: 0 | E13: 25000 | F13: =E13-C13 -> 25000 | G13: 0 | H13: =G13-E13 -> -25000 | I13: 0 | J13: =I13-G13 -> 0 | K13: 0 | L13: =K13-I13 -> 0 | M13: 0 | N13: =M13-K13 -> 0 | O13: 0 | P13: =O13-M13 -> 0 | Q13: 0 | R13: =Q13-O13 -> 0 | S13: 0 | T13: =S13-Q13 -> 0
B14: Intereses Prestamo a la Empresa | J14: 0 | K14: 0 | L14: 0 | M14: 0 | N14: 0 | O14: 0 | P14: 0 | Q14: 0 | R14: 0 | S14: 13725 | T14: =S14-Q14 -> 13725
B15: Sueldos | C15: 0 | D15: 0 | E15: 0 | F15: =E15-C15 -> 0 | G15: 0 | H15: =G15-E15 -> 0 | I15: 0 | J15: =I15-G15 -> 0 | K15: 0 | L15: =K15-I15 -> 0 | M15: 0 | N15: =M15-K15 -> 0 | O15: 0 | P15: =O15-M15 -> 0 | Q15: 0 | R15: =Q15-O15 -> 0 | S15: 24475 | T15: =S15-Q15 -> 24475
B16: Piso Avenida de Campoamor Nº30, 4ºC | C16: 0 | D16: 0 | E16: 0 | F16: =E16-C16 -> 0 | G16: 165757 | H16: =G16-E16 -> 165757 | I16: 165757 | J16: =I16-G16 -> 0 | K16: 165757 | L16: =K16-I16 -> 0 | M16: 165757 | N16: =M16-K16 -> 0 | O16: 165757 | P16: =O16-M16 -> 0 | Q16: 165757 | R16: =Q16-O16 -> 0 | S16: 165757 | T16: =S16-Q16 -> 0
B17: Piso Calle Recreo Nº13, 2º | C17: 0 | D17: 0 | E17: 0 | F17: =E17-C17 -> 0 | G17: 0 | H17: =G17-E17 -> 0 | I17: 100440 | J17: =I17-G17 -> 100440 | K17: 100440 | L17: =K17-I17 -> 0 | M17: 100440 | N17: =M17-K17 -> 0 | O17: 100440 | P17: =O17-M17 -> 0 | Q17: 100440 | R17: =Q17-O17 -> 0 | S17: 100440 | T17: =S17-Q17 -> 0
B18: Piso Calle Villaviciosa Nº28-32, 2A | C18: 0 | D18: 0 | E18: 0 | F18: =E18-C18 -> 0 | G18: 0 | H18: =G18-E18 -> 0 | I18: 157846 | J18: =I18-G18 -> 157846 | K18: 157846 | L18: =K18-I18 -> 0 | M18: 157846 | N18: =M18-K18 -> 0 | O18: 157846 | P18: =O18-M18 -> 0 | Q18: 157846 | R18: =Q18-O18 -> 0 | S18: 157846 | T18: =S18-Q18 -> 0
B19: Unicaja Hipoteca Campoamor | C19: 0 | D19: 0 | E19: 0 | F19: =E19-C19 -> 0 | G19: -77979.81 | H19: =G19-E19 -> -77979.81 | I19: -69841.83 | J19: =I19-G19 -> 8137.98 | K19: -63633.63 | L19: =K19-I19 -> 6208.2 | M19: 0 | N19: =M19-K19 -> 63633.63 | O19: 0 | P19: =O19-M19 -> 0 | Q19: 0 | R19: =Q19-O19 -> 0 | S19: 0 | T19: =S19-Q19 -> 0
B20: Unicaja Hipoteca Campoamor | C20: 0 | D20: 0 | E20: 0 | F20: =E20-C20 -> 0 | G20: 0 | H20: 0 | I20: 0 | J20: =I20-G20 -> 0 | K20: -55400.1 | L20: =K20-I20 -> -55400.1 | M20: 0 | N20: =M20-K20 -> 55400.1 | O20: 0 | P20: =O20-M20 -> 0 | Q20: 0 | R20: =Q20-O20 -> 0 | S20: 0 | T20: =S20-Q20 -> 0
B21: Hacienda | C21: 0 | D21: 0 | E21: 0 | F21: =E21-C21 -> 0 | G21: 0 | H21: =G21-E21 -> 0 | I21: 0 | J21: =I21-G21 -> 0 | K21: 0 | L21: =K21-I21 -> 0 | M21: 0 | N21: =M21-K21 -> 0 | O21: 0 | P21: =O21-M21 -> 0 | Q21: 0 | R21: =Q21-O21 -> 0 | S21: 0 | T21: =S21-Q21 -> 0
B22: Importes | C22: =SUM(C3:C21) -> 390322.79 | D22: 0 | E22: =SUM(E3:E21) -> 426302.88 | F22: =SUM(F3:F21) -> 35980.09 | G22: =SUM(G3:G21) -> 477181.2 | H22: =SUM(H3:H21) -> 50878.32 | I22: =SUM(I3:I21) -> 557241.63 | J22: =SUM(J3:J21) -> 80060.43 | K22: =SUM(K3:K21) -> 640540.11 | L22: =SUM(L3:L21) -> 83298.48 | ... T22: =SUM(T3:T21) -> 83091.25
C23: 2018 | E23: Diferencia del 2018 al 2019 | G23: Diferencia del 2019 al 2020 | I23: Diferencia del 2020 al 2021 | K23: Diferencia del 2021 al 2022 | M23: Diferencia del 2022 al 2023 | O23: Diferencia del 2022 al 2023 | Q23: Diferencia del 2022 al 2023 | S23: Diferencia del 2022 al 2023
B24: TOTAL | C24: 0 | E24: =E22-C22 -> 35980.09 | G24: =G22-E22 -> 50878.32 | I24: =I22-G22 -> 80060.43 | K24: =K22-I22 -> 83298.48 | M24: =M22-K22 -> 64468.66 | O24: =O22-M22 -> 60773.71 | Q24: =Q22-O22 -> 72234.75 | S24: =S22-Q22 -> 83091.25

Sheet Prestamos
B2: 2023 MAYO Banco Santander | E2: Unicaja (Hipoteca Campoamor) 19 Agosto 2020 | H2: Unicaja (Hipoteca Villaviciosa) 23 Marzo 2022 | K2: Iberabal 23 julio 2020 | N2: Iberabal 21 Diciembre 2021
B3: Fechas de Vencimiento | C3: 44787 | E3: Fechas de Vencimiento | F3: 46983 | H3: Fechas de Vencimiento | I3: 43546 | K3: Fechas de Vencimiento | L3: 43668 | N3: Fechas de Vencimiento | O3: 44185
B4: Interes Mensual | C4: 0.03 | E4: Fecha proxima subida | F4: 43695 | H4: Fecha proxima subida | I4: 43546 | K4: Fecha proxima subida | L4: 43487 | N4: Fecha proxima subida | O4: 43454
B5: Interes No Disponibilidad | C5: 0.0035 | E5: Prestamo | F5: 64628.45 | H5: Prestamo | I5: 76371.34 | K5: Prestamo | L5: 50000 | N5: Prestamo | O5: 100000
B6: Prestamo | C6: 200000 | E6: Interes Mensual | F6: 0.01952 | H6: Interes Mensual | I6: 0.0199 | K6: Interes Mensual | L6: 0.0296 | N6: Interes Mensual | O6: 0.0434
B7: Media Importe Disponible | C7: 50000 | E7: Intereses Anuales | F7: =F5*F6 -> 1261.5473 | H7: Intereses Anuales | I7: =I5*I6 -> 1519.7897 | K7: Intereses Anuales | L7: =L5*L6 -> 1480 | N7: Intereses Anuales | O7: =O5*O6 -> 4340
B8: Media Importe NO Disponible | C8: 150000 | E8: Intereses Mensuales | F8: =F7/12 -> 105.12895 | H8: Intereses Mensuales | I8: =I7/12 -> 126.64914 | K8: Intereses Mensuales | L8: =L7/12 -> 123.33333 | N8: Intereses Mensuales | O8: =O7/12 -> 361.66667
B9: Media Importe Disponible | C9: =(C7*C4)/12 -> 125
B10: Media Importe NO Disponible | C10: =(C5*C8)/12 -> 43.75 | E10: Unicaja (Hipoteca Campoamor) 19 Agosto 2022
B11: TOTAL ANUAL | C11: =SUM(C9:C10)*12 -> 2025 | E11: Fechas de Vencimiento | F11: 47713
B12: MEDIA MENSUAL | C12: =C11/12 -> 168.75 | E12: Fecha proxima subida | F12: 43695
E13: Prestamo | F13: 64628.45
E14: Interes Mensual | F14: 0.01952
E15: Intereses Anuales | F15: =F13*F14 -> 1261.5473
E16: Intereses Mensuales | F16: =F15/12 -> 105.12895

Sheet Rentabilidad PISOS y PEx 2022
B2: 2022 | C2: Pagos | D2: Por Bloques | F2: Calculo Rentabilidad Alquiler PISOS
B3: Pago final de Calefacción por Gas C/ Recreo | C3: 1781 | D3: =C3 -> 1781 | F3: Piso | G3: Inversión | H3: Interes | I3: Ganancia | J3: Alquiler Neto | K3: Comunidad | L3: Total Alquiler
B4: Dentista (Implante dental, muela de abajo a la izquierda) | C4: 1390 | D4: =C4 -> 1390 | F4: Avda Campoamor | G4: 194573.55 | H4: 0.0432 | I4: =L4-K4 -> 700 | J4: =G4*H4/12 -> 700.46478 | K4: 125 | L4: 825
B5: Dentista (6 Carillas de Porcelana) | C5: 3300 | D5: =C5 -> 3300 | F5: C/ Recreo, 13 | G5: 124299 | H5: 0.05545 | I5: =L5-K5 -> 575 | J5: =G5*H5/12 -> 574.36496 | K5: 50 | L5: 625
B6: Mosquiteras casa Principe de Vergara | C6: 799.04 | D6: =C6 -> 799.04 | F6: C/ Villaviciosa, 28 | G6: 157846 | H6: 0.0344 | I6: =L6-K6 -> 452.6 | J6: =G6*H6/12 -> 452.49187 | K6: 115 | L6: 567.6
B7: Aire Acondicionado de mi Madre | C7: 3150 | D7: =C7 -> 3150
D9: =C9 -> 0 | F9: Pago en A | G9: IVA 8% | H9: B | I9: Compra muebles, etc
D10: =C10 -> 0 | F10: 185000 | G10: =F10*8% -> 14800 | H10: 10000 | I10: 10200
D11: =C11 -> 0
D12: =C12 -> 0
D13: =C13 -> 0
D14: =C14 -> 0
D15: =C15 -> 0
B16: TOTAL | C16: =SUM(C3:C15) -> 10420.04 | D16: =SUM(D3:D15) -> 10420.04

Sheet Pagos Extras 2021
B2: 2021 | C2: Pagos | D2: Por Bloques | F2: Calculo Rentabilidad Alquiler PISOS
B3: Obras Calle Recreo IVA Incluido | C3: 7671.4 | D3: =C3+C4 -> 11259.05 | F3: Piso | G3: Inversión | H3: Interes | I3: Ganancia | J3: Alquiler | K3: Comunidad | L3: Total Alquiler
B4: Ampliación Obras Calle Recreo, Cocina, Baño y enchufes IVA Incluido | C4: 3587.65 | F4: Avda Campoamor | G4: 194573.55 | H4: 0.0354 | I4: =J4-K4 -> 447.98394 | J4: =G4*H4/12 -> 573.99197 | K4: =L4-J4 -> 126.00803 | L4: 700
B5: Mobiliario Jesús Novomar Calle Recreo IVA Incluido | C5: 8377.55 | D5: =C5 -> 8377.55 | F5: C/ Recreo, 13 | G5: 121259.69 | H5: 0.0445 | I5: =J5-K5 -> 349.3427 | J5: =G5*H5/12 -> 449.67135 | K5: =L5-J5 -> 100.32865 | L5: 550
B6: Lamparas y topes para puertas | C6: 217.09 | D6: =SUM(C6:C9) -> 1183.09 | F6: C/ Villaviciosa, 28 | G6: 157846 | H6: 0.0345 | I6: =J6-K6 -> 357.6145 | J6: =G6*H6/12 -> 453.80725 | K6: =L6-J6 -> 96.19275 | L6: 550
B7: Edredones, escoba, recogedor, Fregona, cubo basura y Felpudos | C7: 150
B8: Ajuar (Vajilla, Cazuelas, Sartenes, etc) | C8: 102 | F8: 100000 | G8: =F8*H4 -> 3540 | H8: =AVERAGE(H4:H6) -> 0.038133333
B9: Pago de Cortinas C/Recreo | C9: 714 | F9: 100000 | G9: =F9*H5 -> 4450
B10: Primer Pago de Calefacción por Gas C/ Recreo | C10: 1259 | D10: =C10 -> 1259 | F10: 100000 | G10: =F10*H6 -> 3450
B11: Lavavajillas principe de Vergara | C11: 575 | D11: =C11 -> 575
B12: Pago Nuevos contadores Calefacción AV/ Campoamor | C12: 671.88 | D12: =C12 -> 671.88 | F12: 194573.55 | G12: =F12*H4 -> 6887.9037 | H12: =AVERAGE(H4:H6) -> 0.038133333
B13: Microcirujia Capilar | C13: 4000 | D13: =C13 -> 4000 | F13: 121259.69 | G13: =F13*H5 -> 5396.0562
B14: Pago Villaviciosa en B (5.000€ empresa + 5.000€ me dio mi Madre) | C14: 5000 | D14: =SUM(C14:C15) -> 7046 | F14: 157846 | G14: =F14*H6 -> 5445.687
B15: Muebles salón y Habitación C/ Villaviciosa | C15: 2046
B16: TOTAL | C16: =SUM(C3:C15) -> 34371.57 | D16: =SUM(D3:D15) -> 34371.57

Sheet Pagos Extras 2020
B2: 2020 | C2: Pagos | D2: Por Bloques
B3: Despido de Angel | C3: 5500 | D3: =C3 -> 5500
B4: Abogado del Erte | C4: 4000 | D4: =C4 -> 4000
B5: Mobiliario de casa Principe de vergara | C5: 13381.59 | D5: =SUM(C5:C6) -> 15030.59
B6: Pintura de Casa Principe de vergara | C6: 1649
B7: Televisión Salón | C7: 6000 | D7: =SUM(C7:C9) -> 12400
B8: Portátil + Grafica RTX 2080Ti + Gafas HP Revert G2 | C8: 5000
B9: Grafica RTX 3090 | C9: 1400
B10: Vacaciones | C10: 4000 | D10: =SUM(C10:C11) -> 7000
B11: Dentista | C11: 3000
B12: Local Auxi Obra, Pintura e Iluminación | C12: 4656 | D12: =SUM(C12:C14) -> 7389
B13: Local Auxiliadora Parket | C13: 1533
B14: Local Auxiliadora Aire acondicionado | C14: 1200
B15: Dinero en B Piso | C15: 8000 | D15: =C15 -> 8000
B16: Obras Campoamor 1 Adelanto IVA Incluido | C16: 8076.75 | D16: =SUM(C16:C18) -> 20295.25
B17: Obras Campoamor 2 Adelanto Iva Incluido | C17: 6050
B18: Obras Campoamor 3 Adelanto PAGO Final Iva Incluido | C18: 6168.5
B19: Campoamor TV + Lamparas | C19: 671 | D19: =SUM(C19:C23) -> 2137.55
B20: Campoamor Cristalero | C20: 140
B21: Campoamor Edredones | C21: 114
B22: Campoamor Articulos de Baño y Lampara | C22: 787.16
B23: Campoamor Cortinas y Estores | C23: 425.39
B24: Mobiliario Jesús Campoamor | C24: 6594 | D24: =C24 -> 6594
B25: TOTAL | C25: =SUM(C3:C24) -> 88346.39 | D25: =SUM(D3:D24) -> 88346.39

Sheet Año 2008 y 2019
A2: DEUDA Año 2007 | B2: DEUDA Año 2008 | C2: DEUDA Año 2009 | D2: Diferencia | E2: DEUDA Año 2010 | F2: Diferencia | G2: DEUDA Año 2011 | H2: Diferencia | I2: DEUDA Año 2012 | J2: Diferencia | K2: DEUDA Año 2013 | L2: Diferencia | M2: DEUDA Año 2014 | N2: Diferencia | O2: Deuda Año 2015 | P2: Diferencia | Q2: Deuda Año 2016 | R2: Diferencia | S2: Deuda Año 2017 | T2: Diferencia | U2: Deuda Año 2018 | V2: Diferencia | W2: Deuda Año 2019 | X2: Diferencia | Y2: A FECHA 31 de ENERO de 2019 | Z2: Interes | AA2: Cuota 2008 | AB2: Cuota 2009 | AC2: Cuota 2010 | AD2: Cuota 2011 | AE2: Cuota 2012 | AF2: Cuota 2013 | AG2: Cuota 2014 | AH2: Cuota 2015 | AI2: Cuota 2016 | AJ2: Cuota 2017 | AK2: Cuota 2018 | AL2: Cuota 2019
A3: 478300 | B3: 478300 | C3: ='Año 2009'!B19 -> 186474.01 | D3: =C3-B3 -> -291825.99 | E3: 176741.71 | F3: =E3-C3 -> -9732.3 | G3: 169396.51 | H3: =G3-E3 -> -7345.2 | I3: 142951.56 | J3: =I3-G3 -> -26444.95 | K3: 134546.8 | L3: =K3-I3 -> -8404.76 | M3: 126495.77 | N3: =M3-K3 -> -8051.03 | O3: 118043.26 | P3: =O3-M3 -> -8452.51 | Q3: 86727.94 | R3: =Q3-O3 -> -31315.32 | S3: 47779.63 | T3: =S3-Q3 -> -38948.31 | U3: 15877.57 | V3: =U3-S3 -> -31902.06 | W3: 0 | X3: =W3-U3 -> -15877.57 | Y3: Aluis Hipoteca Piso Principe de Vergara Banco Popular | Z3: 0.00744 | AA3: 2280.62 | AB3: 843.23 | AC3: 843.23 | AD3: 829.22 | AE3: 718 | AF3: 696.58 | AG3: 674.82 | AH3: 541.84 | AI3: 446.21 | AJ3: 263.21 | AK3: 99.22 | AL3: 83.38
B4: 0 | C4: ='Año 2009'!B24 -> 188287.32 | D4: =C4-B4 -> 188287.32 | E4: 175972.84 | F4: =E4-C4 -> -12314.48 | G4: 134712.46 | H4: =G4-E4 -> -41260.38 | I4: 125972.94 | J4: =I4-G4 -> -8739.52 | K4: 116945.11 | L4: =K4-I4 -> -9027.83 | M4: 107619.47 | N4: =M4-K4 -> -9325.64 | O4: 91174.52 | P4: =O4-M4 -> -16444.95 | Q4: 78931.51 | R4: =Q4-O4 -> -12243.01 | S4: 55965.66 | T4: =S4-Q4 -> -22965.85 | U4: 39836.56 | V4: =U4-S4 -> -16129.1 | W4: 0 | X4: =W4-U4 -> -39836.56 | Y4: Micro Infor Hipoteca Piso Principe de Vergara Banco Popular | Z4: 0.02 | AA4: 0 | AB4: 1329.12 | AC4: 1331.45 | AD4: 1082.7 | AE4: 1082.71 | AF4: 1082.35 | AG4: 1082.35 | AH4: 975.99 | AI4: 900.16 | AJ4: 747.83 | AK4: 747.83 | AL4: 618.38
O5: -8002.8 | P5: =O5-M5 -> -8002.8 | Q5: -15996.75 | R5: =Q5-O5 -> -7993.95 | S5: -23940.34 | T5: =S5-Q5 -> -7943.59 | U5: -31053 | V5: =U5-S5 -> -7112.66 | W5: -32362.7 | X5: =W5-U5 -> -1309.7 | Y5: Plan de Pensiones | Z5: 0.001 | AA5: 0 | AB5: 0 | AC5: 0 | AD5: 0 | AE5: 0 | AF5: 0 | AG5: 0 | AH5: 0 | AI5: 0 | AJ5: 0 | AK5: 0 | AL5: 0
A6: 160000 | B6: 147394.25 | C6: ='Año 2009'!B4 -> 142595.66 | D6: =C6-B6 -> -4798.59 | E6: 138228.93 | F6: =E6-C6 -> -4366.73 | G6: 132881.43 | H6: =G6-E6 -> -5347.5 | I6: 89992.06 | J6: =I6-G6 -> -42889.37 | K6: 66965.8 | L6: =K6-I6 -> -23026.26 | M6: 43500.01 | N6: =M6-K6 -> -23465.79 | O6: 10359.8 | P6: =O6-M6 -> -33140.21 | Q6: 0 | R6: =Q6-O6 -> -10359.8 | S6: 0 | T6: =S6-Q6 -> 0 | U6: 0 | V6: =U6-S6 -> 0 | W6: 0 | X6: =W6-U6 -> 0 | Y6: Angel Luis Chalet CAJA DUERO (Hipoteca Nº 0008.7034126671) TENGO HIPOTECA | Z6: 0.0225 | AA6: 1023.95 | AB6: 1023.95 | AC6: 758.97 | AD6: 768.51 | AE6: 536.41 | AF6: 417.78 | AG6: 286.29 | AH6: 69.16 | AI6: 0 | AJ6: 0 | AK6: 0 | AL6: 0
A7: 105000 | B7: 98634.88 | C7: ='Año 2009'!B11 -> 87451.21 | D7: =C7-B7 -> -11183.67 | E7: 54318.76 | F7: =E7-C7 -> -33132.45 | G7: 17343.04 | H7: =G7-E7 -> -36975.72 | I7: 0 | J7: =I7-G7 -> -17343.04 | K7: 0 | L7: =I7-K7 -> 0 | M7: 0 | N7: =K7-M7 -> 0 | O7: 0 | P7: =M7-O7 -> 0 | Q7: 0 | R7: =M7-Q7 -> 0 | S7: 0 | T7: =O7-S7 -> 0 | U7: 0 | V7: =O7-U7 -> 0 | W7: 0 | X7: =U7-W7 -> 0 | Y7: Angel Luis Chalet CAJA DUERO (Hipoteca Nº 0008.7039621728) TENGO HIPOTECA | Z7: 0.0365 | AA7: 639.86 | AB7: 539.85 | AC7: 315.68 | AD7: 104.32 | AE7: 0 | AF7: 0 | AG7: 0 | AH7: 0 | AI7: 0 | AJ7: 0 | AK7: 0 | AL7: 0
A8: 133000 | B8: 123708.33 | C8: ='Año 2009'!B30 -> 111540.38 | D8: =C8-B8 -> -12167.95 | E8: 59538.21 | F8: =E8-C8 -> -52002.17 | G8: 0 | H8: =G8-E8 -> -59538.21 | I8: 0 | J8: =G8-I8 -> 0 | K8: 0 | L8: =I8-K8 -> 0 | M8: 0 | N8: =K8-M8 -> 0 | O8: 0 | P8: =M8-O8 -> 0 | Q8: 0 | R8: =M8-Q8 -> 0 | S8: 0 | T8: =O8-S8 -> 0 | U8: 0 | V8: =O8-U8 -> 0 | W8: 0 | X8: =U8-W8 -> 0 | Y8: Micro Infor CAJA DUERO (Avalando chalet ASTURIAS) | Z8: 0.035 | AA8: 1114.83 | AB8: 836.81 | AC8: 572.89 | AD8: 0 | AE8: 0 | AF8: 0 | AG8: 0 | AH8: 0 | AI8: 0 | AJ8: 0 | AK8: 0 | AL8: 0
A9: 15025.3 | B9: 15025.3 | C9: ='Año 2009'!B35 -> 12000 | D9: =C9-B9 -> -3025.3 | E9: 9000 | F9: =E9-C9 -> -3000 | G9: 0 | H9: =G9-E9 -> -9000 | I9: 0 | J9: =G9-I9 -> 0 | K9: 0 | L9: =I9-K9 -> 0 | M9: 0 | N9: =K9-M9 -> 0 | O9: 0 | P9: =M9-O9 -> 0 | Q9: 0 | R9: =M9-Q9 -> 0 | S9: 0 | T9: =O9-S9 -> 0 | U9: 0 | V9: =O9-U9 -> 0 | W9: 0 | X9: =U9-W9 -> 0 | Y9: Prestamo de mi Padre | Z9: 0.035 | AA9: 62.61 | AB9: 35 | AC9: 26.25 | AD9: 0 | AE9: 0 | AF9: 0 | AG9: 0 | AH9: 0 | AI9: 0 | AJ9: 0 | AK9: 0 | AL9: 0
A10: 24000 | B10: 21049.95 | C10: 20000 | D10: =C10-B10 -> -1049.95 | E10: 18000 | F10: =E10-C10 -> -2000 | G10: 0 | H10: =E10-G10 -> 18000 | I10: 0 | J10: =G10-I10 -> 0 | K10: 0 | L10: =I10-K10 -> 0 | M10: 0 | N10: =K10-M10 -> 0 | O10: 0 | P10: =M10-O10 -> 0 | Q10: 0 | R10: =M10-Q10 -> 0 | S10: 0 | T10: =O10-S10 -> 0 | U10: 0 | V10: =O10-U10 -> 0 | W10: 0 | X10: =U10-W10 -> 0 | Y10: Piso Calle Independencia (Prestamo Nº 0008.7039621582) TENGO HIPOTECA | AA10: 207.12 | AB10: 143.38 | AC10: 143.38 | AD10: 0 | AE10: 0 | AF10: 0 | AG10: 0 | AH10: 0 | AI10: 0 | AJ10: 0 | AK10: 0 | AL10: 0
A11: =A6+A7+A3+A8+A4+A9+A10 -> 915325.3 | B11: =B6+B7+B3+B8+B4+B9+B10 -> 884112.71 | C11: =C6+C7+C3+C8+C4+C9+C10 -> 748348.58 | D11: =C11-B11 -> -135764.13 | E11: =E6+E7+E3+E8+E4+E9+E10 -> 631800.45 | F11: =E11-C11 -> -116548.13 | G11: =G6+G7+G3+G8+G4+G9+G10 -> 454333.44 | H11: =G11-E11 -> -177467.01 | I11: =I6+I3+I4 -> 358916.56 | J11: =I11-G11 -> -95416.88 | K11: =K6+K3+K4 -> 318457.71 | L11: =K11-I11 -> -40458.85 | M11: =M6+M3+M4 -> 277615.25 | N11: =M11-K11 -> -40842.46 | O11: =SUM(O3:O6) -> 211574.78 | P11: =O11-M11 -> -66040.47 | Q11: =SUM(Q3:Q5) -> 149662.7 | R11: =Q11-O11 -> -61912.08 | S11: =SUM(S3:S5) -> 79804.95 | T11: =S11-Q11 -> -69857.75 | U11: =SUM(U3:U5) -> 24661.13 | V11: =U11-S11 -> -55143.82 | W11: =SUM(W3:W5) -> -32362.7 | X11: =W11-U11 -> -57023.83 | Y11: Cuotas Mensuales | AA11: =SUM(AA3:AA10) -> 5328.99 | AB11: =SUM(AB3:AB10) -> 4751.34 | AC11: =SUM(AC3:AC10) -> 3991.85 | AD11: =SUM(AD3:AD10) -> 2784.75 | AE11: =SUM(AE3:AE10) -> 2337.12 | AF11: =SUM(AF3:AF10) -> 2196.71 | AG11: =SUM(AG3:AG10) -> 2043.46 | AH11: =SUM(AH3:AH10) -> 1586.99 | ... AL11: =SUM(AL3:AL10) -> 701.76
A12: Diferencia del 2000 al 2007 | B12: Diferencia del 2007 al 2008 | C12: Diferencia del 2008 al 2009 | E12: Diferencia del 2009 al 2010 | G12: Diferencia del 2010 al 2011 | I12: Diferencia del 2011 al 2012 | K12: Diferencia del 2012 al 2013 | M12: Diferencia del 2013 al 2014 | O12: Diferencia del 2014 al 2015 | Q12: Diferencia del 2015 al 2016 | S12: Diferencia del 2016 al 2017 | U12: Diferencia del 2017 al 2018 | W12: Diferencia del 2018 al 2019 | Y12: DEUDA ACTUAL Aluis 2016 | AE12: DEUDA ACTUAL Micro InFor 2016
A13: 915325.3 | B13: =B11-A11 -> -31212.59 | C13: =C11-B11 -> -135764.13 | E13: =E11-C11 -> -116548.13 | G13: =G11-E11 -> -177467.01 | I13: =I11-G11 -> -95416.88 | K13: =K11-I11 -> -40458.85 | M13: =M11-K11 -> -40842.46 | O13: =O11-M11 -> -66040.47 | Q13: =Q11-O11 -> -61912.08 | S13: =S11-Q11 -> -69857.75 | U13: =U11-Q11 -> -125001.57 | W13: =W11-U11 -> -57023.83 | Y13: =W3+W5 -> -32362.7 | AE13: =W4 -> 0
W14: Total Deuda | Y14: =Y13+AE13 -> -32362.7
W15: Hacienda | Y15: 3500
W16: Caja Fuerte | Y16: 0
W17: Amortización Prestamo Empresa | Y17: 0
W18: Sueldos Hasta Diciembre | Y18: 22000
W19: Total Deuda | Y19: =Y14-Y15-Y16-Y17-Y18 -> -57862.7

Sheet Año 2000 al 2011
A1: Años 2000 al 2008 | B1: Año 2008 | C1: Año 2009 | D1: Año 2010 | E1: Año 2011 | F1: ACTUALIZADO A FECHA DE 2 de Julio de 2011 | G1: 2010 | H1: 2011 | I1: 2010 | J1: 2011 | K1: Cuota 2011
A2: 147394.25 | B2: 147394.25 | C2: ='Año 2009'!B4 -> 142595.66 | D2: 138228.93 | E2: 134662.86 | F2: Prestamo Angel Luis Chalet Luanco CAJA DUERO
F3: 2104 0008 61 7034126671 PREST. GTIA. HIPOT. Construcción
F4: Proxima revision Septiembre 2010 Finaliza el 9 de Agosto 2030
A5: 98634.88 | B5: 98634.88 | C5: ='Año 2009'!B11 -> 87451.21 | D5: 54318.76 | E5: 34286.1 | F5: Prestamo Angel Luis Chalet Luanco CAJA DUERO | G5: 30000 | H5: 20000 | I5: 30000 | J5: 20000
F6: 2104 0008 60 7039621728 PREST. GTIA. HIPOT. SIN CLASIF.
F7: Años que quedan por Amortizar 11 de Marzo 2031
A8: 478300 | B8: 478300 | C8: ='Año 2009'!B19 -> 186474.01 | D8: 176741.71 | E8: 173796.86 | F8: Prestamo Angel Luis Piso Calle Vergara BANCO CASTILLA
F9: Vence el día 4-Octubre-2036
A10: 0 | B10: 0 | C10: ='Año 2009'!B24 -> 188287.32 | D10: 175972.84 | E10: 136853.38 | F10: Prestamo Micro Infor Calle Vergara BANCO CASTILLA | G10: 0 | H10: 40000 | I10: 0 | J10: 32000
F11: Años que quedan por Amortizar Vence el 13 de Agosto del 2024
A12: 15025.3 | B12: 15025.3 | C12: ='Año 2009'!B35 -> 12000 | D12: 9000 | E12: 0 | F12: Prestamo de mi Padre
A13: 123708.33 | B13: 123708.33 | C13: ='Año 2009'!B30 -> 111540.38 | D13: 59538.21 | E13: 0 | F13: Prestamo Micro Infor CAJA DUERO | G13: 50000 | H13: 59000 | I13: 28000 | J13: 14684.63
A14: 21049.95 | B14: 21049.95 | C14: ='Año 2009'!B37 -> 0 | D14: 0 | E14: 0 | F14: Prestamo Piso Calle Independencia | I14: 15000 | J14: 44669.87
A15: 1498112.7 | B15: =B2+B5+B8+B13+B10+B12+B14 -> 884112.71 | C15: =C2+C5+C8+C13+C10+C12+C14 -> 728348.58 | D15: =D2+D5+D8+D13+D10+D12+D14 -> 613800.45 | E15: =E2+E5+E8+E13+E10+E12+E14 -> 479599.2 | F15: TOTAL DEUDA | G15: =SUM(G2:G14) -> 80000 | H15: =SUM(H2:H14) -> 119000 | I15: =SUM(I2:I14) -> 73000 | J15: =SUM(J2:J14) -> 111354.5 | K15: =SUM(K2:K14) -> 0
A16: Total deuda General 2.000 | B16: Diferencia del 2000 al 2008 | C16: Diferencia del 2008 al 2009 | D16: Diferencia del 2009 al 2010 | E16: Diferencia del 2010 al 2011 | F16: DEUDA ACTUAL 2011
A17: 0 | B17: 614000 | C17: =B15-C15 -> 155764.13 | D17: =C15-D15 -> 114548.13 | E17: =D15-E15 -> 134201.25 | F17: =E15 -> 479599.2

Sheet Año 2009
C2: ACTUALIZADO A FECHA DE 30 de Diciembre de 2009 | E2: Actualizado a Fecha 26 de Febrero 2016
E3: Compra | F3: Concepto | G3: Valor estimado 2016
B4: 142595.66 | C4: Prestamo Angel Luis Chalet Luanco CAJA DUERO | E4: 500000 | F4: Chalet Luanco | G4: 400000
C5: Nº de Prestamo 2104 0008 61 7034126671 PREST. GTIA. HIPOT. Construcción | E5: 500000 | F5: Casa Principe de Vergara | G5: 500000
C6: Al 2,75% | E6: 240000 | F6: Piso Independencia | G6: 240000
C7: Proxima revision Septiembre 2010 | E7: 50000 | F7: Mercedes | G7: 71000
C8: Pago Ahora 758,97 | E8: 20000 | F8: Sang Young Andrés | G8: 0
C9: Años que quedan por Amortizar 9 de Agosto del 2030 | E9: 30000 | F9: Resto de Coches | G9: 20000
E10: 300000 | F10: Valor Empresa | G10: 500000
B11: 87451.21 | C11: Prestamo Angel Luis Chalet Luanco CAJA DUERO | E11: =SUM(E4:E10) -> 1640000 | F11: Total | G11: =SUM(G4:G10) -> 1731000
C12: Nº de Prestamo 2104 0008 60 7039621728 PREST. GTIA. HIPOT. SIN CLASIF. / Al 3,65%
C13: Proxima Revisión Abril 2010
C14: Pago Ahora 494,75
C15: Años que quedan por Amortizar 11 de Marzo 2031
C17: Prestamo Angel Luis Piso Calle Vergara BANCO CASTILLA
C18: Banco Castilla
B19: 186474.01 | C19: Al 3,25%
C20: Pago Ahora 843,23
C21: Años que quedan por Amortizar
C22: Prestamo Micro Infor Calle Vergara BANCO CASTILLA
C23: Banco Castilla
B24: 188287.32 | C24: Al 3,25%
C25: Pago Ahora 1.329,10
C26: Años que quedan por Amortizar Vence el 13 de Agosto del 2024
C27: Prestamo Micro Infor CAJA DUERO
C28: Nº de Prestamo 0008.7039621582
C29: Caja Duero
B30: 111540.38 | C30: Al 4,50
C31: Proxima revision el 11 Abril del 2010
C32: Pago Ahora 1.031,14
C33: Años que quedan por Amortizar Vence el 11 de Abril del 2021
C34: Prestamo de mi Padre
B35: 12000 | C35: Al 3,50%
B38: =SUM(B4+B11+B19+B30+B24+B35) -> 728348.58 | C38: TOTAL DEUDA

Sheet Cuadro de Amortización
B1: Prestamo Empresa Asturias | G1: Prestamo Empresa
B2: Prestado el día 31 de Enero de 2019 | G2: Prestado el día 31 de Enero de 2019
B3: Lo Ingresa Cristina sobre el día 8 de cada mes | G3: Lo Ingresa Cristina sobre el día 8 de cada mes
B4: Importe | C4: Cuotas | D4: Mes | E4: Pagada | G4: Importe | H4: Cuotas | I4: Mes | J4: Pagada
B5: 39170 | C5: IMPORTE INICIAL | G5: 49457.36 | H5: IMPORTE INICIAL
B6: =B5-C6 -> 35670 | C6: 3500 | D6: Febrero | E6: OK | G6: =G5-H6 -> 46957.36 | H6: 2500 | I6: Febrero | J6: OK
B7: =B6-C6 -> 32170 | C7: 3500 | D7: Marzo | E7: OK | G7: =G6-H6 -> 44457.36 | H7: 2500 | I7: Marzo | J7: OK
B8: =B7-C7 -> 28670 | C8: 3500 | D8: Abril | E8: OK | G8: =G7-H7 -> 41957.36 | H8: 2500 | I8: Abril | J8: OK
B9: =B8-C8 -> 25170 | C9: 3500 | D9: Mayo | E9: OK | G9: =G8-H8 -> 39457.36 | H9: 2500 | I9: Mayo | J9: OK
B10: =B9-C9 -> 21670 | C10: 3500 | D10: Junio | E10: OK | G10: =G9-H9 -> 36957.36 | H10: 2500 | I10: Junio | J10: OK
B11: =B10-C10 -> 18170 | C11: 3500 | D11: Julio | E11: OK | G11: =G10-H10 -> 34457.36 | H11: 2500 | I11: Julio | J11: OK
B12: =B11-C11 -> 14670 | C12: 3500 | D12: Agosto | E12: OK | G12: =G11-H11 -> 31957.36 | H12: 2500 | I12: Agosto | J12: OK
B13: =B12-C12 -> 11170 | C13: 3500 | D13: Septiembre | E13: OK | G13: =G12-H12 -> 29457.36 | H13: 2500 | I13: Septiembre | J13: OK
B14: =B13-C13 -> 7670 | C14: 3500 | D14: Octubre | E14: OK | G14: =G13-H13 -> 26957.36 | H14: 2500 | I14: Octubre | J14: OK
B15: =B14-C14 -> 4170 | C15: 3500 | D15: Noviembre | E15: OK | G15: =G14-H14 -> 24457.36 | H15: 2500 | I15: Noviembre | J15: OK
B16: =B15-C15 -> 670 | C16: 4170 | D16: Diciembre | E16: OK | G16: =G15-H15 -> 21957.36 | H16: 2500 | I16: Diciembre | J16: OK
B17: PAGADO (FINALIZADO) | G17: =G16-H16 -> 19457.36 | H17: 2500 | I17: Enero | J17: OK
G18: =G17-H17 -> 16957.36 | H18: 2500 | I18: Febrero | J18: OK
G19: =G18-H18 -> 14457.36 | H19: 2500 | I19: Marzo | J19: OK
G20: =G19-H19 -> 11957.36 | H20: 2500 | I20: Abril | J20: OK
G21: =G20-H20 -> 9457.36 | H21: 2500 | I21: Mayo | J21: OK
G22: =G21-H21 -> 6957.36 | H22: 2500 | I22: Junio | J22: OK
G23: =G22-H22 -> 4457.36 | H23: 2500 | I23: Julio | J23: OK
G24: 4457.38 | H24: 4457.36 | I24: Agosto | J24: OK
G25: PAGADO (FINALIZADO)

Sheet Intereses de mi Padre (3)
B2: Prestamo del día 21 de Noviembre del 2014 | E2: Intereses al 2,5%
E3: Intereses Trimestrales | F3: Intereses Semestrales
B4: Capital Dejado | E4: =F6*3 -> 187.5 | F4: =E4*2 -> 375
E5: Intereses Anuales | F5: Intereses Mensuales
B6: 30000 | E6: =B6*2.5% -> 750 | F6: =E6/12 -> 62.5
B7: Fecha de Pago | C7: Intereses | D7: Anticipo | E7: Total Pagado | F7: Liquidación Del Al

Sheet Intereses de mi Padre (2)
B2: Prestamo del día 27 de Noviembre del 2013 | E2: Intereses al 2,5%
E3: Intereses Trimestrales | F3: Intereses Semestrales
B4: Capital Dejado | E4: =F6*3 -> 125 | F4: =E4*2 -> 250
E5: Intereses Anuales | F5: Intereses Mensuales
B6: 20000 | E6: =B6*2.5% -> 500 | F6: =E6/12 -> 41.666667
B7: Fecha de Pago | C7: Intereses | D7: Anticipo | E7: Total Pagado | F7: Liquidación Del Al
B8: 40235 | C8: 150 | D8: 2000 | E8: 2125 | F8: 27/11/2013 al 27/02/2014
B9: Prestamo del día 27 de Febrero del 2014 | E9: Intereses al 2,5%
E10: Intereses Trimestrales | F10: Intereses Semestrales
B11: Capital Dejado | E11: =F13*3 -> 112.5 | F11: =E11*2 -> 225
E12: Intereses Anuales | F12: Intereses Mensuales
B13: 18000 | E13: =B13*2.5% -> 450 | F13: =E13/12 -> 37.5

Sheet Intereses de mi Padre
C2: Nuevo convenio echo el día 3 de Noviembre del 2007 | D2: Se lo estaba pagando al 3,5% y quedamos de acuerdo en subirlo al 5%
C4: Capital Dejado | D4: Intereses Anuales | E4: Intereses Mensuales | F4: Intereses Trimestrales | G4: Intereses Semestrales
B5: AL 5% | C5: 2500000 | D5: =C5*5% -> 125000 | E5: =D5/12 -> 10416.667 | F5: =D5/4 -> 31250 | G5: =D5/2 -> 62500
B6: AL 5% en € | C6: =C5/166.386 -> 15025.303 | D6: =D5/166.386 -> 751.26513 | E6: =E5/166.386 -> 62.605428 | F6: =F5/166.386 -> 187.81628 | G6: =G5/166.386 -> 375.63257
B8: Liquidación de Interes | C8: 03 de Noviembre del 2007 | D8: 368 | E8: Pagado
C9: 03 de Mayo del 2008 | D9: 525.88559 | E9: Pagado
C10: 04 de Junio Pagado 6.000 € | D10: 6000 | E10: Pagado
C11: 04 de mayo Junio 87,64 € de Intereses | D11: 87.64 | E11: Pagado
C12: 03 de Diciembre del 2008 | D12: 375.63 | E12: Pagado
C13: 03 de Junio del 2009 | D13: 375.63 | E13: Pagado
C14: Adelanto de pago de cancelación de deuda en Julio 2009 | D14: 3025.3 | E14: Pagado
C15: Capital Dejado | D15: Intereses Anuales | E15: Intereses Mensuales | F15: Intereses Trimestrales | G15: Intereses Semestrales
B16: AL 3,5% | C16: 1996632 | D16: =C16*3.5% -> 69882.12 | E16: =D16/12 -> 5823.51 | F16: =D16/4 -> 17470.53 | G16: =D16/2 -> 34941.06
B17: AL 3,5% en € | C17: =C16/166.386 -> 12000 | D17: =D16/166.386 -> 420 | E17: =E16/166.386 -> 35 | F17: =F16/166.386 -> 105 | G17: =G16/166.386 -> 210
C19: 03 de Diciembre del 2009 | D19: 210 | E19: Pagado 6 de Enero
C20: 03 de Junio del 2010 | D20: 210 | E20: Pagado 18 de Junio
C21: Liquidación de Intereses de Junio y Julio | D21: 70 | E21: Pagado el 1 de Agosto 2010
C22: Adelanto el 1 de Agosto | D22: 3000 | E22: Pagado el 1 de Agosto 2010
C23: Capital Dejado | D23: Intereses Anuales | E23: Intereses Mensuales | F23: Intereses Trimestrales | G23: Intereses Semestrales
B24: AL 3,5% | C24: 1497474 | D24: =C24*3.5% -> 52411.59 | E24: =D24/12 -> 4367.6325 | F24: =D24/4 -> 13102.898 | G24: =D24/2 -> 26205.795
B25: AL 3,5% en € | C25: 9000 | D25: =D24/166.386 -> 315 | E25: =E24/166.386 -> 26.25 | F25: =F24/166.386 -> 78.75 | G25: =G24/166.386 -> 157.5
C26: Proximo Pago 1 de Febrero 2011 | D26: 157.5
C27: Proximo Pago 1 de Agosto 2011 (Cancelado) | D27: 157.5
C28: Adelanto de pago cancelación de deuda Enero 2011 (3.000€ + Intereses) | D28: 3157.5 | E28: Pagado el 3 de Enero 2011
C29: Capital Dejado | D29: Intereses Anuales | E29: Intereses Mensuales | F29: Intereses Trimestrales | G29: Intereses Semestrales
B30: AL 3,5% | C30: 998316 | D30: =C30*3.5% -> 34941.06 | E30: =D30/12 -> 2911.755 | F30: =D30/4 -> 8735.265 | G30: =D30/2 -> 17470.53
B31: AL 3,5% en € | C31: 6000 | D31: =D30/166.386 -> 210 | E31: =E30/166.386 -> 17.5 | F31: =F30/166.386 -> 52.5 | G31: =G30/166.386 -> 105
C32: Proximo Pago 1 de Agosto 2011 | D32: 105
C33: Proximo Pago 1 de Febrero 2012 | D33: 105
C34: Total Liquidación hasta el 1 de julio del 2011 | D34: 4087.5
C35: Capital Dejado | D35: Intereses Anuales | E35: Intereses Mensuales | F35: Intereses Trimestrales | G35: Intereses Semestrales
B36: AL 3,5% | C36: 332772 | D36: =C36*3.5% -> 11647.02 | E36: =D36/12 -> 970.585 | F36: =D36/4 -> 2911.755 | G36: =D36/2 -> 5823.51
B37: AL 3,5% en € | C37: 2000 | D37: =D36/166.386 -> 70 | E37: =E36/166.386 -> 5.8333333 | F37: =F36/166.386 -> 17.5 | G37: =G36/166.386 -> 35
C38: Proximo Pago 1 de Enero 2012 | D38: 35
C39: Total Liquidación el día 25 de Julio 2011 | D39: 2.005 Euros | E39: FIN DEUDA
